Workbook

Sheet Cover
B3: 46174
B4: Carlos Arizcuren Elizondo
B7: Table of Contents
B8: Drivers and Assumptions
B9: 3-Statement Financial Analysis
B10: Debt scheudle chart
B11: Weighted Average Cost of Capital
B12: DCF - Exit multiple and Perpetual Growth
B13: Dividend Discount Model
B14: Sensitivity Charts
B15: Football Field
B16: Ratios
B18: Legend
... B26: This document has been done exclusively for personal use, and without Coca-Cola's supervision. May contain errors.

Sheet Drivers
C1: 2021 | D1: 2022 | E1: 2023 | F1: 2024 | G1: 2025 | H1: 2026 | I1: 2027 | J1: 2028 | K1: 2029 | L1: 2030 | M1: 2031 | N1: 2032 | O1: 2033 | P1: 2034 | Q1: 2035
B3: Revenue Drivers
B5: Base Case | S5: 2
B6: Growth by segments | H6: =+MODL!D34/100 -> 0.047258264 | I6: =+MODL!E34/100 -> 0.046633719 | J6: =+MODL!F34/100 -> 0.046689495 | K6: =+MODL!G34/100 -> 0.042408925 | L6: =+MODL!H34/100 -> 0.044995557 | M6: =+MODL!I34/100 -> 0.045092981 | N6: =+MODL!J34/100 -> 0.048022752 | O6: =+MODL!K34/100 -> 0.04281989 | ... Q6: =+MODL!M34/100 -> 0.045510235 | S6: Upside | T6: 1
B7: EMEA | H7: =+MODL!D35/100 -> 0.05795102 | I7: =+MODL!E35/100 -> 0.045261133 | J7: =+MODL!F35/100 -> 0.045518364 | K7: =+MODL!G35/100 -> 0.037190631 | L7: =+MODL!H35/100 -> 0.039820309 | M7: =+MODL!I35/100 -> 0.039818125 | N7: =+MODL!J35/100 -> 0.043566416 | O7: =+MODL!K35/100 -> 0.037197778 | ... Q7: =+MODL!M35/100 -> 0.039822394 | S7: Base | T7: 2
B8: Latin America | H8: =+MODL!D36/100 -> 0.045139482 | I8: =+MODL!E36/100 -> 0.065433257 | J8: =+MODL!F36/100 -> 0.065 | K8: =+MODL!G36/100 -> 0.065 | L8: =+MODL!H36/100 -> 0.065 | M8: =+MODL!I36/100 -> 0.065 | N8: =+MODL!J36/100 -> 0.065 | O8: =+MODL!K36/100 -> 0.065 | ... Q8: =+MODL!M36/100 -> 0.065 | S8: Downside | T8: 3
B9: North America | H9: =+MODL!D37/100 -> 0.051145989 | I9: =+MODL!E37/100 -> 0.042054848 | J9: =+MODL!F37/100 -> 0.043643297 | K9: =+MODL!G37/100 -> 0.04255804 | L9: =+MODL!H37/100 -> 0.043816365 | M9: =+MODL!I37/100 -> 0.043815331 | N9: =+MODL!J37/100 -> 0.044692868 | O9: =+MODL!K37/100 -> 0.042560639 | ... Q9: =+MODL!M37/100 -> 0.043817359
B10: Asia Pacific | H10: =+MODL!D38/100 -> 0.016135375 | I10: =+MODL!E38/100 -> 0.040113099 | J10: =+MODL!F38/100 -> 0.046312062 | K10: =+MODL!G38/100 -> 0.051487102 | L10: =+MODL!H38/100 -> 0.054339401 | M10: =+MODL!I38/100 -> 0.054336071 | N10: =+MODL!J38/100 -> 0.061215387 | O10: =+MODL!K38/100 -> 0.051500027 | ... Q10: =+MODL!M38/100 -> 0.054342565
B12: Upside Case (+0.5%) | C12: 0.005
B13: EMEA | H13: =+H7+$C$12 -> 0.06295102 | I13: =+I7+$C$12 -> 0.050261133 | J13: =+J7+$C$12 -> 0.050518364 | K13: =+K7+$C$12 -> 0.042190631 | L13: =+L7+$C$12 -> 0.044820309 | M13: =+M7+$C$12 -> 0.044818125 | N13: =+N7+$C$12 -> 0.048566416 | O13: =+O7+$C$12 -> 0.042197778 | ... Q13: =+Q7+$C$12 -> 0.044822394
B14: Latin America | H14: =+H8+$C$12 -> 0.050139482 | I14: =+I8+$C$12 -> 0.070433257 | J14: =+J8+$C$12 -> 0.07 | K14: =+K8+$C$12 -> 0.07 | L14: =+L8+$C$12 -> 0.07 | M14: =+M8+$C$12 -> 0.07 | N14: =+N8+$C$12 -> 0.07 | O14: =+O8+$C$12 -> 0.07 | ... Q14: =+Q8+$C$12 -> 0.07
B15: North America | H15: =+H9+$C$12 -> 0.056145989 | I15: =+I9+$C$12 -> 0.047054848 | J15: =+J9+$C$12 -> 0.048643297 | K15: =+K9+$C$12 -> 0.04755804 | L15: =+L9+$C$12 -> 0.048816365 | M15: =+M9+$C$12 -> 0.048815331 | N15: =+N9+$C$12 -> 0.049692868 | O15: =+O9+$C$12 -> 0.047560639 | ... Q15: =+Q9+$C$12 -> 0.048817359
B16: Asia Pacific | H16: =+H10+$C$12 -> 0.021135375 | I16: =+I10+$C$12 -> 0.045113099 | J16: =+J10+$C$12 -> 0.051312062 | K16: =+K10+$C$12 -> 0.056487102 | L16: =+L10+$C$12 -> 0.059339401 | M16: =+M10+$C$12 -> 0.059336071 | N16: =+N10+$C$12 -> 0.066215387 | O16: =+O10+$C$12 -> 0.056500027 | ... Q16: =+Q10+$C$12 -> 0.059342565
B18: Downside Case (-0.5%) | C18: 0.005
B19: EMEA | H19: =+H7-$C$18 -> 0.05295102 | I19: =+I7-$C$18 -> 0.040261133 | J19: =+J7-$C$18 -> 0.040518364 | K19: =+K7-$C$18 -> 0.032190631 | L19: =+L7-$C$18 -> 0.034820309 | M19: =+M7-$C$18 -> 0.034818125 | N19: =+N7-$C$18 -> 0.038566416 | O19: =+O7-$C$18 -> 0.032197778 | ... Q19: =+Q7-$C$18 -> 0.034822394
B20: Latin America | H20: =+H8-$C$18 -> 0.040139482 | I20: =+I8-$C$18 -> 0.060433257 | J20: =+J8-$C$18 -> 0.06 | K20: =+K8-$C$18 -> 0.06 | L20: =+L8-$C$18 -> 0.06 | M20: =+M8-$C$18 -> 0.06 | N20: =+N8-$C$18 -> 0.06 | O20: =+O8-$C$18 -> 0.06 | ... Q20: =+Q8-$C$18 -> 0.06
B21: North America | H21: =+H9-$C$18 -> 0.046145989 | I21: =+I9-$C$18 -> 0.037054848 | J21: =+J9-$C$18 -> 0.038643297 | K21: =+K9-$C$18 -> 0.03755804 | L21: =+L9-$C$18 -> 0.038816365 | M21: =+M9-$C$18 -> 0.038815331 | N21: =+N9-$C$18 -> 0.039692868 | O21: =+O9-$C$18 -> 0.037560639 | ... Q21: =+Q9-$C$18 -> 0.038817359
B22: Asia Pacific | H22: =+H10-$C$18 -> 0.011135375 | I22: =+I10-$C$18 -> 0.035113099 | J22: =+J10-$C$18 -> 0.041312062 | K22: =+K10-$C$18 -> 0.046487102 | L22: =+L10-$C$18 -> 0.049339401 | M22: =+M10-$C$18 -> 0.049336071 | N22: =+N10-$C$18 -> 0.056215387 | O22: =+O10-$C$18 -> 0.046500027 | ... Q22: =+Q10-$C$18 -> 0.049342565
B24: Active Case
B25: EMEA | H25: =+CHOOSE($S$5, H13, H7, H19) -> 0.05795102 | I25: =+CHOOSE($S$5, I13, I7, I19) -> 0.045261133 | J25: =+CHOOSE($S$5, J13, J7, J19) -> 0.045518364 | K25: =+CHOOSE($S$5, K13, K7, K19) -> 0.037190631 | L25: =+CHOOSE($S$5, L13, L7, L19) -> 0.039820309 | M25: =+CHOOSE($S$5, M13, M7, M19) -> 0.039818125 | N25: =+CHOOSE($S$5, N13, N7, N19) -> 0.043566416 | O25: =+CHOOSE($S$5, O13, O7, O19) -> 0.037197778 | ... Q25: =+CHOOSE($S$5, Q13, Q7, Q19) -> 0.039822394
B26: Latin America | H26: =+CHOOSE($S$5, H14, H8, H20) -> 0.045139482 | I26: =+CHOOSE($S$5, I14, I8, I20) -> 0.065433257 | J26: =+CHOOSE($S$5, J14, J8, J20) -> 0.065 | K26: =+CHOOSE($S$5, K14, K8, K20) -> 0.065 | L26: =+CHOOSE($S$5, L14, L8, L20) -> 0.065 | M26: =+CHOOSE($S$5, M14, M8, M20) -> 0.065 | N26: =+CHOOSE($S$5, N14, N8, N20) -> 0.065 | O26: =+CHOOSE($S$5, O14, O8, O20) -> 0.065 | ... Q26: =+CHOOSE($S$5, Q14, Q8, Q20) -> 0.065
B27: North America | H27: =+CHOOSE($S$5, H15, H9, H21) -> 0.051145989 | I27: =+CHOOSE($S$5, I15, I9, I21) -> 0.042054848 | J27: =+CHOOSE($S$5, J15, J9, J21) -> 0.043643297 | K27: =+CHOOSE($S$5, K15, K9, K21) -> 0.04255804 | L27: =+CHOOSE($S$5, L15, L9, L21) -> 0.043816365 | M27: =+CHOOSE($S$5, M15, M9, M21) -> 0.043815331 | N27: =+CHOOSE($S$5, N15, N9, N21) -> 0.044692868 | O27: =+CHOOSE($S$5, O15, O9, O21) -> 0.042560639 | ... Q27: =+CHOOSE($S$5, Q15, Q9, Q21) -> 0.043817359
B28: Asia Pacific | H28: =+CHOOSE($S$5, H16, H10, H22) -> 0.016135375 | I28: =+CHOOSE($S$5, I16, I10, I22) -> 0.040113099 | J28: =+CHOOSE($S$5, J16, J10, J22) -> 0.046312062 | K28: =+CHOOSE($S$5, K16, K10, K22) -> 0.051487102 | L28: =+CHOOSE($S$5, L16, L10, L22) -> 0.054339401 | M28: =+CHOOSE($S$5, M16, M10, M22) -> 0.054336071 | N28: =+CHOOSE($S$5, N16, N10, N22) -> 0.061215387 | O28: =+CHOOSE($S$5, O16, O10, O22) -> 0.051500027 | ... Q28: =+CHOOSE($S$5, Q16, Q10, Q22) -> 0.054342565
B31: Cost Drivers
B33: Gross Profit (Margin %) | C33: =+CR!C10/CR!C6 -> 0.60137617 | D33: =+CR!D10/CR!D6 -> 0.57759141 | E33: =+CR!E10/CR!E6 -> 0.59669317 | F33: =+CR!F10/CR!F6 -> 0.61076401 | G33: =+CR!G10/CR!G6 -> 0.61994923
B34: Upside | C34: 0.002 | H34: =+H35+C34 -> 0.6032748 | I34: =+H34+$C$34 -> 0.6052748 | J34: =+I34+$C$34 -> 0.6072748 | K34: =+J34+$C$34 -> 0.6092748 | L34: =+K34+$C$34 -> 0.6112748 | M34: =+L34+$C$34 -> 0.6132748 | N34: =+M34+$C$34 -> 0.6152748 | O34: =+N34+$C$34 -> 0.6172748 | P34: =+O34+$C$34 -> 0.6192748 | Q34: =+P34+$C$34 -> 0.6212748
B35: Base | C35: 0 | H35: =+AVERAGE($C$33:$G$33)+C35 -> 0.6012748 | I35: =+H35+$C$35 -> 0.6012748 | J35: =+I35+$C$35 -> 0.6012748 | K35: =+J35+$C$35 -> 0.6012748 | L35: =+K35+$C$35 -> 0.6012748 | M35: =+L35+$C$35 -> 0.6012748 | N35: =+M35+$C$35 -> 0.6012748 | O35: =+N35+$C$35 -> 0.6012748 | P35: =+O35+$C$35 -> 0.6012748 | Q35: =+P35+$C$35 -> 0.6012748
B36: Downside | C36: 0.001 | H36: =+H35-C36 -> 0.6002748 | I36: =+H36-$C$36 -> 0.5992748 | J36: =+I36-$C$36 -> 0.5982748 | K36: =+J36-$C$36 -> 0.5972748 | L36: =+K36-$C$36 -> 0.5962748 | M36: =+L36-$C$36 -> 0.5952748 | N36: =+M36-$C$36 -> 0.5942748 | O36: =+N36-$C$36 -> 0.5932748 | P36: =+O36-$C$36 -> 0.5922748 | Q36: =+P36-$C$36 -> 0.5912748
B37: Active | H37: =+CHOOSE($S$5, H34,H35,H36) -> 0.6012748 | I37: =+CHOOSE($S$5, I34,I35,I36) -> 0.6012748 | J37: =+CHOOSE($S$5, J34,J35,J36) -> 0.6012748 | K37: =+CHOOSE($S$5, K34,K35,K36) -> 0.6012748 | L37: =+CHOOSE($S$5, L34,L35,L36) -> 0.6012748 | M37: =+CHOOSE($S$5, M34,M35,M36) -> 0.6012748 | N37: =+CHOOSE($S$5, N34,N35,N36) -> 0.6012748 | O37: =+CHOOSE($S$5, O34,O35,O36) -> 0.6012748 | ... Q37: =+CHOOSE($S$5, Q34,Q35,Q36) -> 0.6012748
B40: SG&A to Sales % | H40: =+MODL!D179/100 -> 0.29422757 | I40: =+MODL!E179/100 -> 0.28611606 | J40: =+MODL!F179/100 -> 0.28348516 | K40: =+MODL!G179/100 -> 0.28032817 | L40: =+MODL!H179/100 -> 0.27532817 | M40: =+MODL!I179/100 -> 0.27032817 | N40: =+MODL!J179/100 -> 0.26532817 | O40: =+MODL!K179/100 -> 0.26032817 | ... Q40: =+MODL!M179/100 -> 0.25032817
B41: Upside | C41: 0.01 | H41: =+H40-$C$41 -> 0.28422757 | I41: =+I40-$C$41 -> 0.27611606 | J41: =+J40-$C$41 -> 0.27348516 | K41: =+K40-$C$41 -> 0.27032817 | L41: =+L40-$C$41 -> 0.26532817 | M41: =+M40-$C$41 -> 0.26032817 | N41: =+N40-$C$41 -> 0.25532817 | O41: =+O40-$C$41 -> 0.25032817 | ... Q41: =+Q40-$C$41 -> 0.24032817
B42: Base | C42: 0 | H42: =+H40+$C$42 -> 0.29422757 | I42: =+I40+$C$42 -> 0.28611606 | J42: =+J40+$C$42 -> 0.28348516 | K42: =+K40+$C$42 -> 0.28032817 | L42: =+L40+$C$42 -> 0.27532817 | M42: =+M40+$C$42 -> 0.27032817 | N42: =+N40+$C$42 -> 0.26532817 | O42: =+O40+$C$42 -> 0.26032817 | ... Q42: =+Q40+$C$42 -> 0.25032817
B43: Downside | C43: 0.01 | H43: =+H40+$C$43 -> 0.30422757 | I43: =+I40+$C$43 -> 0.29611606 | J43: =+J40+$C$43 -> 0.29348516 | K43: =+K40+$C$43 -> 0.29032817 | L43: =+L40+$C$43 -> 0.28532817 | M43: =+M40+$C$43 -> 0.28032817 | N43: =+N40+$C$43 -> 0.27532817 | O43: =+O40+$C$43 -> 0.27032817 | ... Q43: =+Q40+$C$43 -> 0.26032817
B44: Active | H44: =+CHOOSE($S$5,H41,H42,H43) -> 0.29422757 | I44: =+CHOOSE($S$5,I41,I42,I43) -> 0.28611606 | J44: =+CHOOSE($S$5,J41,J42,J43) -> 0.28348516 | K44: =+CHOOSE($S$5,K41,K42,K43) -> 0.28032817 | L44: =+CHOOSE($S$5,L41,L42,L43) -> 0.27532817 | M44: =+CHOOSE($S$5,M41,M42,M43) -> 0.27032817 | N44: =+CHOOSE($S$5,N41,N42,N43) -> 0.26532817 | O44: =+CHOOSE($S$5,O41,O42,O43) -> 0.26032817 | ... Q44: =+CHOOSE($S$5,Q41,Q42,Q43) -> 0.25032817
B47: D&A to Sales % | H47: =+MODL!D185/100 -> 0.023246103 | I47: =+MODL!E185/100 -> 0.025008073 | J47: =+MODL!F185/100 -> 0.025088868 | K47: =+MODL!G185/100 -> 0.028431599 | L47: =+MODL!H185/100 -> 0.028764932 | M47: =+MODL!I185/100 -> 0.028764932 | N47: =+MODL!J185/100 -> 0.028764932 | O47: =+MODL!K185/100 -> 0.028764932 | ... Q47: =+MODL!M185/100 -> 0.028764932
B48: Upside | C48: 0.003 | H48: =+H47-$C$48 -> 0.020246103 | I48: =+I47-$C$48 -> 0.022008073 | J48: =+J47-$C$48 -> 0.022088868 | K48: =+K47-$C$48 -> 0.025431599 | L48: =+L47-$C$48 -> 0.025764932 | M48: =+M47-$C$48 -> 0.025764932 | N48: =+N47-$C$48 -> 0.025764932 | O48: =+O47-$C$48 -> 0.025764932 | ... Q48: =+Q47-$C$48 -> 0.025764932
B49: Base | C49: 0 | H49: =+H47+$C$49 -> 0.023246103 | I49: =+I47+$C$49 -> 0.025008073 | J49: =+J47+$C$49 -> 0.025088868 | K49: =+K47+$C$49 -> 0.028431599 | L49: =+L47+$C$49 -> 0.028764932 | M49: =+M47+$C$49 -> 0.028764932 | N49: =+N47+$C$49 -> 0.028764932 | O49: =+O47+$C$49 -> 0.028764932 | ... Q49: =+Q47+$C$49 -> 0.028764932
B50: Downside | C50: 0.003 | H50: =+H47+$C$50 -> 0.026246103 | I50: =+I47+$C$50 -> 0.028008073 | J50: =+J47+$C$50 -> 0.028088868 | K50: =+K47+$C$50 -> 0.031431599 | L50: =+L47+$C$50 -> 0.031764932 | M50: =+M47+$C$50 -> 0.031764932 | N50: =+N47+$C$50 -> 0.031764932 | O50: =+O47+$C$50 -> 0.031764932 | ... Q50: =+Q47+$C$50 -> 0.031764932
B51: Active | H51: =+CHOOSE($S$5,H48,H49,H50) -> 0.023246103 | I51: =+CHOOSE($S$5,I48,I49,I50) -> 0.025008073 | J51: =+CHOOSE($S$5,J48,J49,J50) -> 0.025088868 | K51: =+CHOOSE($S$5,K48,K49,K50) -> 0.028431599 | L51: =+CHOOSE($S$5,L48,L49,L50) -> 0.028764932 | M51: =+CHOOSE($S$5,M48,M49,M50) -> 0.028764932 | N51: =+CHOOSE($S$5,N48,N49,N50) -> 0.028764932 | O51: =+CHOOSE($S$5,O48,O49,O50) -> 0.028764932 | ... Q51: =+CHOOSE($S$5,Q48,Q49,Q50) -> 0.028764932
B54: Mergers and Acquisitions | C54: =+CR!C26 -> -1173 | D54: =+CR!D26 -> 408 | E54: =+CR!E26 -> 836 | F54: =+CR!F26 -> 1377 | G54: =+CR!G26 -> -654
B55: Upside | C55: 250 | H55: =+H56-$C$55 -> -91.2 | I55: =+I56-$C$55 -> -91.2 | J55: =+J56-$C$55 -> -91.2 | K55: =+K56-$C$55 -> -91.2 | L55: =+L56-$C$55 -> -91.2 | M55: =+M56-$C$55 -> -91.2 | N55: =+N56-$C$55 -> -91.2 | O55: =+O56-$C$55 -> -91.2 | ... Q55: =+Q56-$C$55 -> -91.2
B56: Base | C56: 0 | H56: =+AVERAGE($C$54:$G$54) -> 158.8 | I56: =+AVERAGE($C$54:$G$54) -> 158.8 | J56: =+AVERAGE($C$54:$G$54) -> 158.8 | K56: =+AVERAGE($C$54:$G$54) -> 158.8 | L56: =+AVERAGE($C$54:$G$54) -> 158.8 | M56: =+AVERAGE($C$54:$G$54) -> 158.8 | N56: =+AVERAGE($C$54:$G$54) -> 158.8 | O56: =+AVERAGE($C$54:$G$54) -> 158.8 | ... Q56: =+AVERAGE($C$54:$G$54) -> 158.8
B57: Downside | C57: 250 | H57: =+H56+$C$57 -> 408.8 | I57: =+I56+$C$57 -> 408.8 | J57: =+J56+$C$57 -> 408.8 | K57: =+K56+$C$57 -> 408.8 | L57: =+L56+$C$57 -> 408.8 | M57: =+M56+$C$57 -> 408.8 | N57: =+N56+$C$57 -> 408.8 | O57: =+O56+$C$57 -> 408.8 | ... Q57: =+Q56+$C$57 -> 408.8
B58: Active | H58: =+CHOOSE($S$5,H55,H56,H57) -> 158.8 | I58: =+CHOOSE($S$5,I55,I56,I57) -> 158.8 | J58: =+CHOOSE($S$5,J55,J56,J57) -> 158.8 | K58: =+CHOOSE($S$5,K55,K56,K57) -> 158.8 | L58: =+CHOOSE($S$5,L55,L56,L57) -> 158.8 | M58: =+CHOOSE($S$5,M55,M56,M57) -> 158.8 | N58: =+CHOOSE($S$5,N55,N56,N57) -> 158.8 | O58: =+CHOOSE($S$5,O55,O56,O57) -> 158.8 | ... Q58: =+CHOOSE($S$5,Q55,Q56,Q57) -> 158.8
B61: Restructuring | C61: =+CR!C28 -> 378 | D61: =+CR!D28 -> 117 | E61: =+CR!E28 -> 191 | F61: =+CR!F28 -> 133 | G61: =+CR!G28 -> 97 | H61: =+AVERAGE($D$61:$G$61) -> 134.5 | I61: =+AVERAGE($D$61:$G$61) -> 134.5 | J61: =+AVERAGE($D$61:$G$61) -> 134.5 | K61: =+AVERAGE($D$61:$G$61) -> 134.5 | L61: =+AVERAGE($D$61:$G$61) -> 134.5 | M61: =+AVERAGE($D$61:$G$61) -> 134.5 | N61: =+AVERAGE($D$61:$G$61) -> 134.5 | O61: =+AVERAGE($D$61:$G$61) -> 134.5 | ... Q61: =+AVERAGE($D$61:$G$61) -> 134.5
B64: Tax Rate | C64: =+CR!C32/CR!C31 -> 0.21094567 | D64: =+CR!D32/CR!D31 -> 0.18098579 | E64: =+CR!E32/CR!E31 -> 0.17364114 | F64: =+CR!F32/CR!F31 -> 0.18622956 | G64: =+CR!G32/CR!G31 -> 0.17883485
B65: Upside | C65: 0.01 | H65: =+H66-$C$65 -> 0.1761274 | I65: =+I66-$C$65 -> 0.1761274 | J65: =+J66-$C$65 -> 0.1761274 | K65: =+K66-$C$65 -> 0.1761274 | L65: =+L66-$C$65 -> 0.1761274 | M65: =+M66-$C$65 -> 0.1761274 | N65: =+N66-$C$65 -> 0.1761274 | O65: =+O66-$C$65 -> 0.1761274 | ... Q65: =+Q66-$C$65 -> 0.1761274
B66: Base | C66: 0 | H66: =+AVERAGE($C$64:$G$64)+$C$66 -> 0.1861274 | I66: =+AVERAGE($C$64:$G$64)+$C$66 -> 0.1861274 | J66: =+AVERAGE($C$64:$G$64)+$C$66 -> 0.1861274 | K66: =+AVERAGE($C$64:$G$64)+$C$66 -> 0.1861274 | L66: =+AVERAGE($C$64:$G$64)+$C$66 -> 0.1861274 | M66: =+AVERAGE($C$64:$G$64)+$C$66 -> 0.1861274 | N66: =+AVERAGE($C$64:$G$64)+$C$66 -> 0.1861274 | O66: =+AVERAGE($C$64:$G$64)+$C$66 -> 0.1861274 | ... Q66: =+AVERAGE($C$64:$G$64)+$C$66 -> 0.1861274
B67: Downside | C67: 0.01 | H67: =+H66+$C$67 -> 0.1961274 | I67: =+I66+$C$67 -> 0.1961274 | J67: =+J66+$C$67 -> 0.1961274 | K67: =+K66+$C$67 -> 0.1961274 | L67: =+L66+$C$67 -> 0.1961274 | M67: =+M66+$C$67 -> 0.1961274 | N67: =+N66+$C$67 -> 0.1961274 | O67: =+O66+$C$67 -> 0.1961274 | ... Q67: =+Q66+$C$67 -> 0.1961274
B68: Active | H68: =+CHOOSE($S$5, H65, H66, H67) -> 0.1861274 | I68: =+CHOOSE($S$5, I65, I66, I67) -> 0.1861274 | J68: =+CHOOSE($S$5, J65, J66, J67) -> 0.1861274 | K68: =+CHOOSE($S$5, K65, K66, K67) -> 0.1861274 | L68: =+CHOOSE($S$5, L65, L66, L67) -> 0.1861274 | M68: =+CHOOSE($S$5, M65, M66, M67) -> 0.1861274 | N68: =+CHOOSE($S$5, N65, N66, N67) -> 0.1861274 | O68: =+CHOOSE($S$5, O65, O66, O67) -> 0.1861274 | ... Q68: =+CHOOSE($S$5, Q65, Q66, Q67) -> 0.1861274
B72: Structure Drivers
B74: Days Sales Outstanding (DSO) | C74: =+'Balance Sheet'!C10/CR!C6*365 -> 33.159501 | D74: =+'Balance Sheet'!D10/CR!D6*365 -> 29.567323 | E74: =+'Balance Sheet'!E10/CR!E6*365 -> 27.185261 | F74: =+'Balance Sheet'!F10/CR!F6*365 -> 27.777576 | G74: =+'Balance Sheet'!G10/CR!G6*365 -> 23.071657 | S74: DSO Scenario
B75: Upside | C75: 0.1 | H75: =+H76*(1-$C$75) -> 25.337038 | I75: =+I76*(1-$C$75) -> 25.337038 | J75: =+J76*(1-$C$75) -> 25.337038 | K75: =+K76*(1-$C$75) -> 25.337038 | L75: =+L76*(1-$C$75) -> 25.337038 | M75: =+M76*(1-$C$75) -> 25.337038 | N75: =+N76*(1-$C$75) -> 25.337038 | O75: =+O76*(1-$C$75) -> 25.337038 | ... Q75: =+Q76*(1-$C$75) -> 25.337038 | S75: Upside | T75: 1
B76: Base | C76: 0 | H76: =+AVERAGE($C$74:$G$74)*(1+$C$76) -> 28.152264 | I76: =+AVERAGE($C$74:$G$74)*(1+$C$76) -> 28.152264 | J76: =+AVERAGE($C$74:$G$74)*(1+$C$76) -> 28.152264 | K76: =+AVERAGE($C$74:$G$74)*(1+$C$76) -> 28.152264 | L76: =+AVERAGE($C$74:$G$74)*(1+$C$76) -> 28.152264 | M76: =+AVERAGE($C$74:$G$74)*(1+$C$76) -> 28.152264 | N76: =+AVERAGE($C$74:$G$74)*(1+$C$76) -> 28.152264 | O76: =+AVERAGE($C$74:$G$74)*(1+$C$76) -> 28.152264 | ... Q76: =+AVERAGE($C$74:$G$74)*(1+$C$76) -> 28.152264 | S76: Base | T76: 2
B77: Downside | C77: 0.1 | H77: =+H76*(1+$C$77) -> 30.96749 | I77: =+I76*(1+$C$77) -> 30.96749 | J77: =+J76*(1+$C$77) -> 30.96749 | K77: =+K76*(1+$C$77) -> 30.96749 | L77: =+L76*(1+$C$77) -> 30.96749 | M77: =+M76*(1+$C$77) -> 30.96749 | N77: =+N76*(1+$C$77) -> 30.96749 | O77: =+O76*(1+$C$77) -> 30.96749 | ... Q77: =+Q76*(1+$C$77) -> 30.96749 | S77: Downside | T77: 3
B78: Active | H78: =+CHOOSE($S$78,H75,H76,H77) -> 28.152264 | I78: =+CHOOSE($S$78,I75,I76,I77) -> 28.152264 | J78: =+CHOOSE($S$78,J75,J76,J77) -> 28.152264 | K78: =+CHOOSE($S$78,K75,K76,K77) -> 28.152264 | L78: =+CHOOSE($S$78,L75,L76,L77) -> 28.152264 | M78: =+CHOOSE($S$78,M75,M76,M77) -> 28.152264 | N78: =+CHOOSE($S$78,N75,N76,N77) -> 28.152264 | O78: =+CHOOSE($S$78,O75,O76,O77) -> 28.152264 | ... Q78: =+CHOOSE($S$78,Q75,Q76,Q77) -> 28.152264 | S78: 2
B80: Accounts Payable % of revenue | C80: =+'Balance Sheet'!C43/CR!C6 -> 0.11904392 | D80: =+'Balance Sheet'!D43/CR!D6 -> 0.12328672 | E80: =+'Balance Sheet'!E43/CR!E6 -> 0.12209506 | F80: =+'Balance Sheet'!F43/CR!F6 -> 0.11659594 | G80: =+'Balance Sheet'!G43/CR!G6 -> 0.11753568 | S80: AP% Scenario
B81: Upside | C81: 0.1 | H81: =+H82*(1+$C$81) -> 0.13168261 | I81: =+I82*(1+$C$81) -> 0.13168261 | J81: =+J82*(1+$C$81) -> 0.13168261 | K81: =+K82*(1+$C$81) -> 0.13168261 | L81: =+L82*(1+$C$81) -> 0.13168261 | M81: =+M82*(1+$C$81) -> 0.13168261 | N81: =+N82*(1+$C$81) -> 0.13168261 | O81: =+O82*(1+$C$81) -> 0.13168261 | ... Q81: =+Q82*(1+$C$81) -> 0.13168261 | S81: Upside | T81: 1
B82: Base | C82: 0 | H82: =+AVERAGE($C$80:$G$80)*(1+$C$82) -> 0.11971146 | I82: =+AVERAGE($C$80:$G$80)*(1+$C$82) -> 0.11971146 | J82: =+AVERAGE($C$80:$G$80)*(1+$C$82) -> 0.11971146 | K82: =+AVERAGE($C$80:$G$80)*(1+$C$82) -> 0.11971146 | L82: =+AVERAGE($C$80:$G$80)*(1+$C$82) -> 0.11971146 | M82: =+AVERAGE($C$80:$G$80)*(1+$C$82) -> 0.11971146 | N82: =+AVERAGE($C$80:$G$80)*(1+$C$82) -> 0.11971146 | O82: =+AVERAGE($C$80:$G$80)*(1+$C$82) -> 0.11971146 | ... Q82: =+AVERAGE($C$80:$G$80)*(1+$C$82) -> 0.11971146 | S82: Base | T82: 2
B83: Downside | C83: 0.1 | H83: =+H82*(1-$C$83) -> 0.10774032 | I83: =+I82*(1-$C$83) -> 0.10774032 | J83: =+J82*(1-$C$83) -> 0.10774032 | K83: =+K82*(1-$C$83) -> 0.10774032 | L83: =+L82*(1-$C$83) -> 0.10774032 | M83: =+M82*(1-$C$83) -> 0.10774032 | N83: =+N82*(1-$C$83) -> 0.10774032 | O83: =+O82*(1-$C$83) -> 0.10774032 | ... Q83: =+Q82*(1-$C$83) -> 0.10774032 | S83: Downside | T83: 3
B84: Active | H84: =+CHOOSE($S$84,H81,H82,H83) -> 0.11971146 | I84: =+CHOOSE($S$84,I81,I82,I83) -> 0.11971146 | J84: =+CHOOSE($S$84,J81,J82,J83) -> 0.11971146 | K84: =+CHOOSE($S$84,K81,K82,K83) -> 0.11971146 | L84: =+CHOOSE($S$84,L81,L82,L83) -> 0.11971146 | M84: =+CHOOSE($S$84,M81,M82,M83) -> 0.11971146 | N84: =+CHOOSE($S$84,N81,N82,N83) -> 0.11971146 | O84: =+CHOOSE($S$84,O81,O82,O83) -> 0.11971146 | ... Q84: =+CHOOSE($S$84,Q81,Q82,Q83) -> 0.11971146 | S84: 2
B86: Days Inventory Outstanding (DIO) | C86: =+'Balance Sheet'!C13/CR!C8*365 -> 80.863725 | D86: =+'Balance Sheet'!D13/CR!D8*365 -> 84.971952 | E86: =+'Balance Sheet'!E13/CR!E8*365 -> 87.44977 | F86: =+'Balance Sheet'!F13/CR!F8*365 -> 94.539279 | G86: =+'Balance Sheet'!G13/CR!G8*365 -> 88.422479 | S86: DIO Scenario
B87: Upside | C87: 0.1 | H87: =+H88*(1-$C$87) -> 78.524497 | I87: =+I88*(1-$C$87) -> 78.524497 | J87: =+J88*(1-$C$87) -> 78.524497 | K87: =+K88*(1-$C$87) -> 78.524497 | L87: =+L88*(1-$C$87) -> 78.524497 | M87: =+M88*(1-$C$87) -> 78.524497 | N87: =+N88*(1-$C$87) -> 78.524497 | O87: =+O88*(1-$C$87) -> 78.524497 | ... Q87: =+Q88*(1-$C$87) -> 78.524497 | S87: Upside | T87: 1
B88: Base | C88: 0 | H88: =+AVERAGE($C$86:$G$86)*(1+$C$88) -> 87.249441 | I88: =+AVERAGE($C$86:$G$86)*(1+$C$88) -> 87.249441 | J88: =+AVERAGE($C$86:$G$86)*(1+$C$88) -> 87.249441 | K88: =+AVERAGE($C$86:$G$86)*(1+$C$88) -> 87.249441 | L88: =+AVERAGE($C$86:$G$86)*(1+$C$88) -> 87.249441 | M88: =+AVERAGE($C$86:$G$86)*(1+$C$88) -> 87.249441 | N88: =+AVERAGE($C$86:$G$86)*(1+$C$88) -> 87.249441 | O88: =+AVERAGE($C$86:$G$86)*(1+$C$88) -> 87.249441 | ... Q88: =+AVERAGE($C$86:$G$86)*(1+$C$88) -> 87.249441 | S88: Base | T88: 2
B89: Downside | C89: 0.1 | H89: =+H88*(1+$C$89) -> 95.974385 | I89: =+I88*(1+$C$89) -> 95.974385 | J89: =+J88*(1+$C$89) -> 95.974385 | K89: =+K88*(1+$C$89) -> 95.974385 | L89: =+L88*(1+$C$89) -> 95.974385 | M89: =+M88*(1+$C$89) -> 95.974385 | N89: =+N88*(1+$C$89) -> 95.974385 | O89: =+O88*(1+$C$89) -> 95.974385 | ... Q89: =+Q88*(1+$C$89) -> 95.974385 | S89: Downside | T89: 3
B90: Active | H90: =+CHOOSE($S$90,H87,H88,H89) -> 87.249441 | I90: =+CHOOSE($S$90,I87,I88,I89) -> 87.249441 | J90: =+CHOOSE($S$90,J87,J88,J89) -> 87.249441 | K90: =+CHOOSE($S$90,K87,K88,K89) -> 87.249441 | L90: =+CHOOSE($S$90,L87,L88,L89) -> 87.249441 | M90: =+CHOOSE($S$90,M87,M88,M89) -> 87.249441 | N90: =+CHOOSE($S$90,N87,N88,N89) -> 87.249441 | O90: =+CHOOSE($S$90,O87,O88,O89) -> 87.249441 | ... Q90: =+CHOOSE($S$90,Q87,Q88,Q89) -> 87.249441 | S90: 2
B92: Accruals % of revenue | C92: =+'Balance Sheet'!C46/CR!C6 -> 0.24967665 | D92: =+'Balance Sheet'!D46/CR!D6 -> 0.2305673 | E92: =+'Balance Sheet'!E46/CR!E6 -> 0.20188275 | F92: =+'Balance Sheet'!F46/CR!F6 -> 0.3371431 | G92: =+'Balance Sheet'!G46/CR!G6 -> 0.17756232 | S92: Accruals Scenario
B93: Upside | C93: 0.1 | H93: =+H94*(1+$C$93) -> 0.19531855 | I93: =+I94*(1+$C$93) -> 0.19531855 | J93: =+J94*(1+$C$93) -> 0.19531855 | K93: =+K94*(1+$C$93) -> 0.19531855 | L93: =+L94*(1+$C$93) -> 0.19531855 | M93: =+M94*(1+$C$93) -> 0.19531855 | N93: =+N94*(1+$C$93) -> 0.19531855 | O93: =+O94*(1+$C$93) -> 0.19531855 | ... Q93: =+Q94*(1+$C$93) -> 0.19531855 | S93: Upside | T93: 1
B94: Base | C94: 0 | H94: =+$G$92*(1+$C$94) -> 0.17756232 | I94: =+$G$92*(1+$C$94) -> 0.17756232 | J94: =+$G$92*(1+$C$94) -> 0.17756232 | K94: =+$G$92*(1+$C$94) -> 0.17756232 | L94: =+$G$92*(1+$C$94) -> 0.17756232 | M94: =+$G$92*(1+$C$94) -> 0.17756232 | N94: =+$G$92*(1+$C$94) -> 0.17756232 | O94: =+$G$92*(1+$C$94) -> 0.17756232 | ... Q94: =+$G$92*(1+$C$94) -> 0.17756232 | S94: Base | T94: 2
B95: Downside | C95: 0.1 | H95: =+H94*(1-$C$95) -> 0.15980608 | I95: =+I94*(1-$C$95) -> 0.15980608 | J95: =+J94*(1-$C$95) -> 0.15980608 | K95: =+K94*(1-$C$95) -> 0.15980608 | L95: =+L94*(1-$C$95) -> 0.15980608 | M95: =+M94*(1-$C$95) -> 0.15980608 | N95: =+N94*(1-$C$95) -> 0.15980608 | O95: =+O94*(1-$C$95) -> 0.15980608 | ... Q95: =+Q94*(1-$C$95) -> 0.15980608 | S95: Downside | T95: 3
B96: Active | H96: =+CHOOSE($S$96,H93,H94,H95) -> 0.17756232 | I96: =+CHOOSE($S$96,I93,I94,I95) -> 0.17756232 | J96: =+CHOOSE($S$96,J93,J94,J95) -> 0.17756232 | K96: =+CHOOSE($S$96,K93,K94,K95) -> 0.17756232 | L96: =+CHOOSE($S$96,L93,L94,L95) -> 0.17756232 | M96: =+CHOOSE($S$96,M93,M94,M95) -> 0.17756232 | N96: =+CHOOSE($S$96,N93,N94,N95) -> 0.17756232 | O96: =+CHOOSE($S$96,O93,O94,O95) -> 0.17756232 | ... Q96: =+CHOOSE($S$96,Q93,Q94,Q95) -> 0.17756232 | S96: 2
B98: Taxes Payable % of tax expense | C98: =+'Balance Sheet'!C44/CR!C32 -> 0.26173216 | D98: =+'Balance Sheet'!D44/CR!D32 -> 0.56879433 | E98: =+'Balance Sheet'!E44/CR!E32 -> 0.6976434 | F98: =+'Balance Sheet'!F44/CR!F32 -> 0.56914239 | G98: =+'Balance Sheet'!G44/CR!G32 -> 0.18350227 | S98: Taxes Pay. Scenario
B99: Upside | C99: 0.1 | H99: =+H100*(1+$C$99) -> 0.2018525 | I99: =+I100*(1+$C$99) -> 0.2018525 | J99: =+J100*(1+$C$99) -> 0.2018525 | K99: =+K100*(1+$C$99) -> 0.2018525 | L99: =+L100*(1+$C$99) -> 0.2018525 | M99: =+M100*(1+$C$99) -> 0.2018525 | N99: =+N100*(1+$C$99) -> 0.2018525 | O99: =+O100*(1+$C$99) -> 0.2018525 | ... Q99: =+Q100*(1+$C$99) -> 0.2018525 | S99: Upside | T99: 1
B100: Base | C100: 0 | H100: =+$G$98*(1+$C$100) -> 0.18350227 | I100: =+$G$98*(1+$C$100) -> 0.18350227 | J100: =+$G$98*(1+$C$100) -> 0.18350227 | K100: =+$G$98*(1+$C$100) -> 0.18350227 | L100: =+$G$98*(1+$C$100) -> 0.18350227 | M100: =+$G$98*(1+$C$100) -> 0.18350227 | N100: =+$G$98*(1+$C$100) -> 0.18350227 | O100: =+$G$98*(1+$C$100) -> 0.18350227 | ... Q100: =+$G$98*(1+$C$100) -> 0.18350227 | S100: Base | T100: 2
B101: Downside | C101: 0.1 | H101: =+H100*(1-$C$101) -> 0.16515204 | I101: =+I100*(1-$C$101) -> 0.16515204 | J101: =+J100*(1-$C$101) -> 0.16515204 | K101: =+K100*(1-$C$101) -> 0.16515204 | L101: =+L100*(1-$C$101) -> 0.16515204 | M101: =+M100*(1-$C$101) -> 0.16515204 | N101: =+N100*(1-$C$101) -> 0.16515204 | O101: =+O100*(1-$C$101) -> 0.16515204 | ... Q101: =+Q100*(1-$C$101) -> 0.16515204 | S101: Downside | T101: 3
B102: Active | H102: =+CHOOSE($S$102,H99,H100,H101) -> 0.18350227 | I102: =+CHOOSE($S$102,I99,I100,I101) -> 0.18350227 | J102: =+CHOOSE($S$102,J99,J100,J101) -> 0.18350227 | K102: =+CHOOSE($S$102,K99,K100,K101) -> 0.18350227 | L102: =+CHOOSE($S$102,L99,L100,L101) -> 0.18350227 | M102: =+CHOOSE($S$102,M99,M100,M101) -> 0.18350227 | N102: =+CHOOSE($S$102,N99,N100,N101) -> 0.18350227 | O102: =+CHOOSE($S$102,O99,O100,O101) -> 0.18350227 | ... Q102: =+CHOOSE($S$102,Q99,Q100,Q101) -> 0.18350227 | S102: 2
B104: CapEx % of Revenue | C104: =+-FC!C23/CR!C6 -> 0.035361374 | D104: =+-FC!D23/CR!D6 -> 0.034474748 | E104: =+-FC!E23/CR!E6 -> 0.040450813 | F104: =+-FC!F23/CR!F6 -> 0.044011344 | G104: =+-FC!G23/CR!G6 -> 0.04394324
B105: Upside | C105: 0.005 | H105: =+H106+$C$105 -> 0.047801799 | I105: =+I106+$C$105 -> 0.047801799 | J105: =+J106+$C$105 -> 0.047801799 | K105: =+K106+$C$105 -> 0.047801799 | L105: =+L106+$C$105 -> 0.047801799 | M105: =+M106+$C$105 -> 0.047801799 | N105: =+N106+$C$105 -> 0.047801799 | O105: =+O106+$C$105 -> 0.047801799 | ... Q105: =+Q106+$C$105 -> 0.047801799
B106: Base | C106: 0 | H106: =+AVERAGE($E$104:$G$104)+$C$106 -> 0.042801799 | I106: =+AVERAGE($E$104:$G$104)+$C$106 -> 0.042801799 | J106: =+AVERAGE($E$104:$G$104)+$C$106 -> 0.042801799 | K106: =+AVERAGE($E$104:$G$104)+$C$106 -> 0.042801799 | L106: =+AVERAGE($E$104:$G$104)+$C$106 -> 0.042801799 | M106: =+AVERAGE($E$104:$G$104)+$C$106 -> 0.042801799 | N106: =+AVERAGE($E$104:$G$104)+$C$106 -> 0.042801799 | O106: =+AVERAGE($E$104:$G$104)+$C$106 -> 0.042801799 | ... Q106: =+AVERAGE($E$104:$G$104)+$C$106 -> 0.042801799
B107: Downside | C107: 0.005 | H107: =+H106-$C$107 -> 0.037801799 | I107: =+I106-$C$107 -> 0.037801799 | J107: =+J106-$C$107 -> 0.037801799 | K107: =+K106-$C$107 -> 0.037801799 | L107: =+L106-$C$107 -> 0.037801799 | M107: =+M106-$C$107 -> 0.037801799 | N107: =+N106-$C$107 -> 0.037801799 | O107: =+O106-$C$107 -> 0.037801799 | ... Q107: =+Q106-$C$107 -> 0.037801799
B108: Active | H108: =+CHOOSE($S$5, H105, H106, H107) -> 0.042801799 | I108: =+CHOOSE($S$5, I105, I106, I107) -> 0.042801799 | J108: =+CHOOSE($S$5, J105, J106, J107) -> 0.042801799 | K108: =+CHOOSE($S$5, K105, K106, K107) -> 0.042801799 | L108: =+CHOOSE($S$5, L105, L106, L107) -> 0.042801799 | M108: =+CHOOSE($S$5, M105, M106, M107) -> 0.042801799 | N108: =+CHOOSE($S$5, N105, N106, N107) -> 0.042801799 | O108: =+CHOOSE($S$5, O105, O106, O107) -> 0.042801799 | ... Q108: =+CHOOSE($S$5, Q105, Q106, Q107) -> 0.042801799
B112: Other Drivers
B114: Dilution Ratio | C114: =+CR!C55/CR!C50-1 -> 0.0057937428 | D114: =+CR!D55/CR!D50-1 -> 0.0050831793 | E114: =+CR!E55/CR!E50-1 -> 0.0037011335 | F114: =+CR!F55/CR!F50-1 -> 0.0025527965 | G114: =+CR!G55/CR!G50-1 -> 0.00232396 | H114: =+AVERAGE($C$114:$G$114) -> 0.0038909624 | I114: =+AVERAGE($C$114:$G$114) -> 0.0038909624 | J114: =+AVERAGE($C$114:$G$114) -> 0.0038909624 | K114: =+AVERAGE($C$114:$G$114) -> 0.0038909624 | L114: =+AVERAGE($C$114:$G$114) -> 0.0038909624 | M114: =+AVERAGE($C$114:$G$114) -> 0.0038909624 | N114: =+AVERAGE($C$114:$G$114) -> 0.0038909624 | O114: =+AVERAGE($C$114:$G$114) -> 0.0038909624 | ... Q114: =+AVERAGE($C$114:$G$114) -> 0.0038909624
B116: Dividend Payout Ratio | C116: =+-FC!C38/IS!C51 -> 0.7421963 | D116: =+-FC!D38/IS!D51 -> 0.79815552 | E116: =+-FC!E38/IS!E51 -> 0.74220646 | F116: =+-FC!F38/IS!F51 -> 0.78628539 | G116: =+-FC!G38/IS!G51 -> 0.66979477
B117: Upside | C117: 0.02 | H117: =+H118+$C$117 -> 0.75276221 | I117: =+I118+$C$117 -> 0.75276221 | J117: =+J118+$C$117 -> 0.75276221 | K117: =+K118+$C$117 -> 0.75276221 | L117: =+L118+$C$117 -> 0.75276221 | M117: =+M118+$C$117 -> 0.75276221 | N117: =+N118+$C$117 -> 0.75276221 | O117: =+O118+$C$117 -> 0.75276221 | ... Q117: =+Q118+$C$117 -> 0.75276221
B118: Base | C118: 0 | H118: =+AVERAGE($E$116:$G$116)+$C$118 -> 0.73276221 | I118: =+AVERAGE($E$116:$G$116)+$C$118 -> 0.73276221 | J118: =+AVERAGE($E$116:$G$116)+$C$118 -> 0.73276221 | K118: =+AVERAGE($E$116:$G$116)+$C$118 -> 0.73276221 | L118: =+AVERAGE($E$116:$G$116)+$C$118 -> 0.73276221 | M118: =+AVERAGE($E$116:$G$116)+$C$118 -> 0.73276221 | N118: =+AVERAGE($E$116:$G$116)+$C$118 -> 0.73276221 | O118: =+AVERAGE($E$116:$G$116)+$C$118 -> 0.73276221 | ... Q118: =+AVERAGE($E$116:$G$116)+$C$118 -> 0.73276221
B119: Downside | C119: 0.02 | H119: =+H118-$C$119 -> 0.71276221 | I119: =+I118-$C$119 -> 0.71276221 | J119: =+J118-$C$119 -> 0.71276221 | K119: =+K118-$C$119 -> 0.71276221 | L119: =+L118-$C$119 -> 0.71276221 | M119: =+M118-$C$119 -> 0.71276221 | N119: =+N118-$C$119 -> 0.71276221 | O119: =+O118-$C$119 -> 0.71276221 | ... Q119: =+Q118-$C$119 -> 0.71276221
B120: Active | H120: =+CHOOSE($S$5, H117, H118, H119) -> 0.73276221 | I120: =+CHOOSE($S$5, I117, I118, I119) -> 0.73276221 | J120: =+CHOOSE($S$5, J117, J118, J119) -> 0.73276221 | K120: =+CHOOSE($S$5, K117, K118, K119) -> 0.73276221 | L120: =+CHOOSE($S$5, L117, L118, L119) -> 0.73276221 | M120: =+CHOOSE($S$5, M117, M118, M119) -> 0.73276221 | N120: =+CHOOSE($S$5, N117, N118, N119) -> 0.73276221 | O120: =+CHOOSE($S$5, O117, O118, O119) -> 0.73276221 | ... Q120: =+CHOOSE($S$5, Q117, Q118, Q119) -> 0.73276221
B122: SBC % of Revenue | C122: =+FC!C10/CR!C6 -> 0.0087174712 | D122: =+FC!D10/CR!D6 -> 0.0082702226 | E122: =+FC!E10/CR!E6 -> 0.0055477896 | F122: =+FC!F10/CR!F6 -> 0.0060984711 | G122: =+FC!G10/CR!G6 -> 0.0058050019 | H122: =+AVERAGE($E$122:$G$122) -> 0.0058170875 | I122: =+AVERAGE($E$122:$G$122) -> 0.0058170875 | J122: =+AVERAGE($E$122:$G$122) -> 0.0058170875 | K122: =+AVERAGE($E$122:$G$122) -> 0.0058170875 | L122: =+AVERAGE($E$122:$G$122) -> 0.0058170875 | M122: =+AVERAGE($E$122:$G$122) -> 0.0058170875 | N122: =+AVERAGE($E$122:$G$122) -> 0.0058170875 | O122: =+AVERAGE($E$122:$G$122) -> 0.0058170875 | ... Q122: =+AVERAGE($E$122:$G$122) -> 0.0058170875
B124: Deferred taxes % of income taxes | C124: =+FC!C11/IS!C43 -> 0.34109119 | D124: =+FC!D11/IS!D43 -> -0.057683215 | E124: =+FC!E11/IS!E43 -> -0.00088928413 | F124: =+FC!F11/IS!F43 -> -0.0045137464 | G124: =+FC!G11/IS!G43 -> 0.18070605 | H124: =+AVERAGE($E$124:$G$124) -> 0.058434339 | I124: =+AVERAGE($E$124:$G$124) -> 0.058434339 | J124: =+AVERAGE($E$124:$G$124) -> 0.058434339 | K124: =+AVERAGE($E$124:$G$124) -> 0.058434339 | L124: =+AVERAGE($E$124:$G$124) -> 0.058434339 | M124: =+AVERAGE($E$124:$G$124) -> 0.058434339 | N124: =+AVERAGE($E$124:$G$124) -> 0.058434339 | O124: =+AVERAGE($E$124:$G$124) -> 0.058434339 | ... Q124: =+AVERAGE($E$124:$G$124) -> 0.058434339
B126: Other Current Assets/Other LT items | C126: =+'Balance Sheet'!C22/CR!C6 -> 0.072378292 | D126: =+'Balance Sheet'!D22/CR!D6 -> 0.070482739 | E126: =+'Balance Sheet'!E22/CR!E6 -> 0.10977634 | F126: =+'Balance Sheet'!F22/CR!F6 -> 0.056698723 | G126: =+'Balance Sheet'!G22/CR!G6 -> 0.045482918 | H126: =+AVERAGE($E$126:$G$126) -> 0.070652661 | I126: =+AVERAGE($E$126:$G$126) -> 0.070652661 | J126: =+AVERAGE($E$126:$G$126) -> 0.070652661 | K126: =+AVERAGE($E$126:$G$126) -> 0.070652661 | L126: =+AVERAGE($E$126:$G$126) -> 0.070652661 | M126: =+AVERAGE($E$126:$G$126) -> 0.070652661 | N126: =+AVERAGE($E$126:$G$126) -> 0.070652661 | O126: =+AVERAGE($E$126:$G$126) -> 0.070652661 | ... Q126: =+AVERAGE($E$126:$G$126) -> 0.070652661
B128: Share Buybacks % of Net Income | C128: =+-FC!C40/IS!C51 -> -0.060485109 | D128: =+-FC!D40/IS!D51 -> 0.060888703 | E128: =+-FC!E40/IS!E51 -> 0.16333769 | F128: =+-FC!F40/IS!F51 -> 0.098579626 | G128: =+-FC!G40/IS!G51 -> 0.033035782
B129: Cash for buybacks | C129: =+FC!C40 -> 591 | D129: =+FC!D40 -> -581 | E129: =+FC!E40 -> -1750 | F129: =+FC!F40 -> -1048 | G129: =+FC!G40 -> -433 | H129: =+CF!H31 -> 0 | I129: =+CF!I31 -> -2370.8757 | J129: =+CF!J31 -> -3077.4972 | K129: =+CF!K31 -> -3420.5248 | L129: =+CF!L31 -> -3637.2336 | M129: =+CF!M31 -> -3900.9956 | N129: =+CF!N31 -> -4169.4131 | O129: =+CF!O31 -> -4485.8129 | ... Q129: =+CF!Q31 -> -5080.8887
B130: Basic Shares Outstanding | H130: =+IS!G55 -> 4303 | I130: =+H130+H133 -> 4303 | J130: =+I130-I133 -> 4279.8045 | K130: =+J130-J133 -> 4251.1295 | L130: =+K130-K133 -> 4220.776 | M130: =+L130-L133 -> 4190.0364 | N130: =+M130-M133 -> 4158.6376 | O130: =+N130-N133 -> 4126.6764 | P130: =+O130-O133 -> 4093.9272 | Q130: =+P130-P133 -> 4060.9489
B131: Estimated share price | C131: #VALUE! | G131: {=+_FV(C131,"Price")} -> 92.71 | H131: =+G131*(1+H132) -> 97.3455 | I131: =+H131*(1+I132) -> 102.21278 | J131: =+I131*(1+J132) -> 107.32341 | K131: =+J131*(1+K132) -> 112.68958 | L131: =+K131*(1+L132) -> 118.32406 | M131: =+L131*(1+M132) -> 124.24027 | N131: =+M131*(1+N132) -> 130.45228 | O131: =+N131*(1+O132) -> 136.97489 | ... Q131: =+P131*(1+Q132) -> 151.01482
B132: Share Growth | H132: 0.05 | I132: 0.05 | J132: 0.05 | K132: 0.05 | L132: 0.05 | M132: 0.05 | N132: 0.05 | O132: 0.05 | P132: 0.05 | Q132: 0.05
B133: Number of Shares repurschased | H133: =+-CF!H31/H131 -> 0 | I133: =+-I129/I131 -> 23.195493 | J133: =+-J129/J131 -> 28.674984 | K133: =+-K129/K131 -> 30.353514 | L133: =+-L129/L131 -> 30.739593 | M133: =+-M129/M131 -> 31.398802 | N133: =+-N129/N131 -> 31.961213 | O133: =+-O129/O131 -> 32.749161 | P133: =+-P129/P131 -> 32.97835 | Q133: =+-Q129/Q131 -> 33.644967
B135: LTD / EBITDA (Leverage Target)
B136: Upside | C136: 0.25 | H136: =H137-$C$136 -> 2.54 | I136: =I137-$C$136 -> 2.47 | J136: =J137-$C$136 -> 2.4 | K136: =K137-$C$136 -> 2.33 | L136: =L137-$C$136 -> 2.25 | M136: =M137-$C$136 -> 2.25 | N136: =N137-$C$136 -> 2.25 | O136: =O137-$C$136 -> 2.25 | ... Q136: =Q137-$C$136 -> 2.25
B137: Base | C137: 0 | H137: 2.79 | I137: 2.72 | J137: 2.65 | K137: 2.58 | L137: 2.5 | M137: 2.5 | N137: 2.5 | O137: 2.5 | P137: 2.5 | Q137: 2.5
...

Sheet Debt
B3: 1. Current Debt Summary (as of 12/31/2025)
B4: Instrument | C4: Amount | D4: Avg Rate | E4: Maturity
B5: Commercial paper | C5: 1495 | D5: 0.039 | E5: <1 yr
B6: Lines of credit / other ST | C6: 56 | D6: 0.039 | E6: <1 yr
B7: Short-term borrowings (CP + LOC) | C7: =SUM(C5:C6) -> 1551
B8: U.S. dollar notes due 2027-2093 | C8: 26945 | D8: 0.036
B9: U.S. dollar debentures due 2026-2098 | C9: 767 | D9: 0.048
B10: Euro notes due 2026-2053 | C10: 15470 | D10: 0.024
B11: Swiss franc notes due 2028 | C11: 726 | D11: 0.051
B12: Other, due through 2098 | C12: 651 | D12: 0.049
B13: Fair value adjustments | C13: -618
B14: Total long-term debt (incl. current) | C14: =SUM(C8:C13) -> 43941 | D14: =+Drivers!C148 -> 0.033
B15: Less: current portion of LTD | C15: -1822
B16: Noncurrent long-term debt | C16: =C14+C15 -> 42119
B18: 2. Operating Leases (as of 12/31/2025)
B19: Item | C19: Amount
B20: Operating lease ROU assets | C20: 1697
B21: Current portion of lease liabilities | C21: 321
B22: Noncurrent portion of lease liabilities | C22: 1401
B23: Total operating lease liabilities | C23: =C21+C22 -> 1722
B24: Weighted-avg discount rate | C24: 0.039
B25: Annual operating lease cost (2025) | C25: 405
B27: 3. Maturity Schedule
B28: Year | C28: LTD Maturities | D28: Lease Payments
B29: 2026 | C29: 1822 | D29: 381
B30: 2027 | C30: 4817 | D30: 317
B31: 2028 | C31: 2923 | D31: 259
B32: 2029 | C32: 2955 | D32: 213
B33: 2030 | C33: 3411 | D33: 170
B34: Thereafter | D34: 679
B35: Total lease payments | D35: =SUM(D29:D34) -> 2019
B36: Less: imputed interest | D36: -297
B37: Total lease liabilities (PV) | D37: =D35+D36 -> 1722
B39: 4. Projected Roll-Forward (Target Leverage)
B40: Target LTD / EBITDA | C40: =+Drivers!H139 -> 2.79 | D40: =+Drivers!I139 -> 2.72 | E40: =+Drivers!J139 -> 2.65 | F40: =+Drivers!K139 -> 2.58 | G40: =+Drivers!L139 -> 2.5 | H40: =+Drivers!M139 -> 2.5 | I40: =+Drivers!N139 -> 2.5 | J40: =+Drivers!O139 -> 2.5 | ... L40: =+Drivers!Q139 -> 2.5
C41: 2026 | D41: 2027 | E41: 2028 | F41: 2029 | G41: 2030 | H41: 2031 | I41: 2032 | J41: 2033 | K41: 2034 | L41: 2035 | M41: 2036
B42: Long-Term Debt
B43: Opening balance | C43: =C14 -> 43941 | D43: =C46 -> 43941 | E43: =D46 -> 43941 | F43: =E46 -> 43941 | G43: =F46 -> 43941 | H43: =G46 -> 43941 | I43: =H46 -> 43941 | J43: =I46 -> 43941 | K43: =J46 -> 43941 | ... M43: =L46 -> 43941
B44: Less: maturities (repayments) | C44: =-C29 -> -1822 | D44: =-C30 -> -4817 | E44: =-C31 -> -2923 | F44: =-C32 -> -2955 | G44: =-C33 -> -3411 | H44: 0 | I44: 0 | J44: 0 | K44: 0 | L44: 0 | M44: =-L29 -> 0
B45: Add: new issuance (refinancing) | C45: =C46-C43-C44 -> 1822 | D45: =D46-D43-D44 -> 4817 | E45: =E46-E43-E44 -> 2923 | F45: =F46-F43-F44 -> 2955 | G45: =G46-G43-G44 -> 3411 | H45: =H46-H43-H44 -> 0 | I45: =I46-I43-I44 -> 0 | J45: =J46-J43-J44 -> 0 | ... L45: =L46-L43-L44 -> 0 | M45: =-M44*$C$40 -> 0
B46: Closing balance (held constant; maturities refinanced) | C46: =+C43 -> 43941 | D46: =+D43 -> 43941 | E46: =+E43 -> 43941 | F46: =+F43 -> 43941 | G46: =+G43 -> 43941 | H46: =+H43 -> 43941 | I46: =+I43 -> 43941 | J46: =+J43 -> 43941 | ... L46: =+L43 -> 43941 | M46: =M43+M44+M45 -> 43941
B47: Interest expense @ 3.3% | C47: =AVERAGE(C43,C46)*$D$14 -> 1450.053 | D47: =AVERAGE(D43,D46)*$D$14 -> 1450.053 | E47: =AVERAGE(E43,E46)*$D$14 -> 1450.053 | F47: =AVERAGE(F43,F46)*$D$14 -> 1450.053 | G47: =AVERAGE(G43,G46)*$D$14 -> 1450.053 | H47: =AVERAGE(H43,H46)*$D$14 -> 1450.053 | I47: =AVERAGE(I43,I46)*$D$14 -> 1450.053 | J47: =AVERAGE(J43,J46)*$D$14 -> 1450.053 | ... M47: =AVERAGE(M43,M46)*$D$14 -> 1450.053
C49: Lease/Sales % | D49: =C23/IS!G5 -> 0.035828721 | E49: Pmt/Balance % | F49: =C25/C23 -> 0.23519164
B50: Operating Leases (% of Sales)
B51: Opening balance | C51: =C23 -> 1722 | D51: =C54 -> 1760.4507 | E51: =D54 -> 1785.9862 | F51: =E54 -> 1876.5282 | G51: =F54 -> 1971.6053 | H51: =G54 -> 2062.4474 | I51: =H54 -> 2159.9692 | J51: =I54 -> 2262.249 | K51: =J54 -> 2374.3399 | L51: =K54 -> 2483.4856
B52: Interest @ 3.9% | C52: =C51*$C$24 -> 67.158 | D52: =D51*$C$24 -> 68.657577 | E52: =E51*$C$24 -> 69.653462 | F52: =F51*$C$24 -> 73.184598 | G52: =G51*$C$24 -> 76.892607 | H52: =H51*$C$24 -> 80.435449 | I52: =I51*$C$24 -> 84.238799 | J52: =J51*$C$24 -> 88.227711 | ... L52: =L51*$C$24 -> 96.855938
B53: Less: lease payment | C53: =-$F$49*C51 -> -405 | D53: =-$F$49*D51 -> -414.04328 | E53: =-$F$49*E51 -> -420.04902 | F53: =-$F$49*F51 -> -441.34373 | G53: =-$F$49*G51 -> -463.70508 | H53: =-$F$49*H51 -> -485.07038 | I53: =-$F$49*I51 -> -508.00669 | J53: =-$F$49*J51 -> -532.06205 | ... L53: =-$F$49*L51 -> -584.09504
B54: Closing balance = Target | C54: =$D$49*IS!H5 -> 1760.4507 | D54: =$D$49*IS!I5 -> 1785.9862 | E54: =$D$49*IS!J5 -> 1876.5282 | F54: =$D$49*IS!K5 -> 1971.6053 | G54: =$D$49*IS!L5 -> 2062.4474 | H54: =$D$49*IS!M5 -> 2159.9692 | I54: =$D$49*IS!N5 -> 2262.249 | J54: =$D$49*IS!O5 -> 2374.3399 | ... L54: =$D$49*IS!Q5 -> 2601.6252
C55: =C54-C51-C52-C53 -> 376.29268 | D55: =D54-D51-D52-D53 -> 370.92122 | E55: =E54-E51-E52-E53 -> 440.93752 | F55: =F54-F51-F52-F53 -> 463.23629 | G55: =G54-G51-G52-G53 -> 477.65457 | H55: =H54-H51-H52-H53 -> 502.15673 | I55: =I54-I51-I52-I53 -> 526.04768 | J55: =J54-J51-J52-J53 -> 555.92523 | ... L55: =L54-L51-L52-L53 -> 605.37877
B57: Total debt (LTD + leases + CP) | C57: =C46+C54+$C$7 -> 47252.451 | D57: =D46+D54+$C$7 -> 47277.986 | E57: =E46+E54+$C$7 -> 47368.528 | F57: =F46+F54+$C$7 -> 47463.605 | G57: =G46+G54+$C$7 -> 47554.447 | H57: =H46+H54+$C$7 -> 47651.969 | I57: =I46+I54+$C$7 -> 47754.249 | J57: =J46+J54+$C$7 -> 47866.34 | ... L57: =L46+L54+$C$7 -> 48093.625
B58: Total interest expense | C58: =C47+C52+$C$7*$D$5 -> 1577.7 | D58: =D47+D52+$C$7*$D$5 -> 1579.1996 | E58: =E47+E52+$C$7*$D$5 -> 1580.1955 | F58: =F47+F52+$C$7*$D$5 -> 1583.7266 | G58: =G47+G52+$C$7*$D$5 -> 1587.4346 | H58: =H47+H52+$C$7*$D$5 -> 1590.9774 | I58: =I47+I52+$C$7*$D$5 -> 1594.7808 | J58: =J47+J52+$C$7*$D$5 -> 1598.7697 | ... L58: =L47+L52+$C$7*$D$5 -> 1607.3979

Sheet IS
C1: 2021 | D1: 2022 | E1: 2023 | F1: 2024 | G1: 2025 | H1: 2026 | I1: 2027 | J1: 2028 | K1: 2029 | L1: 2030 | M1: 2031 | N1: 2032 | O1: 2033 | P1: 2034 | Q1: 2035
B3: Income Statement
B5: Total Revenue | C5: =+CR!C6 -> 38658 | D5: =+CR!D6 -> 43046 | E5: =+CR!E6 -> 45784 | F5: =+CR!F6 -> 46897 | G5: =+CR!G6 -> 48062 | H5: =+H6+H8+H10+H12+H14 -> 49135.18 | I5: =+I6+I8+I10+I12+I14 -> 49847.891 | J5: =+J6+J8+J10+J12+J14 -> 52374.969 | K5: =+K6+K8+K10+K12+K14 -> 55028.626 | L5: =+L6+L8+L10+L12+L14 -> 57564.081 | M5: =+M6+M8+M10+M12+M14 -> 60285.97 | N5: =+N6+N8+N10+N12+N14 -> 63140.657 | O5: =+O6+O8+O10+O12+O14 -> 66269.178 | ... Q5: =+Q6+Q8+Q10+Q12+Q14 -> 72612.841
B6: EMEA | H6: =+MODL!D22 -> 12228.31 | I6: =+H6*(1+H7) -> 12936.953 | J6: =+I6*(1+I7) -> 13522.494 | K6: =+J6*(1+J7) -> 14138.016 | L6: =+K6*(1+K7) -> 14663.818 | M6: =+L6*(1+L7) -> 15247.736 | N6: =+M6*(1+M7) -> 15854.872 | O6: =+N6*(1+N7) -> 16545.612 | P6: =+O6*(1+O7) -> 17161.072 | Q6: =+P6*(1+P7) -> 17844.504
B7: YoY growth % | H7: =+Drivers!H7 -> 0.05795102 | I7: =+Drivers!I7 -> 0.045261133 | J7: =+Drivers!J7 -> 0.045518364 | K7: =+Drivers!K7 -> 0.037190631 | L7: =+Drivers!L7 -> 0.039820309 | M7: =+Drivers!M7 -> 0.039818125 | N7: =+Drivers!N7 -> 0.043566416 | O7: =+Drivers!O7 -> 0.037197778 | ... Q7: =+Drivers!Q7 -> 0.039822394
B8: Latin America | H8: =+MODL!D23 -> 6858.39 | I8: =+H8*(1+H9) -> 7167.9741 | J8: =+I8*(1+I9) -> 7636.998 | K8: =+J8*(1+J9) -> 8133.4029 | L8: =+K8*(1+K9) -> 8662.0741 | M8: =+L8*(1+L9) -> 9225.1089 | N8: =+M8*(1+M9) -> 9824.741 | O8: =+N8*(1+N9) -> 10463.349 | P8: =+O8*(1+O9) -> 11143.467 | Q8: =+P8*(1+P9) -> 11867.792
B9: YoY growth % | H9: =+Drivers!H8 -> 0.045139482 | I9: =+Drivers!I8 -> 0.065433257 | J9: =+Drivers!J8 -> 0.065 | K9: =+Drivers!K8 -> 0.065 | L9: =+Drivers!L8 -> 0.065 | M9: =+Drivers!M8 -> 0.065 | N9: =+Drivers!N8 -> 0.065 | O9: =+Drivers!O8 -> 0.065 | ... Q9: =+Drivers!Q8 -> 0.065
B10: North America | H10: =+MODL!D24 -> 20552.014 | I10: =+H10*(1+H11) -> 21603.167 | J10: =+I10*(1+I11) -> 22511.685 | K10: =+J10*(1+J11) -> 23494.169 | L10: =+K10*(1+K11) -> 24494.035 | M10: =+L10*(1+L11) -> 25567.275 | N10: =+M10*(1+M11) -> 26687.513 | O10: =+N10*(1+N11) -> 27880.255 | P10: =+O10*(1+O11) -> 29066.856 | Q10: =+P10*(1+P11) -> 30340.519
B11: YoY growth % | H11: =+Drivers!H9 -> 0.051145989 | I11: =+Drivers!I9 -> 0.042054848 | J11: =+Drivers!J9 -> 0.043643297 | K11: =+Drivers!K9 -> 0.04255804 | L11: =+Drivers!L9 -> 0.043816365 | M11: =+Drivers!M9 -> 0.043815331 | N11: =+Drivers!N9 -> 0.044692868 | O11: =+Drivers!O9 -> 0.042560639 | ... Q11: =+Drivers!Q9 -> 0.043817359
B12: Asia Pacific | H12: =+MODL!D25 -> 5779.3126 | I12: =+H12*(1+H13) -> 5872.564 | J12: =+I12*(1+I13) -> 6108.1307 | K12: =+J12*(1+J13) -> 6391.0108 | L12: =+K12*(1+K13) -> 6720.0654 | M12: =+L12*(1+L13) -> 7085.2298 | N12: =+M12*(1+M13) -> 7470.2133 | O12: =+N12*(1+N13) -> 7927.5053 | P12: =+O12*(1+O13) -> 8335.7721 | Q12: =+P12*(1+P13) -> 8788.7869
B13: YoY growth % | H13: =+Drivers!H10 -> 0.016135375 | I13: =+Drivers!I10 -> 0.040113099 | J13: =+Drivers!J10 -> 0.046312062 | K13: =+Drivers!K10 -> 0.051487102 | L13: =+Drivers!L10 -> 0.054339401 | M13: =+Drivers!M10 -> 0.054336071 | N13: =+Drivers!N10 -> 0.061215387 | O13: =+Drivers!O10 -> 0.051500027 | ... Q13: =+Drivers!Q10 -> 0.054342565
B14: Bottling & Other | H14: =+MODL!D18+MODL!D19+MODL!D20 -> 3717.1536 | I14: =+MODL!E18+MODL!E19+MODL!E20 -> 2267.2327 | J14: =+MODL!F18+MODL!F19+MODL!F20 -> 2595.6606 | K14: =+MODL!G18+MODL!G19+MODL!G20 -> 2872.0271 | L14: =+MODL!H18+MODL!H19+MODL!H20 -> 3024.0884 | M14: =+L14*(1+AVERAGE($H$7:$L$7)) -> 3160.6208 | N14: =+M14*(1+AVERAGE($H$7:$L$7)) -> 3303.3174 | O14: =+N14*(1+AVERAGE($H$7:$L$7)) -> 3452.4565 | P14: =+O14*(1+AVERAGE($H$7:$L$7)) -> 3608.3291 | Q14: =+P14*(1+AVERAGE($H$7:$L$7)) -> 3771.2389
B16: Cost of Goods Sold (COGS) | C16: =+C5-C18 -> 15410 | D16: =+D5-D18 -> 18183 | E16: =+E5-E18 -> 18465 | F16: =+F5-F18 -> 18254 | G16: =+G5-G18 -> 18266 | H16: =+H5-H18 -> 19591.435 | I16: =+I5-I18 -> 19875.61 | J16: =+J5-J18 -> 20883.22 | ... Q16: =+Q5-Q18 -> 28952.57
B18: Gross Profit | C18: =+CR!C10 -> 23248 | D18: =+CR!D10 -> 24863 | E18: =+CR!E10 -> 27319 | F18: =+CR!F10 -> 28643 | G18: =+CR!G10 -> 29796 | H18: =+H19*H5 -> 29543.746 | I18: =+I19*I5 -> 29972.281 | J18: =+J19*J5 -> 31491.749 | K18: =+K19*K5 -> 33087.326 | L18: =+L19*L5 -> 34611.831 | M18: =+M19*M5 -> 36248.434 | N18: =+N19*N5 -> 37964.886 | O18: =+O19*O5 -> 39845.987 | ... Q18: =+Q19*Q5 -> 43660.272
B19: Gross Profit Margin % | C19: =+C18/C5 -> 0.60137617 | D19: =+D18/D5 -> 0.57759141 | E19: =+E18/E5 -> 0.59669317 | F19: =+F18/F5 -> 0.61076401 | G19: =+G18/G5 -> 0.61994923 | H19: =+Drivers!H37 -> 0.6012748 | I19: =+Drivers!I37 -> 0.6012748 | J19: =+Drivers!J37 -> 0.6012748 | K19: =+Drivers!K37 -> 0.6012748 | L19: =+Drivers!L37 -> 0.6012748 | M19: =+Drivers!M37 -> 0.6012748 | N19: =+Drivers!N37 -> 0.6012748 | O19: =+Drivers!O37 -> 0.6012748 | ... Q19: =+Drivers!Q37 -> 0.6012748
B21: SG&A expenses | C21: =+CR!C12 -> 12139 | D21: =+CR!D12 -> 12263 | E21: =+CR!E12 -> 13983 | F21: =+CR!F12 -> 17996 | G21: =+CR!G12 -> 15481 | H21: =+H22*H5 -> 14456.925 | I21: =+I22*I5 -> 14262.282 | J21: =+J22*J5 -> 14847.526 | K21: =+K22*K5 -> 15426.074 | L21: =+L22*L5 -> 15849.013 | M21: =+M22*M5 -> 16296.996 | N21: =+N22*N5 -> 16752.995 | O21: =+O22*O5 -> 17251.734 | ... Q21: =+Q22*Q5 -> 18177.04
B22: SG&A % of Revenue | C22: =+C21/C5 -> 0.31401004 | D22: =+D21/D5 -> 0.28488129 | E22: =+E21/E5 -> 0.30541237 | F22: =+F21/F5 -> 0.38373457 | G22: =+G21/G5 -> 0.32210478 | H22: =+Drivers!H44 -> 0.29422757 | I22: =+Drivers!I44 -> 0.28611606 | J22: =+Drivers!J44 -> 0.28348516 | K22: =+Drivers!K44 -> 0.28032817 | L22: =+Drivers!L44 -> 0.27532817 | M22: =+Drivers!M44 -> 0.27032817 | N22: =+Drivers!N44 -> 0.26532817 | O22: =+Drivers!O44 -> 0.26032817 | ... Q22: =+Drivers!Q44 -> 0.25032817
B24: Depreciation & Amortization | C24: Included on SG&A expenses | H24: =+H25*H5 -> 1142.2015 | I24: =+I25*I5 -> 1246.5997 | J24: =+J25*J5 -> 1314.0287 | K24: =+K25*K5 -> 1564.5518 | L24: =+L25*L5 -> 1655.8269 | M24: =+M25*M5 -> 1734.1218 | N24: =+N25*N5 -> 1816.2367 | O24: =+O25*O5 -> 1906.2284 | ... Q24: =+Q25*Q5 -> 2088.7035
B25: D&A % of Revenue | H25: =+Drivers!H51 -> 0.023246103 | I25: =+Drivers!I51 -> 0.025008073 | J25: =+Drivers!J51 -> 0.025088868 | K25: =+Drivers!K51 -> 0.028431599 | L25: =+Drivers!L51 -> 0.028764932 | M25: =+Drivers!M51 -> 0.028764932 | N25: =+Drivers!N51 -> 0.028764932 | O25: =+Drivers!O51 -> 0.028764932 | ... Q25: =+Drivers!Q51 -> 0.028764932
B27: Operating income (EBIT) | C27: =+CR!C16 -> 11109 | D27: =+CR!D16 -> 12600 | E27: =+CR!E16 -> 13336 | F27: =+CR!F16 -> 10647 | G27: =+CR!G16 -> 14315 | H27: =+H18-H21-H24 -> 13944.62 | I27: =+I18-I21-I24 -> 14463.399 | J27: =+J18-J21-J24 -> 15330.194 | K27: =+K18-K21-K24 -> 16096.7 | L27: =+L18-L21-L24 -> 17106.991 | M27: =+M18-M21-M24 -> 18217.317 | N27: =+N18-N21-N24 -> 19395.654 | O27: =+O18-O21-O24 -> 20688.024 | ... Q27: =+Q18-Q21-Q24 -> 23394.528
B28: EBIT % of Revenue | C28: =+C27/C5 -> 0.28736613 | D28: =+D27/D5 -> 0.29271012 | E28: =+E27/E5 -> 0.2912808 | F28: =+F27/F5 -> 0.22702945 | G28: =+G27/G5 -> 0.29784445 | H28: =+H27/H5 -> 0.28380113 | I28: =+I27/I5 -> 0.29015067 | J28: =+J27/J5 -> 0.29270078 | ... Q28: =+Q27/Q5 -> 0.3221817
B30: Non-operation expenses | C30: =+SUM(C31:C33) -> -1594 | D30: =+SUM(D31:D33) -> -2746 | E30: =+SUM(E31:E33) -> -630 | F30: =+SUM(F31:F33) -> -1242 | G30: =+SUM(G31:G33) -> -1808 | H30: =+SUM(H31:H33) -> 293.3 | I30: =+SUM(I31:I33) -> 293.3 | J30: =+SUM(J31:J33) -> 293.3 | ... Q30: =+SUM(Q31:Q33) -> 293.3
B31: Restructuring charges | C31: =+CR!C28 -> 378 | D31: =+CR!D28 -> 117 | E31: =+CR!E28 -> 191 | F31: =+CR!F28 -> 133 | G31: =+CR!G28 -> 97 | H31: =+Drivers!H61 -> 134.5 | I31: =+Drivers!I61 -> 134.5 | J31: =+Drivers!J61 -> 134.5 | K31: =+Drivers!K61 -> 134.5 | L31: =+Drivers!L61 -> 134.5 | M31: =+Drivers!M61 -> 134.5 | N31: =+Drivers!N61 -> 134.5 | O31: =+Drivers!O61 -> 134.5 | ... Q31: =+Drivers!Q61 -> 134.5
B32: Mergers & acquisitions | C32: =+CR!C26 -> -1173 | D32: =+CR!D26 -> 408 | E32: =+CR!E26 -> 836 | F32: =+CR!F26 -> 1377 | G32: =+CR!G26 -> -654 | H32: =+Drivers!H58 -> 158.8 | I32: =+Drivers!I58 -> 158.8 | J32: =+Drivers!J58 -> 158.8 | K32: =+Drivers!K58 -> 158.8 | L32: =+Drivers!L58 -> 158.8 | M32: =+Drivers!M58 -> 158.8 | N32: =+Drivers!N58 -> 158.8 | O32: =+Drivers!O58 -> 158.8 | ... Q32: =+Drivers!Q58 -> 158.8
B33: Other non-recurring items | C33: =-SUM(CR!C25,CR!C27,CR!C29,CR!C30) -> -799 | D33: =-SUM(CR!D25,CR!D27,CR!D29,CR!D30) -> -3271 | E33: =-SUM(CR!E25,CR!E27,CR!E29,CR!E30) -> -1657 | F33: =-SUM(CR!F25,CR!F27,CR!F29,CR!F30) -> -2752 | G33: =-SUM(CR!G25,CR!G27,CR!G29,CR!G30) -> -1251 | H33: 0 | I33: 0 | J33: 0 | K33: 0 | L33: 0 | M33: 0 | N33: 0 | O33: 0 | P33: 0 | Q33: 0
B35: Net interest expense | C35: =+CR!C18 -> 2142 | D35: =+SUM(D36:D39) -> 1307 | E35: =+SUM(E36:E39) -> 2459 | F35: =+SUM(F36:F39) -> 2669 | G35: =+SUM(G36:G39) -> 2415 | H35: =+SUM(H36:H39) -> 725.08069 | I35: =+SUM(I36:I39) -> 753.41086 | J35: =+SUM(J36:J39) -> 742.1407 | K35: =+SUM(K36:K39) -> 745.67183 | ... Q35: =+SUM(Q36:Q39) -> 769.34317
B36: Paper notes | C36: =+CR!C19 -> 2418 | D36: =+CR!D19 -> 858 | E36: =+CR!E19 -> 1552 | F36: =+CR!F19 -> 1681 | G36: =+CR!G19 -> 1629 | H36: =+Debt!$C$7*Debt!$D$5 -> 60.489 | I36: =+Debt!$C$7*Debt!$D$5 -> 60.489 | J36: =+Debt!$C$7*Debt!$D$5 -> 60.489 | K36: =+Debt!$C$7*Debt!$D$5 -> 60.489 | L36: =+Debt!$C$7*Debt!$D$5 -> 60.489 | M36: =+Debt!$C$7*Debt!$D$5 -> 60.489 | N36: =+Debt!$C$7*Debt!$D$5 -> 60.489 | O36: =+Debt!$C$7*Debt!$D$5 -> 60.489 | ... Q36: =+Debt!$C$7*Debt!$D$5 -> 60.489
B37: LT Debt | H37: =+Debt!C47 -> 1450.053 | I37: =+Debt!D47 -> 1450.053 | J37: =+Debt!E47 -> 1450.053 | K37: =+Debt!F47 -> 1450.053 | L37: =+Debt!G47 -> 1450.053 | M37: =+Debt!H47 -> 1450.053 | N37: =+Debt!I47 -> 1450.053 | O37: =+Debt!J47 -> 1450.053 | ... Q37: =+Debt!L47 -> 1450.053
B38: Lease Liabilities | H38: =+Debt!C52 -> 67.158 | I38: =+Debt!D52 -> 68.657577 | J38: =+Debt!E52 -> 69.653462 | K38: =+Debt!F52 -> 73.184598 | L38: =+Debt!G52 -> 76.892607 | M38: =+Debt!H52 -> 80.435449 | N38: =+Debt!I52 -> 84.238799 | O38: =+Debt!J52 -> 88.227711 | ... Q38: =+Debt!L52 -> 96.855938
B39: Interest on Cashs and STI | C39: =+CR!C20 -> 276 | D39: =+CR!D20 -> 449 | E39: =+CR!E20 -> 907 | F39: =+CR!F20 -> 988 | G39: =+CR!G20 -> 786 | H39: =-Drivers!$H$142*(BS!G7+BS!G8) -> -852.61931 | I39: =-Drivers!$H$142*(BS!H7+BS!H8) -> -825.78871 | J39: =-Drivers!$H$142*(BS!I7+BS!I8) -> -838.05477 | K39: =-Drivers!$H$142*(BS!J7+BS!J8) -> -838.05477 | L39: =-Drivers!$H$142*(BS!K7+BS!K8) -> -838.05477 | M39: =-Drivers!$H$142*(BS!L7+BS!L8) -> -838.05477 | N39: =-Drivers!$H$142*(BS!M7+BS!M8) -> -838.05477 | O39: =-Drivers!$H$142*(BS!N7+BS!N8) -> -838.05477 | ... Q39: =-Drivers!$H$142*(BS!P7+BS!P8) -> -838.05477
B41: Income before taxes (EBT) | C41: =+CR!C31 -> 12425 | D41: =+CR!D31 -> 11686 | E41: =+CR!E31 -> 12952 | F41: =+CR!F31 -> 13086 | G41: =+CR!G31 -> 15998 | H41: =+H27-H30-H35 -> 12926.239 | I41: =+I27-I30-I35 -> 13416.688 | J41: =+J27-J30-J35 -> 14294.753 | K41: =+K27-K30-K35 -> 15057.728 | L41: =+L27-L30-L35 -> 16064.311 | M41: =+M27-M30-M35 -> 17171.094 | N41: =+N27-N30-N35 -> 18345.628 | O41: =+O27-O30-O35 -> 19634.009 | ... Q41: =+Q27-Q30-Q35 -> 22331.885
B43: Income taxes | C43: =+CR!C32 -> 2621 | D43: =+CR!D32 -> 2115 | E43: =+CR!E32 -> 2249 | F43: =+CR!F32 -> 2437 | G43: =+CR!G32 -> 2861 | H43: =+H44*H41 -> 2405.9273 | I43: =+I44*I41 -> 2497.2133 | J43: =+J44*J41 -> 2660.6453 | K43: =+K44*K41 -> 2802.6559 | L43: =+L44*L41 -> 2990.0086 | M43: =+M44*M41 -> 3196.0111 | N43: =+N44*N41 -> 3414.6241 | O43: =+O44*O41 -> 3654.4272 | ... Q43: =+Q44*Q41 -> 4156.5758
B44: Tax % of EBT | C44: =+C43/C41 -> 0.21094567 | D44: =+D43/D41 -> 0.18098579 | E44: =+E43/E41 -> 0.17364114 | F44: =+F43/F41 -> 0.18622956 | G44: =+G43/G41 -> 0.17883485 | H44: =+Drivers!H68 -> 0.1861274 | I44: =+Drivers!I68 -> 0.1861274 | J44: =+Drivers!J68 -> 0.1861274 | K44: =+Drivers!K68 -> 0.1861274 | L44: =+Drivers!L68 -> 0.1861274 | M44: =+Drivers!M68 -> 0.1861274 | N44: =+Drivers!N68 -> 0.1861274 | O44: =+Drivers!O68 -> 0.1861274 | ... Q44: =+Drivers!Q68 -> 0.1861274
B46: Net Income | C46: =+C41-C43 -> 9804 | D46: =+D41-D43 -> 9571 | E46: =+E41-E43 -> 10703 | F46: =+F41-F43 -> 10649 | G46: =+G41-G43 -> 13137 | H46: =+H41-H43 -> 10520.312 | I46: =+I41-I43 -> 10919.475 | J46: =+J41-J43 -> 11634.108 | ... Q46: =+Q41-Q43 -> 18175.309
B47: Net Income % of Revenue | C47: =+C46/C5 -> 0.25360857 | D47: =+D46/D5 -> 0.22234354 | E47: =+E46/E5 -> 0.23377162 | F47: =+F46/F5 -> 0.22707209 | G47: =+G46/G5 -> 0.27333444 | H47: =+H46/H5 -> 0.21410956 | I47: =+I46/I5 -> 0.2190559 | J47: =+J46/J5 -> 0.22213107 | ... Q47: =+Q46/Q5 -> 0.25030434
B49: Minority & Non-controlling interest | C49: =+CR!C40 -> 33 | D49: =+CR!D40 -> 29 | E49: =+CR!E40 -> -11 | F49: =+CR!F40 -> 18 | G49: =+CR!G40 -> 30
B51: Net Income GAAP | C51: =+C46-C49 -> 9771 | D51: =+D46-D49 -> 9542 | E51: =+E46-E49 -> 10714 | F51: =+F46-F49 -> 10631 | G51: =+G46-G49 -> 13107 | H51: =+H46-H49 -> 10520.312 | I51: =+I46-I49 -> 10919.475 | J51: =+J46-J49 -> 11634.108 | ... Q51: =+Q46-Q49 -> 18175.309
B52: Net Income GAAP % of Revenue | C52: =+C51/C5 -> 0.25275493 | D52: =+D51/D5 -> 0.22166984 | E52: =+E51/E5 -> 0.23401188 | F52: =+F51/F5 -> 0.22668827 | G52: =+G51/G5 -> 0.27271025 | H52: =+H51/H5 -> 0.21410956 | I52: =+I51/I5 -> 0.2190559 | J52: =+J51/J5 -> 0.22213107 | ... Q52: =+Q51/Q5 -> 0.25030434
B54: EPS | C54: =+C51/C55 -> 2.2644264 | D54: =+D51/D55 -> 2.2047135 | E54: =+E51/E55 -> 2.4783715 | F54: =+F51/F55 -> 2.4671618 | G54: =+G51/G55 -> 3.0460144 | H54: =+H51/H55 -> 2.4448784 | I54: =+I51/I55 -> 2.5376423 | J54: =+J51/J55 -> 2.7183737 | ... Q54: =+Q51/Q55 -> 4.4756312
B55: Basic Shares Outstanding | C55: =+CR!C50 -> 4315 | D55: =+CR!D50 -> 4328 | E55: =+CR!E50 -> 4323 | F55: =+CR!F50 -> 4309 | G55: =+CR!G50 -> 4303 | H55: =+Drivers!H130 -> 4303 | I55: =+Drivers!I130 -> 4303 | J55: =+Drivers!J130 -> 4279.8045 | K55: =+Drivers!K130 -> 4251.1295 | L55: =+Drivers!L130 -> 4220.776 | M55: =+Drivers!M130 -> 4190.0364 | N55: =+Drivers!N130 -> 4158.6376 | O55: =+Drivers!O130 -> 4126.6764 | ... Q55: =+Drivers!Q130 -> 4060.9489
B57: Diluted EPS | C57: =+C51/C58 -> 2.2513825 | D57: =+D51/D58 -> 2.1935632 | E57: =+E51/E58 -> 2.4692325 | F57: =+F51/F58 -> 2.4608796 | G57: =+G51/G58 -> 3.038952 | H57: =+H51/H58 -> 2.4354023 | I57: =+I51/I58 -> 2.5278067 | J57: =+J51/J58 -> 2.7078376 | ... Q57: =+Q51/Q58 -> 4.4582841
B58: Diluted Shares Outstanding | C58: =+CR!C55 -> 4340 | D58: =+CR!D55 -> 4350 | E58: =+CR!E55 -> 4339 | F58: =+CR!F55 -> 4320 | G58: =+CR!G55 -> 4313 | H58: =+H55*(1+Drivers!H114) -> 4319.7428 | I58: =+I55*(1+Drivers!I114) -> 4319.7428 | J58: =+J55*(1+Drivers!J114) -> 4296.4571 | K58: =+K55*(1+Drivers!K114) -> 4267.6705 | L58: =+L55*(1+Drivers!L114) -> 4237.1989 | M58: =+M55*(1+Drivers!M114) -> 4206.3397 | N58: =+N55*(1+Drivers!N114) -> 4174.8187 | O58: =+O55*(1+Drivers!O114) -> 4142.7331 | ... Q58: =+Q55*(1+Drivers!Q114) -> 4076.7499
B61: EBITDA | C61: =+CR!C62 -> 12903 | D61: =+CR!D62 -> 14257 | E61: =+CR!E62 -> 14861 | F61: =+CR!F62 -> 12084 | G61: =+CR!G62 -> 15770 | H61: =+H27+H24 -> 15086.821 | I61: =+I27+I24 -> 15709.999 | J61: =+J27+J24 -> 16644.223 | K61: =+K27+K24 -> 17661.252 | L61: =+L27+L24 -> 18762.818 | M61: =+M27+M24 -> 19951.438 | N61: =+N27+N24 -> 21211.891 | O61: =+O27+O24 -> 22594.253 | ... Q61: =+Q27+Q24 -> 25483.232
B62: EBITDA Margin % | C62: =+CR!C63/100 -> 0.333773 | D62: =+CR!D63/100 -> 0.331204 | E62: =+CR!E63/100 -> 0.324589 | F62: =+CR!F63/100 -> 0.257671 | G62: =+CR!G63/100 -> 0.328118 | H62: =+H61/H5 -> 0.30704723 | I62: =+I61/I5 -> 0.31515874 | J62: =+J61/J5 -> 0.31778964 | K62: =+K61/K5 -> 0.32094663 | L62: =+L61/L5 -> 0.32594663 | M62: =+M61/M5 -> 0.33094663 | N62: =+N61/N5 -> 0.33594663 | O62: =+O61/O5 -> 0.34094663 | ... Q62: =+Q61/Q5 -> 0.35094663

Sheet CF
C1: 2021 | D1: 2022 | E1: 2023 | F1: 2024 | G1: 2025 | H1: 2026 | I1: 2027 | J1: 2028 | K1: 2029 | L1: 2030 | M1: 2031 | N1: 2032 | O1: 2033 | P1: 2034 | Q1: 2035
B3: Cash Flow Statement
B5: Cash From Operations (CFO)
B7: Net Income | C7: =+FC!C7 -> 9771 | D7: =+FC!D7 -> 9542 | E7: =+FC!E7 -> 10714 | F7: =+FC!F7 -> 10631 | G7: =+FC!G7 -> 13107 | H7: =+IS!H46 -> 10520.312 | I7: =+IS!I46 -> 10919.475 | J7: =+IS!J46 -> 11634.108 | K7: =+IS!K46 -> 12255.073 | L7: =+IS!L46 -> 13074.303 | M7: =+IS!M46 -> 13975.083 | N7: =+IS!N46 -> 14931.004 | O7: =+IS!O46 -> 15979.582 | ... Q7: =+IS!Q46 -> 18175.309
B8: Depreciation & Amortisation | C8: =+FC!C8 -> 1452 | D8: =+FC!D8 -> 1260 | E8: =+FC!E8 -> 1128 | F8: =+FC!F8 -> 1075 | G8: =+FC!G8 -> 1050 | H8: =+IS!H24 -> 1142.2015 | I8: =+IS!I24 -> 1246.5997 | J8: =+IS!J24 -> 1314.0287 | K8: =+IS!K24 -> 1564.5518 | L8: =+IS!L24 -> 1655.8269 | M8: =+IS!M24 -> 1734.1218 | N8: =+IS!N24 -> 1816.2367 | O8: =+IS!O24 -> 1906.2284 | ... Q8: =+IS!Q24 -> 2088.7035
B9: Stock-Based Compensation (SBC) | C9: =+FC!C10 -> 337 | D9: =+FC!D10 -> 356 | E9: =+FC!E10 -> 254 | F9: =+FC!F10 -> 286 | G9: =+FC!G10 -> 279 | H9: =+Drivers!H122*IS!H5 -> 285.82365 | I9: =+Drivers!I122*IS!I5 -> 289.96955 | J9: =+Drivers!J122*IS!J5 -> 304.66978 | K9: =+Drivers!K122*IS!K5 -> 320.10634 | L9: =+Drivers!L122*IS!L5 -> 334.8553 | M9: =+Drivers!M122*IS!M5 -> 350.68876 | N9: =+Drivers!N122*IS!N5 -> 367.29473 | O9: =+Drivers!O122*IS!O5 -> 385.49361 | ... Q9: =+Drivers!Q122*IS!Q5 -> 422.39525
B10: Deferred Taxes | C10: =+FC!C11 -> 894 | D10: =+FC!D11 -> -122 | E10: =+FC!E11 -> -2 | F10: =+FC!F11 -> -11 | G10: =+FC!G11 -> 517 | H10: =+Drivers!H124*IS!H43 -> 140.58877 | I10: =+Drivers!I124*IS!I43 -> 145.92301 | J10: =+Drivers!J124*IS!J43 -> 155.47305 | K10: =+Drivers!K124*IS!K43 -> 163.77134 | L10: =+Drivers!L124*IS!L43 -> 174.71917 | M10: =+Drivers!M124*IS!M43 -> 186.7568 | N10: =+Drivers!N124*IS!N43 -> 199.5313 | O10: =+Drivers!O124*IS!O43 -> 213.54404 | ... Q10: =+Drivers!Q124*IS!Q43 -> 242.88676
B11: ΔNWC | C11: =+FC!C13 -> 1325 | D11: =+FC!D13 -> -605 | E11: =+FC!E13 -> -846 | F11: =+FC!F13 -> -6234 | G11: =+FC!G13 -> -7208 | H11: =+SUM(H12:H16) -> -669.80549 | I11: =+SUM(I12:I16) -> 105.72115 | J11: =+SUM(J12:J16) -> 345.4533 | K11: =+SUM(K12:K16) -> 357.3238 | L11: =+SUM(L12:L16) -> 350.88853 | M11: =+SUM(M12:M16) -> 377.58402 | N11: =+SUM(N12:N16) -> 396.47568 | O11: =+SUM(O12:O16) -> 434.54764 | ... Q11: =+SUM(Q12:Q16) -> 459.59419
B12: ΔAccounts Receivable (AR) | H12: =+-(BS!H9-BS!G9) -> -751.77142 | I12: =+-(BS!I9-BS!H9) -> -54.971017 | J12: =+-(BS!J9-BS!I9) -> -194.91221 | K12: =+-(BS!K9-BS!J9) -> -204.67525 | L12: =+-(BS!L9-BS!K9) -> -195.55832 | M12: =+-(BS!M9-BS!L9) -> -209.9379 | N12: =+-(BS!N9-BS!M9) -> -220.18056 | O12: =+-(BS!O9-BS!N9) -> -241.30121 | ... Q12: =+-(BS!Q9-BS!P9) -> -254.32256
B13: ΔInventory | H13: =+-(BS!H10-BS!G10) -> -258.128 | I13: =+-(BS!I10-BS!H10) -> -67.929245 | J13: =+-(BS!J10-BS!I10) -> -240.85854 | K13: =+-(BS!K10-BS!J10) -> -252.92301 | L13: =+-(BS!L10-BS!K10) -> -241.65696 | M13: =+-(BS!M10-BS!L10) -> -259.42622 | N13: =+-(BS!N10-BS!M10) -> -272.08336 | O13: =+-(BS!O10-BS!N10) -> -298.18275 | ... Q13: =+-(BS!Q10-BS!P10) -> -314.2736
B14: ΔAccounts Payable (AP) | H14: =+(BS!H24-BS!G24) -> 233.04441 | I14: =+(BS!I24-BS!H24) -> 85.319648 | J14: =+(BS!J24-BS!I24) -> 302.52016 | K14: =+(BS!K24-BS!J24) -> 317.67323 | L14: =+(BS!L24-BS!K24) -> 303.52298 | M14: =+(BS!M24-BS!L24) -> 325.84131 | N14: =+(BS!N24-BS!M24) -> 341.73877 | O14: =+(BS!O24-BS!N24) -> 374.5198 | ... Q14: =+(BS!Q24-BS!P24) -> 394.73003
B15: ΔAccruals | H15: =+(BS!H25-BS!G25) -> 190.5564 | I15: =+(BS!I25-BS!H25) -> 126.55057 | J15: =+(BS!J25-BS!I25) -> 448.71375 | K15: =+(BS!K25-BS!J25) -> 471.18957 | L15: =+(BS!L25-BS!K25) -> 450.20118 | M15: =+(BS!M25-BS!L25) -> 483.3049 | N15: =+(BS!N25-BS!M25) -> 506.88485 | O15: =+(BS!O25-BS!N25) -> 555.50739 | ... Q15: =+(BS!Q25-BS!P25) -> 585.48426
B16: ΔTaxes Payable | H16: =+(BS!H26-BS!G26) -> -83.506877 | I16: =+(BS!I26-BS!H26) -> 16.751193 | J16: =+(BS!J26-BS!I26) -> 29.990144 | K16: =+(BS!K26-BS!J26) -> 26.059265 | L16: =+(BS!L26-BS!K26) -> 34.37964 | M16: =+(BS!M26-BS!L26) -> 37.801939 | N16: =+(BS!N26-BS!M26) -> 40.11598 | O16: =+(BS!O26-BS!N26) -> 44.004407 | ... Q16: =+(BS!Q26-BS!P26) -> 47.976057
B17: CFO | C17: =+FC!C16 -> 12625 | D17: =+FC!D16 -> 11018 | E17: =+FC!E16 -> 11599 | F17: =+FC!F16 -> 6805 | G17: =+FC!G16 -> 7408 | H17: =+SUM(H7:H11) -> 11419.12 | I17: =+SUM(I7:I11) -> 12707.688 | J17: =+SUM(J7:J11) -> 13753.733 | K17: =+SUM(K7:K11) -> 14660.826 | L17: =+SUM(L7:L11) -> 15590.593 | M17: =+SUM(M7:M11) -> 16624.234 | N17: =+SUM(N7:N11) -> 17710.542 | O17: =+SUM(O7:O11) -> 18919.396 | ... Q17: =+SUM(Q7:Q11) -> 21388.889
B19: Cash From Investing (CFI)
B21: CapEx | C21: =+FC!C23 -> -1367 | D21: =+FC!D23 -> -1484 | E21: =+FC!E23 -> -1852 | F21: =+FC!F23 -> -2064 | G21: =+FC!G23 -> -2112 | H21: =+-Drivers!H108*IS!H5 -> -2103.0741 | I21: =+-Drivers!I108*IS!I5 -> -2133.5794 | J21: =+-Drivers!J108*IS!J5 -> -2241.7429 | K21: =+-Drivers!K108*IS!K5 -> -2355.3242 | L21: =+-Drivers!L108*IS!L5 -> -2463.8462 | M21: =+-Drivers!M108*IS!M5 -> -2580.3479 | N21: =+-Drivers!N108*IS!N5 -> -2702.5337 | O21: =+-Drivers!O108*IS!O5 -> -2836.44 | ... Q21: =+-Drivers!Q108*IS!Q5 -> -3107.9602
B22: Acquisitions | C22: =+FC!C29 -> -2586 | D22: =+FC!D29 -> 385 | E22: =+FC!E29 -> 368 | F22: =+FC!F29 -> 3170 | G22: =+FC!G29 -> 3106 | H22: =+Drivers!H59 -> 0 | I22: =+Drivers!I59 -> 0 | J22: =+Drivers!J59 -> 0 | K22: =+Drivers!K59 -> 0 | L22: =+Drivers!L59 -> 0 | M22: =+Drivers!M59 -> 0 | N22: =+Drivers!N59 -> 0 | O22: =+Drivers!O59 -> 0 | ... Q22: =+Drivers!Q59 -> 0
B23: Other | C23: =+FC!C33 -> 1080 | D23: =+FC!D33 -> 261 | E23: =+FC!E33 -> -1939 | F23: =+FC!F33 -> 1378 | G23: =+FC!G33 -> -1074 | H23: =0 -> 0 | I23: =0 -> 0 | J23: =0 -> 0 | K23: =0 -> 0 | L23: =0 -> 0 | M23: =0 -> 0 | N23: =0 -> 0 | O23: =0 -> 0 | ... Q23: =0 -> 0
B24: CFI | C24: =+FC!C35 -> -2765 | D24: =+FC!D35 -> -763 | E24: =+FC!E35 -> -3349 | F24: =+FC!F35 -> 2524 | G24: =+FC!G35 -> -67 | H24: =+SUM(H21:H23) -> -2103.0741 | I24: =+SUM(I21:I23) -> -2133.5794 | J24: =+SUM(J21:J23) -> -2241.7429 | K24: =+SUM(K21:K23) -> -2355.3242 | L24: =+SUM(L21:L23) -> -2463.8462 | M24: =+SUM(M21:M23) -> -2580.3479 | N24: =+SUM(N21:N23) -> -2702.5337 | O24: =+SUM(O21:O23) -> -2836.44 | ... Q24: =+SUM(Q21:Q23) -> -3107.9602
B26: Cash From Financing (CFF)
B28: Dividends Paid | C28: =+FC!C38 -> -7252 | D28: =+FC!D38 -> -7616 | E28: =+FC!E38 -> -7952 | F28: =+FC!F38 -> -8359 | G28: =+FC!G38 -> -8779 | H28: =+-Drivers!H120*IS!H51 -> -7708.8867 | I28: =+-Drivers!I120*IS!I51 -> -8001.3784 | J28: =+-Drivers!J120*IS!J51 -> -8525.0346 | K28: =+-Drivers!K120*IS!K51 -> -8980.054 | L28: =+-Drivers!L120*IS!L51 -> -9580.355 | M28: =+-Drivers!M120*IS!M51 -> -10240.412 | N28: =+-Drivers!N120*IS!N51 -> -10940.875 | O28: =+-Drivers!O120*IS!O51 -> -11709.234 | ... Q28: =+-Drivers!Q120*IS!Q51 -> -13318.18
B29: ΔLTDebt | C29: =+FC!C39 -> 228 | D29: =+FC!D39 -> -958 | E29: =+FC!E39 -> 1857 | F29: =+FC!F39 -> 2528 | G29: =+FC!G39 -> 13 | H29: =+(BS!H31-BS!G31)+(BS!H30-BS!G30)+(BS!H27-BS!G27) -> -2143 | I29: =+(BS!I31-BS!H31)+(BS!I30-BS!H30)+(BS!I27-BS!H27) -> 0 | J29: =+(BS!J31-BS!I31)+(BS!J30-BS!I30)+(BS!J27-BS!I27) -> 0 | K29: =+(BS!K31-BS!J31)+(BS!K30-BS!J30)+(BS!K27-BS!J27) -> 0 | L29: =+(BS!L31-BS!K31)+(BS!L30-BS!K30)+(BS!L27-BS!K27) -> 0 | M29: =+(BS!M31-BS!L31)+(BS!M30-BS!L30)+(BS!M27-BS!L27) -> 0 | N29: =+(BS!N31-BS!M31)+(BS!N30-BS!M30)+(BS!N27-BS!M27) -> 0 | O29: =+(BS!O31-BS!N31)+(BS!O30-BS!N30)+(BS!O27-BS!N27) -> 0 | ... Q29: =+(BS!Q31-BS!P31)+(BS!Q30-BS!P30)+(BS!Q27-BS!P27) -> 0
B30: ΔLease Liabilities | H30: =+(BS!H32-BS!G32) -> 38.450682 | I30: =+(BS!I32-BS!H32) -> 25.535515 | J30: =+(BS!J32-BS!I32) -> 90.541958 | K30: =+(BS!K32-BS!J32) -> 95.077156 | L30: =+(BS!L32-BS!K32) -> 90.842095 | M30: =+(BS!M32-BS!L32) -> 97.521799 | N30: =+(BS!N32-BS!M32) -> 102.27979 | O30: =+(BS!O32-BS!N32) -> 112.0909 | ... Q30: =+(BS!Q32-BS!P32) -> 118.13966
B31: Share Buybacks | C31: =+FC!C40 -> 591 | D31: =+FC!D40 -> -581 | E31: =+FC!E40 -> -1750 | F31: =+FC!F40 -> -1048 | G31: =+FC!G40 -> -433 | H31: =-MAX(0,(H35+H17+H24+H28+H29+H30)-Drivers!$H$141) -> 0 | I31: =-MAX(0,(I35+I17+I24+I28+I29+I30)-Drivers!$H$141) -> -2370.8757 | J31: =-MAX(0,(J35+J17+J24+J28+J29+J30)-Drivers!$H$141) -> -3077.4972 | K31: =-MAX(0,(K35+K17+K24+K28+K29+K30)-Drivers!$H$141) -> -3420.5248 | L31: =-MAX(0,(L35+L17+L24+L28+L29+L30)-Drivers!$H$141) -> -3637.2336 | M31: =-MAX(0,(M35+M17+M24+M28+M29+M30)-Drivers!$H$141) -> -3900.9956 | N31: =-MAX(0,(N35+N17+N24+N28+N29+N30)-Drivers!$H$141) -> -4169.4131 | O31: =-MAX(0,(O35+O17+O24+O28+O29+O30)-Drivers!$H$141) -> -4485.8129 | ... Q31: =-MAX(0,(Q35+Q17+Q24+Q28+Q29+Q30)-Drivers!$H$141) -> -5080.8887
B32: CFF | C32: =+FC!C45 -> -6786 | D32: =+FC!D45 -> -10250 | E32: =+FC!E45 -> -8310 | F32: =+FC!F45 -> -6910 | G32: =+FC!G45 -> -8140 | H32: =+SUM(H28:H31) -> -9813.4361 | I32: =+SUM(I28:I31) -> -10346.719 | J32: =+SUM(J28:J31) -> -11511.99 | K32: =+SUM(K28:K31) -> -12305.502 | L32: =+SUM(L28:L31) -> -13126.746 | M32: =+SUM(M28:M31) -> -14043.886 | N32: =+SUM(N28:N31) -> -15008.009 | O32: =+SUM(O28:O31) -> -16082.956 | ... Q32: =+SUM(Q28:Q31) -> -18280.929
B34: Net chage in cash and equivalents | C34: =+C17+C24+C32+FC!C47 -> 2915 | D34: =+D17+D24+D32+FC!D47 -> -200 | E34: =+E17+E24+E32+FC!E47 -> -133 | F34: =+F17+F24+F32+FC!F47 -> 1796 | G34: =+G17+G24+G32+FC!G47 -> -478 | H34: =+H17+H24+H32 -> -497.39015 | I34: =+I17+I24+I32 -> 227.39015 | J34: =+J17+J24+J32 -> 0 | K34: =+K17+K24+K32 -> 0 | L34: =+L17+L24+L32 -> 0 | M34: =+M17+M24+M32 -> 0 | N34: =+N17+N24+N32 -> 0 | O34: =+O17+O24+O32 -> 0 | ... Q34: =+Q17+Q24+Q32 -> 0
B35: Cash and equivalents beginning | C35: =+'Balance Sheet'!C8-C34 -> 6769 | D35: =+C36 -> 9684 | E35: =+D36 -> 9484 | F35: =+E36 -> 9351 | G35: =+F36 -> 11147 | H35: =+'Balance Sheet'!G8 -> 10270 | I35: =+H36 -> 9772.6098 | J35: =+I36 -> 10000 | K35: =+J36 -> 10000 | L35: =+K36 -> 10000 | M35: =+L36 -> 10000 | N35: =+M36 -> 10000 | O35: =+N36 -> 10000 | P35: =+O36 -> 10000 | Q35: =+P36 -> 10000
B36: Cash and equivalents end | C36: =+C35+C34 -> 9684 | D36: =+D35+D34 -> 9484 | E36: =+E35+E34 -> 9351 | F36: =+F35+F34 -> 11147 | G36: =+G35+G34 -> 10669 | H36: =+H35+H34 -> 9772.6098 | I36: =+I35+I34 -> 10000 | J36: =+J35+J34 -> 10000 | ... Q36: =+Q35+Q34 -> 10000
B38: Free Cash Flow | C38: =+C17+C24 -> 9860 | D38: =+D17+D24 -> 10255 | E38: =+E17+E24 -> 8250 | F38: =+F17+F24 -> 9329 | G38: =+G17+G24 -> 7341 | H38: =+H17+H24 -> 9316.0459 | I38: =+I17+I24 -> 10574.109 | J38: =+J17+J24 -> 11511.99 | ... Q38: =+Q17+Q24 -> 18280.929
B39: FCF Margin % | C39: =+C38/IS!C5 -> 0.25505717 | D39: =+D38/IS!D5 -> 0.23823352 | E39: =+E38/IS!E5 -> 0.18019395 | F39: =+F38/IS!F5 -> 0.1989253 | G39: =+G38/IS!G5 -> 0.15274021 | H39: =+H38/IS!H5 -> 0.18960032 | I39: =+I38/IS!I5 -> 0.2121275 | J39: =+J38/IS!J5 -> 0.21979946 | ... Q39: =+Q38/IS!Q5 -> 0.2517589

Sheet BS
C1: 2021 | D1: 2022 | E1: 2023 | F1: 2024 | G1: 2025 | H1: 2026 | I1: 2027 | J1: 2028 | K1: 2029 | L1: 2030 | M1: 2031 | N1: 2032 | O1: 2033 | P1: 2034 | Q1: 2035
B3: Balance Sheet
B5: Assets
B7: Cash & Equivalents | C7: =+'Balance Sheet'!C8 -> 9684 | D7: =+'Balance Sheet'!D8 -> 9519 | E7: =+'Balance Sheet'!E8 -> 9366 | F7: =+'Balance Sheet'!F8 -> 10828 | G7: =+'Balance Sheet'!G8 -> 10270 | H7: =+CF!H36 -> 9772.6098 | I7: =+CF!I36 -> 10000 | J7: =+CF!J36 -> 10000 | K7: =+CF!K36 -> 10000 | L7: =+CF!L36 -> 10000 | M7: =+CF!M36 -> 10000 | N7: =+CF!N36 -> 10000 | O7: =+CF!O36 -> 10000 | ... Q7: =+CF!Q36 -> 10000
B8: Short term Investments (STI) | C8: =+'Balance Sheet'!C9 -> 2941 | D8: =+'Balance Sheet'!D9 -> 2112 | E8: =+'Balance Sheet'!E9 -> 4297 | F8: =+'Balance Sheet'!F9 -> 3743 | G8: =+'Balance Sheet'!G9 -> 5536 | H8: =+G8 -> 5536 | I8: =+H8 -> 5536 | J8: =+I8 -> 5536 | K8: =+J8 -> 5536 | L8: =+K8 -> 5536 | M8: =+L8 -> 5536 | N8: =+M8 -> 5536 | O8: =+N8 -> 5536 | ... Q8: =+P8 -> 5536
B9: Accounts Receivable (AR) | C9: =+'Balance Sheet'!C10 -> 3512 | D9: =+'Balance Sheet'!D10 -> 3487 | E9: =+'Balance Sheet'!E10 -> 3410 | F9: =+'Balance Sheet'!F10 -> 3569 | G9: =+'Balance Sheet'!G10 -> 3038 | H9: =+Drivers!H78*IS!H5/365 -> 3789.7714 | I9: =+Drivers!I78*IS!I5/365 -> 3844.7424 | J9: =+Drivers!J78*IS!J5/365 -> 4039.6546 | K9: =+Drivers!K78*IS!K5/365 -> 4244.3299 | L9: =+Drivers!L78*IS!L5/365 -> 4439.8882 | M9: =+Drivers!M78*IS!M5/365 -> 4649.8261 | N9: =+Drivers!N78*IS!N5/365 -> 4870.0067 | O9: =+Drivers!O78*IS!O5/365 -> 5111.3079 | ... Q9: =+Drivers!Q78*IS!Q5/365 -> 5600.5914
B10: Inventory | C10: =+'Balance Sheet'!C13 -> 3414 | D10: =+'Balance Sheet'!D13 -> 4233 | E10: =+'Balance Sheet'!E13 -> 4424 | F10: =+'Balance Sheet'!F13 -> 4728 | G10: =+'Balance Sheet'!G13 -> 4425 | H10: =+Drivers!H90*IS!H16/365 -> 4683.128 | I10: =+Drivers!I90*IS!I16/365 -> 4751.0572 | J10: =+Drivers!J90*IS!J16/365 -> 4991.9158 | K10: =+Drivers!K90*IS!K16/365 -> 5244.8388 | L10: =+Drivers!L90*IS!L16/365 -> 5486.4958 | M10: =+Drivers!M90*IS!M16/365 -> 5745.922 | N10: =+Drivers!N90*IS!N16/365 -> 6018.0053 | O10: =+Drivers!O90*IS!O16/365 -> 6316.1881 | ... Q10: =+Drivers!Q90*IS!Q16/365 -> 6920.8096
B11: Other Current Assets | C11: =+'Balance Sheet'!C18 -> 2994 | D11: =+'Balance Sheet'!D18 -> 3240 | E11: =+'Balance Sheet'!E18 -> 5235 | F11: =+'Balance Sheet'!F18 -> 3129 | G11: =+'Balance Sheet'!G18 -> 7775 | H11: =+G11 -> 7775 | I11: =+H11 -> 7775 | J11: =+I11 -> 7775 | K11: =+J11 -> 7775 | L11: =+K11 -> 7775 | M11: =+L11 -> 7775 | N11: =+M11 -> 7775 | O11: =+N11 -> 7775 | ... Q11: =+P11 -> 7775
B12: Total Current Assets | C12: =+SUM(C7:C11) -> 22545 | D12: =+SUM(D7:D11) -> 22591 | E12: =+SUM(E7:E11) -> 26732 | F12: =+SUM(F7:F11) -> 25997 | G12: =+SUM(G7:G11) -> 31044 | H12: =+SUM(H7:H11) -> 31556.509 | I12: =+SUM(I7:I11) -> 31906.8 | J12: =+SUM(J7:J11) -> 32342.57 | ... Q12: =+SUM(Q7:Q11) -> 35832.401
B14: Plant, Property & Equipement | C14: =+'Balance Sheet'!C24 -> 11338 | D14: =+'Balance Sheet'!D24 -> 11247 | E14: =+'Balance Sheet'!E24 -> 10564 | F14: =+'Balance Sheet'!F24 -> 11485 | G14: =+'Balance Sheet'!G24 -> 11310 | H14: =+G14+CF!H21*-1-IS!H24 -> 12270.873 | I14: =+H14+CF!I21*-1-IS!I24 -> 13157.852 | J14: =+I14+CF!J21*-1-IS!J24 -> 14085.567 | K14: =+J14+CF!K21*-1-IS!K24 -> 14876.339 | L14: =+K14+CF!L21*-1-IS!L24 -> 15684.358 | M14: =+L14+CF!M21*-1-IS!M24 -> 16530.584 | N14: =+M14+CF!N21*-1-IS!N24 -> 17416.881 | O14: =+N14+CF!O21*-1-IS!O24 -> 18347.093 | ... Q14: =+P14+CF!Q21*-1-IS!Q24 -> 20339.322
B15: Goodwill & Intangibles | C15: =+'Balance Sheet'!C30+'Balance Sheet'!C31 -> 53976 | D15: =+'Balance Sheet'!D30+'Balance Sheet'!D31 -> 52413 | E15: =+'Balance Sheet'!E30+'Balance Sheet'!E31 -> 51581 | F15: =+'Balance Sheet'!F30+'Balance Sheet'!F31 -> 49579 | G15: =+'Balance Sheet'!G30+'Balance Sheet'!G31 -> 43513 | H15: =+G15-CF!H22 -> 43513 | I15: =+H15-CF!I22 -> 43513 | J15: =+I15-CF!J22 -> 43513 | K15: =+J15-CF!K22 -> 43513 | L15: =+K15-CF!L22 -> 43513 | M15: =+L15-CF!M22 -> 43513 | N15: =+M15-CF!N22 -> 43513 | O15: =+N15-CF!O22 -> 43513 | ... Q15: =+P15-CF!Q22 -> 43513
B16: Other LT assets | C16: =+'Balance Sheet'!C39-C12-C14-C15 -> 6495 | D16: =+'Balance Sheet'!D39-D12-D14-D15 -> 6512 | E16: =+'Balance Sheet'!E39-E12-E14-E15 -> 8826 | F16: =+'Balance Sheet'!F39-F12-F14-F15 -> 13488 | G16: =+'Balance Sheet'!G39-G12-G14-G15 -> 18949 | H16: =+G16 -> 18949 | I16: =+H16 -> 18949 | J16: =+I16 -> 18949 | K16: =+J16 -> 18949 | L16: =+K16 -> 18949 | M16: =+L16 -> 18949 | N16: =+M16 -> 18949 | O16: =+N16 -> 18949 | ... Q16: =+P16 -> 18949
B17: Total Non-current Assets | C17: =+SUM(C14:C16) -> 71809 | D17: =+SUM(D14:D16) -> 70172 | E17: =+SUM(E14:E16) -> 70971 | F17: =+SUM(F14:F16) -> 74552 | G17: =+SUM(G14:G16) -> 73772 | H17: =+SUM(H14:H16) -> 74732.873 | I17: =+SUM(I14:I16) -> 75619.852 | J17: =+SUM(J14:J16) -> 76547.567 | ... Q17: =+SUM(Q14:Q16) -> 82801.322
B19: Total Assets | C19: =+C12+C17 -> 94354 | D19: =+D12+D17 -> 92763 | E19: =+E12+E17 -> 97703 | F19: =+F12+F17 -> 100549 | G19: =+G12+G17 -> 104816 | H19: =+H12+H17 -> 106289.38 | I19: =+I12+I17 -> 107526.65 | J19: =+J12+J17 -> 108890.14 | ... Q19: =+Q12+Q17 -> 118633.72
B22: Liabilities
B24: Accounts Payable (AP) | C24: =+'Balance Sheet'!C43 -> 4602 | D24: =+'Balance Sheet'!D43 -> 5307 | E24: =+'Balance Sheet'!E43 -> 5590 | F24: =+'Balance Sheet'!F43 -> 5468 | G24: =+'Balance Sheet'!G43 -> 5649 | H24: =+Drivers!H84*IS!H5 -> 5882.0444 | I24: =+Drivers!I84*IS!I5 -> 5967.3641 | J24: =+Drivers!J84*IS!J5 -> 6269.8842 | K24: =+Drivers!K84*IS!K5 -> 6587.5574 | L24: =+Drivers!L84*IS!L5 -> 6891.0804 | M24: =+Drivers!M84*IS!M5 -> 7216.9217 | N24: =+Drivers!N84*IS!N5 -> 7558.6605 | O24: =+Drivers!O84*IS!O5 -> 7933.1803 | ... Q24: =+Drivers!Q84*IS!Q5 -> 8692.5896
B25: Accruals | C25: =+'Balance Sheet'!C46 -> 9652 | D25: =+'Balance Sheet'!D46 -> 9925 | E25: =+'Balance Sheet'!E46 -> 9243 | F25: =+'Balance Sheet'!F46 -> 15811 | G25: =+'Balance Sheet'!G46 -> 8534 | H25: =+Drivers!H96*IS!H5 -> 8724.5564 | I25: =+Drivers!I96*IS!I5 -> 8851.107 | J25: =+Drivers!J96*IS!J5 -> 9299.8207 | K25: =+Drivers!K96*IS!K5 -> 9771.0103 | L25: =+Drivers!L96*IS!L5 -> 10221.211 | M25: =+Drivers!M96*IS!M5 -> 10704.516 | N25: =+Drivers!N96*IS!N5 -> 11211.401 | O25: =+Drivers!O96*IS!O5 -> 11766.909 | ... Q25: =+Drivers!Q96*IS!Q5 -> 12893.304
B26: Taxes Payable | C26: =+'Balance Sheet'!C44 -> 686 | D26: =+'Balance Sheet'!D44 -> 1203 | E26: =+'Balance Sheet'!E44 -> 1569 | F26: =+'Balance Sheet'!F44 -> 1387 | G26: =+'Balance Sheet'!G44 -> 525 | H26: =+Drivers!H102*IS!H43 -> 441.49312 | I26: =+Drivers!I102*IS!I43 -> 458.24432 | J26: =+Drivers!J102*IS!J43 -> 488.23446 | K26: =+Drivers!K102*IS!K43 -> 514.29372 | L26: =+Drivers!L102*IS!L43 -> 548.67336 | M26: =+Drivers!M102*IS!M43 -> 586.4753 | N26: =+Drivers!N102*IS!N43 -> 626.59128 | O26: =+Drivers!O102*IS!O43 -> 670.59569 | ... Q26: =+Drivers!Q102*IS!Q43 -> 762.74111
B27: Short-term debt | C27: =+'Balance Sheet'!C47 -> 4955 | D27: =+'Balance Sheet'!D47 -> 3113 | E27: =+'Balance Sheet'!E47 -> 6878 | F27: =+'Balance Sheet'!F47 -> 2437 | G27: =+'Balance Sheet'!G47 -> 3694 | H27: =+Debt!$C$7 -> 1551 | I27: =+Debt!$C$7 -> 1551 | J27: =+Debt!$C$7 -> 1551 | K27: =+Debt!$C$7 -> 1551 | L27: =+Debt!$C$7 -> 1551 | M27: =+Debt!$C$7 -> 1551 | N27: =+Debt!$C$7 -> 1551 | O27: =+Debt!$C$7 -> 1551 | ... Q27: =+Debt!$C$7 -> 1551
B28: Total Current Liabilities | C28: =+'Balance Sheet'!C58 -> 19950 | D28: =+'Balance Sheet'!D58 -> 19724 | E28: =+'Balance Sheet'!E58 -> 23571 | F28: =+'Balance Sheet'!F58 -> 25249 | G28: =+'Balance Sheet'!G58 -> 21281 | H28: =+SUM(H24:H27)+'Balance Sheet'!$G$53 -> 19478.094 | I28: =+SUM(I24:I27)+'Balance Sheet'!$G$53 -> 19706.715 | J28: =+SUM(J24:J27)+'Balance Sheet'!$G$53 -> 20487.939 | K28: =+SUM(K24:K27)+'Balance Sheet'!$G$53 -> 21302.861 | L28: =+SUM(L24:L27)+'Balance Sheet'!$G$53 -> 22090.965 | M28: =+SUM(M24:M27)+'Balance Sheet'!$G$53 -> 22937.913 | N28: =+SUM(N24:N27)+'Balance Sheet'!$G$53 -> 23826.653 | O28: =+SUM(O24:O27)+'Balance Sheet'!$G$53 -> 24800.685 | ... Q28: =+SUM(Q24:Q27)+'Balance Sheet'!$G$53 -> 26778.635
B30: Current portion LTD | C30: =+'Balance Sheet'!C52 -> 1338 | D30: =+'Balance Sheet'!D52 -> 399 | E30: =+'Balance Sheet'!E52 -> 1960 | F30: =+'Balance Sheet'!F52 -> 648 | G30: =+'Balance Sheet'!G52 -> 1822 | H30: =+Debt!C29 -> 1822 | I30: =+Debt!D29 -> 381 | J30: =+Debt!E29 -> 0 | K30: =+Debt!F29 -> 0 | L30: =+Debt!G29 -> 0 | M30: =+Debt!$G$29 -> 0 | N30: =+Debt!$G$29 -> 0 | O30: =+Debt!$G$29 -> 0 | P30: =+Debt!$G$29 -> 0 | Q30: =+Debt!$G$29 -> 0
B31: Long-term debt | C31: =+'Balance Sheet'!C60 -> 38116 | D31: =+'Balance Sheet'!D60 -> 36377 | E31: =+'Balance Sheet'!E60 -> 35547 | F31: =+'Balance Sheet'!F60 -> 42375 | G31: =+'Balance Sheet'!G60 -> 42119 | H31: =+Debt!C46-H30 -> 42119 | I31: =+Debt!D46-I30 -> 43560 | J31: =+Debt!E46-J30 -> 43941 | K31: =+Debt!F46-K30 -> 43941 | L31: =+Debt!G46-L30 -> 43941 | M31: =+Debt!H46-M30 -> 43941 | N31: =+Debt!I46-N30 -> 43941 | O31: =+Debt!J46-O30 -> 43941 | ... Q31: =+Debt!L46-Q30 -> 43941
B32: Lease liabilities (ST + LT) | C32: =+'Balance Sheet'!C49+'Balance Sheet'!C61 -> 1471 | D32: =+'Balance Sheet'!D49+'Balance Sheet'!D61 -> 1454 | E32: =+'Balance Sheet'!E49+'Balance Sheet'!E61 -> 1362 | F32: =+'Balance Sheet'!F49+'Balance Sheet'!F61 -> 1213 | G32: =+'Balance Sheet'!G49+'Balance Sheet'!G61 -> 1722 | H32: =+Debt!C54 -> 1760.4507 | I32: =+Debt!D54 -> 1785.9862 | J32: =+Debt!E54 -> 1876.5282 | K32: =+Debt!F54 -> 1971.6053 | L32: =+Debt!G54 -> 2062.4474 | M32: =+Debt!H54 -> 2159.9692 | N32: =+Debt!I54 -> 2262.249 | O32: =+Debt!J54 -> 2374.3399 | ... Q32: =+Debt!L54 -> 2601.6252
B33: Other LT liabilities | C33: =+'Balance Sheet'!C72-C28-C30-C31-C32 -> 8619 | D33: =+'Balance Sheet'!D72-D28-D30-D31-D32 -> 8983 | E33: =+'Balance Sheet'!E72-E28-E30-E31-E32 -> 7783 | F33: =+'Balance Sheet'!F72-F28-F30-F31-F32 -> 4692 | G33: =+'Balance Sheet'!G72-G28-G30-G31-G32 -> 3597 | H33: =+G33+CF!H10 -> 3737.5888 | I33: =+H33+CF!I10 -> 3883.5118 | J33: =+I33+CF!J10 -> 4038.9848 | K33: =+J33+CF!K10 -> 4202.7562 | L33: =+K33+CF!L10 -> 4377.4753 | M33: =+L33+CF!M10 -> 4564.2321 | N33: =+M33+CF!N10 -> 4763.7634 | O33: =+N33+CF!O10 -> 4977.3075 | ... Q33: =+P33+CF!Q10 -> 5447.8035
B34: Total Non-current Liabilities | C34: =+'Balance Sheet'!C71 -> 49544 | D34: =+'Balance Sheet'!D71 -> 47213 | E34: =+'Balance Sheet'!E71 -> 46652 | F34: =+'Balance Sheet'!F71 -> 48928 | G34: =+'Balance Sheet'!G71 -> 49260 | H34: =+SUM(H30:H33) -> 49439.039 | I34: =+SUM(I30:I33) -> 49610.498 | J34: =+SUM(J30:J33) -> 49856.513 | K34: =+SUM(K30:K33) -> 50115.361 | L34: =+SUM(L30:L33) -> 50380.923 | M34: =+SUM(M30:M33) -> 50665.201 | N34: =+SUM(N30:N33) -> 50967.012 | O34: =+SUM(O30:O33) -> 51292.647 | ... Q34: =+SUM(Q30:Q33) -> 51990.429
B36: Total Liabilities | C36: =+'Balance Sheet'!C72 -> 69494 | D36: =+'Balance Sheet'!D72 -> 66937 | E36: =+'Balance Sheet'!E72 -> 70223 | F36: =+'Balance Sheet'!F72 -> 74177 | G36: =+'Balance Sheet'!G72 -> 70541 | H36: =+H28+H34 -> 68917.133 | I36: =+I28+I34 -> 69317.213 | J36: =+J28+J34 -> 70344.452 | K36: =+K28+K34 -> 71418.223 | L36: =+L28+L34 -> 72471.888 | M36: =+M28+M34 -> 73603.115 | N36: =+N28+N34 -> 74793.665 | O36: =+O28+O34 -> 76093.332 | ... Q36: =+Q28+Q34 -> 78769.064
B38: Equity
B40: Common stock + APIC | C40: =+'Balance Sheet'!C74 -> 19876 | D40: =+'Balance Sheet'!D74 -> 20582 | E40: =+'Balance Sheet'!E74 -> 20969 | F40: =+'Balance Sheet'!F74 -> 21561 | G40: =+'Balance Sheet'!G74 -> 22341 | H40: =+G40+CF!H9 -> 22626.824 | I40: =+H40+CF!I9 -> 22916.793 | J40: =+I40+CF!J9 -> 23221.463 | K40: =+J40+CF!K9 -> 23541.569 | L40: =+K40+CF!L9 -> 23876.425 | M40: =+L40+CF!M9 -> 24227.113 | N40: =+M40+CF!N9 -> 24594.408 | O40: =+N40+CF!O9 -> 24979.902 | ... Q40: =+P40+CF!Q9 -> 25805.511
B41: Treasury Stock | C41: =+-'Balance Sheet'!C77 -> -51641 | D41: =+-'Balance Sheet'!D77 -> -52601 | E41: =+-'Balance Sheet'!E77 -> -54535 | F41: =+-'Balance Sheet'!F77 -> -55916 | G41: =+-'Balance Sheet'!G77 -> -56423 | H41: =+G41-CF!H31*-1 -> -56423 | I41: =+H41-CF!I31*-1 -> -58793.876 | J41: =+I41-CF!J31*-1 -> -61871.373 | K41: =+J41-CF!K31*-1 -> -65291.898 | L41: =+K41-CF!L31*-1 -> -68929.131 | M41: =+L41-CF!M31*-1 -> -72830.127 | N41: =+M41-CF!N31*-1 -> -76999.54 | O41: =+N41-CF!O31*-1 -> -81485.353 | ... Q41: =+P41-CF!Q31*-1 -> -91309.308
B42: Retained Earnings | C42: =+'Balance Sheet'!C78+'Balance Sheet'!C79 -> 54764 | D42: =+'Balance Sheet'!D78+'Balance Sheet'!D79 -> 56124 | E42: =+'Balance Sheet'!E78+'Balance Sheet'!E79 -> 59507 | F42: =+'Balance Sheet'!F78+'Balance Sheet'!F79 -> 59211 | G42: =+'Balance Sheet'!G78+'Balance Sheet'!G79 -> 66251 | H42: =+G42+IS!H51-CF!H28*-1 -> 69062.425 | I42: =+H42+IS!I51-CF!I28*-1 -> 71980.521 | J42: =+I42+IS!J51-CF!J28*-1 -> 75089.595 | K42: =+J42+IS!K51-CF!K28*-1 -> 78364.613 | L42: =+K42+IS!L51-CF!L28*-1 -> 81858.561 | M42: =+L42+IS!M51-CF!M28*-1 -> 85593.231 | N42: =+M42+IS!N51-CF!N28*-1 -> 89583.36 | O42: =+N42+IS!O51-CF!O28*-1 -> 93853.708 | ... Q42: =+P42+IS!Q51-CF!Q28*-1 -> 103262.46
B43: Minority interest | C43: =+'Balance Sheet'!C81 -> 1861 | D43: =+'Balance Sheet'!D81 -> 1721 | E43: =+'Balance Sheet'!E81 -> 1539 | F43: =+'Balance Sheet'!F81 -> 1516 | G43: =+'Balance Sheet'!G81 -> 2106 | H43: =+G43+IS!H49 -> 2106 | I43: =+H43+IS!I49 -> 2106 | J43: =+I43+IS!J49 -> 2106 | K43: =+J43+IS!K49 -> 2106 | L43: =+K43+IS!L49 -> 2106 | M43: =+L43+IS!M49 -> 2106 | N43: =+M43+IS!N49 -> 2106 | O43: =+N43+IS!O49 -> 2106 | ... Q43: =+P43+IS!Q49 -> 2106
B44: Total Equity | C44: =+'Balance Sheet'!C82 -> 24860 | D44: =+'Balance Sheet'!D82 -> 25826 | E44: =+'Balance Sheet'!E82 -> 27480 | F44: =+'Balance Sheet'!F82 -> 26372 | G44: =+'Balance Sheet'!G82 -> 34275 | H44: =+SUM(H40:H43) -> 37372.249 | I44: =+SUM(I40:I43) -> 38209.439 | J44: =+SUM(J40:J43) -> 38545.685 | K44: =+SUM(K40:K43) -> 38720.285 | L44: =+SUM(L40:L43) -> 38911.854 | M44: =+SUM(M40:M43) -> 39096.218 | N44: =+SUM(N40:N43) -> 39284.228 | O44: =+SUM(O40:O43) -> 39454.257 | ... Q44: =+SUM(Q40:Q43) -> 39864.659
B46: Total Liabilities + Equity | C46: =+C36+C44 -> 94354 | D46: =+D36+D44 -> 92763 | E46: =+E36+E44 -> 97703 | F46: =+F36+F44 -> 100549 | G46: =+G36+G44 -> 104816 | H46: =+H36+H44 -> 106289.38 | I46: =+I36+I44 -> 107526.65 | J46: =+J36+J44 -> 108890.14 | ... Q46: =+Q36+Q44 -> 118633.72
B48: BS Check | C48: =+C19-C46 -> 0 | D48: =+D19-D46 -> 0 | E48: =+E19-E46 -> 0 | F48: =+F19-F46 -> 0 | G48: =+G19-G46 -> 0 | H48: =+H19-H46 -> 0 | I48: =+I19-I46 -> 0 | J48: =+J19-J46 -> 0 | ... Q48: =+Q19-Q46 -> 0

Sheet WACC
B2: WACC | F2: Comparable Companies Unlevered Betas
B3: Capital structure | F3: Company name | G3: TICKER | H3: Levered Beta | I3: Total Debt | J3: Equity | K3: TOTAL (D+E) | L3: D / E | M3: Tax Rate | N3: Unlevered Beta
B4: Total debt | D4: =+Debt!C57*1000000 -> 4.7252451e+10 | F4: KEURIG DR PEPPER INC. (XNAS:KDP) | G4: KDP | H4: 0.3822 | I4: 16141000000 | J4: 47193000000 | K4: =+I4+J4 -> 63334000000 | L4: =+I4/J4 -> 0.34202106 | M4: 0.226 | N4: =+H4*(J4/K4)+$D$21*(I4/K4) -> 0.28479434
B5: Total Equity | D5: 398889317790 | F5: Pepsico, Inc. (XNAS:PEP) | G5: PEP | H5: 0.3298 | I5: 40901000000 | J5: 185019345570 | K5: =+I5+J5 -> 225920345570 | L5: =+I5/J5 -> 0.22106337 | M5: 0.19 | N5: =+H5*(J5/K5)+$D$21*(I5/K5) -> 0.27009245
B6: Debt to Value | D6: =+D4/(D5+D4) -> 0.10591353 | F6: MONSTER BEVERAGE CORPORATION (XNAS:MNST) | G6: MNST | H6: 0.5268 | I6: 0 | J6: 90348379040 | K6: =+I6+J6 -> 90348379040 | L6: =+I6/J6 -> 0 | M6: 0.232 | N6: =+H6*(J6/K6)+$D$21*(I6/K6) -> 0.5268
B7: Equity to Value | D7: =+D5/(D5+D4) -> 0.89408647 | F7: CELSIUS HOLDINGS, INC. (XNAS:CELH) | G7: CELH | H7: 1.0037 | I7: 669926000 | J7: 7203906450 | K7: =+I7+J7 -> 7873832450 | L7: =+I7/J7 -> 0.092994822 | M7: 0.257 | N7: =+H7*(J7/K7)+$D$21*(I7/K7) -> 0.91830261
B8: D/E | D8: =+D4/D5 -> 0.11846006 | F8: NATIONAL BEVERAGE CORP. (XNAS:FIZZ) | G8: FIZZ | H8: 0.8348 | I8: 58936000 | J8: 3384193095 | K8: =+I8+J8 -> 3443129095 | L8: =+I8/J8 -> 0.017415082 | M8: 0.236 | N8: =+H8*(J8/K8)+$D$21*(I8/K8) -> 0.82051074
B9: E/D | D9: =+D5/D4 -> 8.4416641 | F9: Median All | H9: =+MEDIAN(H4:H8) -> 0.5268 | N9: =+MEDIAN(N4:N8) -> 0.5268
F10: Average All | H10: =+AVERAGE(H4:H8) -> 0.61546 | N10: =+AVERAGE(N4:N8) -> 0.56410003
B11: Cost of Equity | F11: Median Restricted | H11: =+MEDIAN(H4:H6) -> 0.3822 | N11: =+MEDIAN(N4:N6) -> 0.28479434
B12: Risk Free Rate | D12: 0.0425 | F12: Average Restricted | H12: =+AVERAGE(H4:H6) -> 0.41293333 | N12: =+AVERAGE(N4:N6) -> 0.36056226
B13: Implied Market Return | D13: =+D14+D12 -> 0.0952
B14: Equity to Risk Premium (ERP) | D14: 0.0527
B15: Company Beta | D15: =+D16*(1+D8)-D21*D8 -> 0.40327449
B16: Assets Beta | D16: =+N12 -> 0.36056226
B17: Cost of equity | D17: =+D12+D15*D14 -> 0.063752566
B19: Cost of Debt
B20: Corporate Marginal Tax Rate | D20: 0.21
B21: Debt Beta | D21: =+MAX((D22-D12)/(D13-D12),0) -> 0
B22: Interest expense % over debt | D22: =+Debt!C58/Debt!C57 -> 0.033388744
B23: After tax cost of debt | D23: =+D22*(1-D20) -> 0.026377108
B25: WACC | D25: =+D17*D7+D23*D6 -> 0.059793999
B26: Damodaran WACC | D26: 0.0589
B28: #VALUE! | D28: {=+_FV(B28,"Beta")} -> 0.2869

Sheet DCF + DDM
C2: 2021 | D2: 2022 | E2: 2023 | F2: 2024 | G2: 2025 | H2: 2026 | I2: 2027 | J2: 2028 | K2: 2029 | L2: 2030 | M2: 2031 | N2: 2032 | O2: 2033 | P2: 2034 | Q2: 2035
B3: EBIT | C3: =+IS!C27 -> 11109 | D3: =+IS!D27 -> 12600 | E3: =+IS!E27 -> 13336 | F3: =+IS!F27 -> 10647 | G3: =+IS!G27 -> 14315 | H3: =+IS!H27 -> 13944.62 | I3: =+IS!I27 -> 14463.399 | J3: =+IS!J27 -> 15330.194 | ... Q3: =+IS!Q27 -> 23394.528
B4: =+Drivers!B54 -> Mergers and Acquisitions | C4: =+Drivers!C54*-1 -> 1173 | D4: =+Drivers!D54*-1 -> -408 | E4: =+Drivers!E54*-1 -> -836 | F4: =+Drivers!F54*-1 -> -1377 | G4: =+Drivers!G54*-1 -> 654 | H4: =-Drivers!H58 -> -158.8 | I4: =-Drivers!I58 -> -158.8 | J4: =-Drivers!J58 -> -158.8 | K4: =-Drivers!K58 -> -158.8 | L4: =-Drivers!L58 -> -158.8 | M4: =-Drivers!M58 -> -158.8 | N4: =-Drivers!N58 -> -158.8 | O4: =-Drivers!O58 -> -158.8 | ... Q4: =-Drivers!Q58 -> -158.8
B5: =+Drivers!B61 -> Restructuring | C5: =+Drivers!C61*-1 -> -378 | D5: =+Drivers!D61*-1 -> -117 | E5: =+Drivers!E61*-1 -> -191 | F5: =+Drivers!F61*-1 -> -133 | G5: =+Drivers!G61*-1 -> -97 | H5: =+Drivers!H61*-1 -> -134.5 | I5: =+Drivers!I61*-1 -> -134.5 | J5: =+Drivers!J61*-1 -> -134.5 | ... Q5: =+Drivers!Q61*-1 -> -134.5
B6: NOPAT | C6: =+SUM(C3:C5)*(1-WACC!$D$20) -> 9404.16 | D6: =+SUM(D3:D5)*(1-WACC!$D$20) -> 9539.25 | E6: =+SUM(E3:E5)*(1-WACC!$D$20) -> 9724.11 | F6: =+SUM(F3:F5)*(1-WACC!$D$20) -> 7218.23 | G6: =+SUM(G3:G5)*(1-WACC!$D$20) -> 11748.88 | H6: =+SUM(H3:H5)*(1-WACC!$D$20) -> 10784.542 | I6: =+SUM(I3:I5)*(1-WACC!$D$20) -> 11194.378 | J6: =+SUM(J3:J5)*(1-WACC!$D$20) -> 11879.146 | ... Q6: =+SUM(Q3:Q5)*(1-WACC!$D$20) -> 18249.97
B7: =+IS!B24 -> Depreciation & Amortization | H7: =+IS!H24 -> 1142.2015 | I7: =+IS!I24 -> 1246.5997 | J7: =+IS!J24 -> 1314.0287 | K7: =+IS!K24 -> 1564.5518 | L7: =+IS!L24 -> 1655.8269 | M7: =+IS!M24 -> 1734.1218 | N7: =+IS!N24 -> 1816.2367 | O7: =+IS!O24 -> 1906.2284 | ... Q7: =+IS!Q24 -> 2088.7035
B8: =+CF!B21 -> CapEx | C8: =+CF!C21 -> -1367 | D8: =+CF!D21 -> -1484 | E8: =+CF!E21 -> -1852 | F8: =+CF!F21 -> -2064 | G8: =+CF!G21 -> -2112 | H8: =+CF!H21 -> -2103.0741 | I8: =+CF!I21 -> -2133.5794 | ... Q8: =+CF!Q21 -> -3107.9602
B9: =+CF!B11 -> ΔNWC | C9: =+CF!C11 -> 1325 | D9: =+CF!D11 -> -605 | E9: =+CF!E11 -> -846 | F9: =+CF!F11 -> -6234 | G9: =+CF!G11 -> -7208 | H9: =+CF!H11 -> -669.80549 | I9: =+CF!I11 -> 105.72115 | ... Q9: =+CF!Q11 -> 459.59419
B10: Free Cash Flow (FCFF) | C10: =+SUM(C6:C9) -> 9362.16 | D10: =+SUM(D6:D9) -> 7450.25 | E10: =+SUM(E6:E9) -> 7026.11 | F10: =+SUM(F6:F9) -> -1079.77 | G10: =+SUM(G6:G9) -> 2428.88 | H10: =+SUM(H6:H9) -> 9153.8644 | I10: =+SUM(I6:I9) -> 10413.12 | J10: =+SUM(J6:J9) -> 11296.885 | ... Q10: =+SUM(Q6:Q9) -> 17690.308
B12: Year | H12: 1 | I12: 2 | J12: 3 | K12: 4 | L12: 5 | M12: 6 | N12: 7 | O12: 8 | P12: 9 | Q12: 10
B13: Discount Factor | H13: =1/(1+WACC!$D$25)^H12 -> 0.9435796 | I13: =1/(1+WACC!$D$25)^I12 -> 0.89034247 | J13: =1/(1+WACC!$D$25)^J12 -> 0.84010899 | K13: =1/(1+WACC!$D$25)^K12 -> 0.79270971 | L13: =1/(1+WACC!$D$25)^L12 -> 0.74798471 | M13: =1/(1+WACC!$D$25)^M12 -> 0.70578312 | N13: =1/(1+WACC!$D$25)^N12 -> 0.66596255 | O13: =1/(1+WACC!$D$25)^O12 -> 0.62838868 | ... Q13: =1/(1+WACC!$D$25)^Q12 -> 0.55948113
B14: Discounted Cash Flow | H14: =+H13*H10 -> 8637.3997 | I14: =+I13*I10 -> 9271.2425 | J14: =+J13*J10 -> 9490.6149 | K14: =+K13*K10 -> 9553.1331 | L14: =+L13*L10 -> 9593.4165 | M14: =+M13*M10 -> 9663.1103 | N14: =+N13*N10 -> 9723.7448 | O14: =+O13*O10 -> 9813.0233 | ... Q14: =+Q13*Q10 -> 9897.3934
B16: EBITDA | C16: =+C3+C7 -> 11109 | D16: =+D3+D7 -> 12600 | E16: =+E3+E7 -> 13336 | F16: =+F3+F7 -> 10647 | G16: =+G3+G7 -> 14315 | H16: =+H3+H7 -> 15086.821 | I16: =+I3+I7 -> 15709.999 | J16: =+J3+J7 -> 16644.223 | ... Q16: =+Q3+Q7 -> 25483.232
B18: Dividends paid | H18: =+-CF!H28 -> 7708.8867 | I18: =+-CF!I28 -> 8001.3784 | J18: =+-CF!J28 -> 8525.0346 | K18: =+-CF!K28 -> 8980.054 | L18: =+-CF!L28 -> 9580.355 | M18: =+-CF!M28 -> 10240.412 | N18: =+-CF!N28 -> 10940.875 | O18: =+-CF!O28 -> 11709.234 | ... Q18: =+-CF!Q28 -> 13318.18
B19: Share buybacks | H19: =+-CF!H31 -> 0 | I19: =+-CF!I31 -> 2370.8757 | J19: =+-CF!J31 -> 3077.4972 | K19: =+-CF!K31 -> 3420.5248 | L19: =+-CF!L31 -> 3637.2336 | M19: =+-CF!M31 -> 3900.9956 | N19: =+-CF!N31 -> 4169.4131 | O19: =+-CF!O31 -> 4485.8129 | ... Q19: =+-CF!Q31 -> 5080.8887
B20: Total payout (Dividends + Buybacks) | H20: =+H18+H19 -> 7708.8867 | I20: =+I18+I19 -> 10372.254 | J20: =+J18+J19 -> 11602.532 | K20: =+K18+K19 -> 12400.579 | L20: =+L18+L19 -> 13217.589 | M20: =+M18+M19 -> 14141.408 | N20: =+N18+N19 -> 15110.288 | O20: =+O18+O19 -> 16195.047 | ... Q20: =+Q18+Q19 -> 18399.069
B21: Discount factor | H21: =1/(1+WACC!$D$17)^H12 -> 0.94006824 | I21: =1/(1+WACC!$D$17)^I12 -> 0.88372829 | J21: =1/(1+WACC!$D$17)^J12 -> 0.8307649 | K21: =1/(1+WACC!$D$17)^K12 -> 0.78097569 | L21: =1/(1+WACC!$D$17)^L12 -> 0.73417044 | M21: =1/(1+WACC!$D$17)^M12 -> 0.69017032 | N21: =1/(1+WACC!$D$17)^N12 -> 0.64880719 | O21: =1/(1+WACC!$D$17)^O12 -> 0.60992304 | ... Q21: =1/(1+WACC!$D$17)^Q12 -> 0.53900624
B22: Discounted Total Payout | H22: =+H21*H20 -> 7246.8796 | I22: =+I21*I20 -> 9166.2544 | J22: =+J21*J20 -> 9638.9762 | K22: =+K21*K20 -> 9684.5506 | L22: =+L21*L20 -> 9703.9629 | M22: =+M21*M20 -> 9759.9801 | N22: =+N21*N20 -> 9803.6638 | O22: =+O21*O20 -> 9877.7321 | ... Q22: =+Q21*Q20 -> 9917.2128
B26: Implied Equity Value and Share Price | F26: Terminal Value - Exit Multiple | J26: Terminal Value - Perpetual Growth | N26: Dividend Discount Model - Total Payout | R26: Market Value | S26: =+$D$44 -> 92.71
B27: PV of FCFF 10 years | D27: =+SUM(H14:Q14) -> 95478.918 | F27: EBITDA Yr 10 | H27: =+Q16 -> 25483.232 | J27: NOPAT Yr 10 | L27: =+Q6 -> 18249.97 | N27: PV of total payout (2026-2035) | P27: =+SUM(H22:Q22) -> 94674.66 | R27: Upside | S27: =+S28-S26 -> -0.57480504
B28: Implied Enterprise Value - Exit Multiple | D28: =+D27+H32 -> 380626.66 | F28: Times EBITDA Yr 10 | H28: 20 | J28: ROIC Year 10 (RONIC) | L28: =+L27/(BS!Q9+BS!Q10+BS!Q11-BS!Q24-BS!Q25-BS!Q26+BS!Q17) -> 0.22600838 | N28: Perpetual payout growth | P28: 0.025 | R28: Intrinsic value | S28: =+D40 -> 92.135195
B29: Implied Enterprise Value - Perpetual growth | D29: =+D27+L35 -> 362999.22 | F29: Terminal Value | H29: =+H27*H28 -> 509664.64 | J29: Terminal g | L29: 0.025 | N29: TV of total payout | P29: =+Q20*(1+P28)/(WACC!$D$17-P28) -> 486652.82
B30: Implied Enterprise Value - DDM Total Payout | D30: =+P27+P32 -> 356983.57 | J30: Reinvestment rate (g / RONIC) | L30: =+L29/L28 -> 0.11061537 | R30: Market Value | S30: =+$D$44 -> 92.71
B31: (-) Gross Debt (ST + LT + leases) | D31: =-(BS!G27+BS!G30+BS!G31+BS!G32) -> -49357 | F31: Discount Factor | H31: =+Q13 -> 0.55948113 | J31: Terminal FCFF (Yr 11) | L31: =+L27*(1+L29)*(1-L30) -> 16637.024 | N31: Discount factor | P31: =+Q21 -> 0.53900624 | R31: Upside | S31: =+S32-S30 -> -4.6618541
B32: (-) Minority Interest | D32: =-BS!G43 -> -2106 | F32: PV of TV | H32: =+H29*H31 -> 285147.75 | J32: Terminal Value | L32: =+L31/(WACC!$D$25-L29) -> 478157.87 | N32: PV of TV | P32: =+P31*P29 -> 262308.91 | R32: Intrinsic value | S32: =+D41 -> 88.048146
B33: (+) Investments in associates (book value × P/BV) | D33: =+H36*H38 -> 52409.433
B34: (+) Cash and Equivalents (FY2025) | D34: =+BS!G7+BS!G8 -> 15806 | J34: Discount factor | L34: =+Q13 -> 0.55948113
B35: Implied Equity Value - Exit Multiple | D35: =+SUM(D31:D34)+D28 -> 397379.1 | F35: Investments in associates | J35: PV of TV | L35: =+L32*L34 -> 267520.3 | R35: Market Value | S35: =+$D$44 -> 92.71
B36: Implied Equity Value - Perpetual Growth | D36: =+D29+SUM(D31:D34) -> 379751.65 | F36: Book value FY2025 | H36: =+'Balance Sheet'!G36 -> 20235 | R36: Upside | S36: =+S37-S35 -> -9.9407984
B37: Implied Equity Value - DDM Total Payout | D37: =+D30 -> 356983.57 | F37: P/BV multiple applied | H37: 1 | R37: Intrinsic value | S37: =+D42 -> 82.769202
B38: WASO | D38: =+IS!G58 -> 4313 | F38: Implied P/B (capitalised earnings) | H38: =+(-CR!G22/(WACC!$D$17-$L$29))/H36 -> 2.5900387
B40: Implied Share Price - Exit Multiple | D40: =+D35/$D$38 -> 92.135195
B41: Implied Share Price - Perpetual Growth | D41: =+D36/$D$38 -> 88.048146
B42: Implied Share Price - DDM Total Payout | D42: =+D37/$D$38 -> 82.769202
B44: #VALUE! | D44: {=+_FV(B44,"Price")} -> 92.71

Sheet Sensitivity
B2: WACC - Exit Multiple - Sensitivity Table
D4: Exit Multiple
D5: =+E5-1 -> 17 | E5: =+F5-1 -> 18 | F5: =+G5-1 -> 19 | G5: =+'DCF + DDM'!H28 -> 20 | H5: =+G5+1 -> 21 | I5: =+H5+2 -> 23 | J5: =+I5+2 -> 25
B6: WACC | C6: =+C9+0.015 -> 0.074793999 | D6: {=(SUMPRODUCT('DCF + DDM'!$H$10:$Q$10/(1+$C6)^'DCF + DDM'!$H$12:$Q$12)+'DCF + DDM'!$Q$16*D$5/(1+$C6)^'DCF + DDM'!$Q$12+SUM('DCF + DDM'!$D$31:$D$34))/'DCF + DDM'!$D$38} -> 73.193312 | E6: {=(SUMPRODUCT('DCF + DDM'!$H$10:$Q$10/(1+$C6)^'DCF + DDM'!$H$12:$Q$12)+'DCF + DDM'!$Q$16*E$5/(1+$C6)^'DCF + DDM'!$Q$12+SUM('DCF + DDM'!$D$31:$D$34))/'DCF + DDM'!$D$38} -> 76.065565 | F6: {=(SUMPRODUCT('DCF + DDM'!$H$10:$Q$10/(1+$C6)^'DCF + DDM'!$H$12:$Q$12)+'DCF + DDM'!$Q$16*F$5/(1+$C6)^'DCF + DDM'!$Q$12+SUM('DCF + DDM'!$D$31:$D$34))/'DCF + DDM'!$D$38} -> 78.937818 | G6: {=(SUMPRODUCT('DCF + DDM'!$H$10:$Q$10/(1+$C6)^'DCF + DDM'!$H$12:$Q$12)+'DCF + DDM'!$Q$16*G$5/(1+$C6)^'DCF + DDM'!$Q$12+SUM('DCF + DDM'!$D$31:$D$34))/'DCF + DDM'!$D$38} -> 81.810071 | H6: {=(SUMPRODUCT('DCF + DDM'!$H$10:$Q$10/(1+$C6)^'DCF + DDM'!$H$12:$Q$12)+'DCF + DDM'!$Q$16*H$5/(1+$C6)^'DCF + DDM'!$Q$12+SUM('DCF + DDM'!$D$31:$D$34))/'DCF + DDM'!$D$38} -> 84.682325 | I6: {=(SUMPRODUCT('DCF + DDM'!$H$10:$Q$10/(1+$C6)^'DCF + DDM'!$H$12:$Q$12)+'DCF + DDM'!$Q$16*I$5/(1+$C6)^'DCF + DDM'!$Q$12+SUM('DCF + DDM'!$D$31:$D$34))/'DCF + DDM'!$D$38} -> 90.426831 | J6: {=(SUMPRODUCT('DCF + DDM'!$H$10:$Q$10/(1+$C6)^'DCF + DDM'!$H$12:$Q$12)+'DCF + DDM'!$Q$16*J$5/(1+$C6)^'DCF + DDM'!$Q$12+SUM('DCF + DDM'!$D$31:$D$34))/'DCF + DDM'!$D$38} -> 96.171337
C7: =+C9+0.01 -> 0.069793999 | D7: {=(SUMPRODUCT('DCF + DDM'!$H$10:$Q$10/(1+$C7)^'DCF + DDM'!$H$12:$Q$12)+'DCF + DDM'!$Q$16*D$5/(1+$C7)^'DCF + DDM'!$Q$12+SUM('DCF + DDM'!$D$31:$D$34))/'DCF + DDM'!$D$38} -> 76.05571 | E7: {=(SUMPRODUCT('DCF + DDM'!$H$10:$Q$10/(1+$C7)^'DCF + DDM'!$H$12:$Q$12)+'DCF + DDM'!$Q$16*E$5/(1+$C7)^'DCF + DDM'!$Q$12+SUM('DCF + DDM'!$D$31:$D$34))/'DCF + DDM'!$D$38} -> 79.065066 | F7: {=(SUMPRODUCT('DCF + DDM'!$H$10:$Q$10/(1+$C7)^'DCF + DDM'!$H$12:$Q$12)+'DCF + DDM'!$Q$16*F$5/(1+$C7)^'DCF + DDM'!$Q$12+SUM('DCF + DDM'!$D$31:$D$34))/'DCF + DDM'!$D$38} -> 82.074421 | G7: {=(SUMPRODUCT('DCF + DDM'!$H$10:$Q$10/(1+$C7)^'DCF + DDM'!$H$12:$Q$12)+'DCF + DDM'!$Q$16*G$5/(1+$C7)^'DCF + DDM'!$Q$12+SUM('DCF + DDM'!$D$31:$D$34))/'DCF + DDM'!$D$38} -> 85.083776 | H7: {=(SUMPRODUCT('DCF + DDM'!$H$10:$Q$10/(1+$C7)^'DCF + DDM'!$H$12:$Q$12)+'DCF + DDM'!$Q$16*H$5/(1+$C7)^'DCF + DDM'!$Q$12+SUM('DCF + DDM'!$D$31:$D$34))/'DCF + DDM'!$D$38} -> 88.093132 | I7: {=(SUMPRODUCT('DCF + DDM'!$H$10:$Q$10/(1+$C7)^'DCF + DDM'!$H$12:$Q$12)+'DCF + DDM'!$Q$16*I$5/(1+$C7)^'DCF + DDM'!$Q$12+SUM('DCF + DDM'!$D$31:$D$34))/'DCF + DDM'!$D$38} -> 94.111842 | J7: {=(SUMPRODUCT('DCF + DDM'!$H$10:$Q$10/(1+$C7)^'DCF + DDM'!$H$12:$Q$12)+'DCF + DDM'!$Q$16*J$5/(1+$C7)^'DCF + DDM'!$Q$12+SUM('DCF + DDM'!$D$31:$D$34))/'DCF + DDM'!$D$38} -> 100.13055
C8: =+C9+0.005 -> 0.064793999 | D8: {=(SUMPRODUCT('DCF + DDM'!$H$10:$Q$10/(1+$C8)^'DCF + DDM'!$H$12:$Q$12)+'DCF + DDM'!$Q$16*D$5/(1+$C8)^'DCF + DDM'!$Q$12+SUM('DCF + DDM'!$D$31:$D$34))/'DCF + DDM'!$D$38} -> 79.061308 | E8: {=(SUMPRODUCT('DCF + DDM'!$H$10:$Q$10/(1+$C8)^'DCF + DDM'!$H$12:$Q$12)+'DCF + DDM'!$Q$16*E$5/(1+$C8)^'DCF + DDM'!$Q$12+SUM('DCF + DDM'!$D$31:$D$34))/'DCF + DDM'!$D$38} -> 82.214999 | F8: {=(SUMPRODUCT('DCF + DDM'!$H$10:$Q$10/(1+$C8)^'DCF + DDM'!$H$12:$Q$12)+'DCF + DDM'!$Q$16*F$5/(1+$C8)^'DCF + DDM'!$Q$12+SUM('DCF + DDM'!$D$31:$D$34))/'DCF + DDM'!$D$38} -> 85.36869 | G8: {=(SUMPRODUCT('DCF + DDM'!$H$10:$Q$10/(1+$C8)^'DCF + DDM'!$H$12:$Q$12)+'DCF + DDM'!$Q$16*G$5/(1+$C8)^'DCF + DDM'!$Q$12+SUM('DCF + DDM'!$D$31:$D$34))/'DCF + DDM'!$D$38} -> 88.52238 | H8: {=(SUMPRODUCT('DCF + DDM'!$H$10:$Q$10/(1+$C8)^'DCF + DDM'!$H$12:$Q$12)+'DCF + DDM'!$Q$16*H$5/(1+$C8)^'DCF + DDM'!$Q$12+SUM('DCF + DDM'!$D$31:$D$34))/'DCF + DDM'!$D$38} -> 91.676071 | I8: {=(SUMPRODUCT('DCF + DDM'!$H$10:$Q$10/(1+$C8)^'DCF + DDM'!$H$12:$Q$12)+'DCF + DDM'!$Q$16*I$5/(1+$C8)^'DCF + DDM'!$Q$12+SUM('DCF + DDM'!$D$31:$D$34))/'DCF + DDM'!$D$38} -> 97.983452 | J8: {=(SUMPRODUCT('DCF + DDM'!$H$10:$Q$10/(1+$C8)^'DCF + DDM'!$H$12:$Q$12)+'DCF + DDM'!$Q$16*J$5/(1+$C8)^'DCF + DDM'!$Q$12+SUM('DCF + DDM'!$D$31:$D$34))/'DCF + DDM'!$D$38} -> 104.29083
C9: =+WACC!$D$25 -> 0.059793999 | D9: {=(SUMPRODUCT('DCF + DDM'!$H$10:$Q$10/(1+$C9)^'DCF + DDM'!$H$12:$Q$12)+'DCF + DDM'!$Q$16*D$5/(1+$C9)^'DCF + DDM'!$Q$12+SUM('DCF + DDM'!$D$31:$D$34))/'DCF + DDM'!$D$38} -> 82.218162 | E9: {=(SUMPRODUCT('DCF + DDM'!$H$10:$Q$10/(1+$C9)^'DCF + DDM'!$H$12:$Q$12)+'DCF + DDM'!$Q$16*E$5/(1+$C9)^'DCF + DDM'!$Q$12+SUM('DCF + DDM'!$D$31:$D$34))/'DCF + DDM'!$D$38} -> 85.52384 | F9: {=(SUMPRODUCT('DCF + DDM'!$H$10:$Q$10/(1+$C9)^'DCF + DDM'!$H$12:$Q$12)+'DCF + DDM'!$Q$16*F$5/(1+$C9)^'DCF + DDM'!$Q$12+SUM('DCF + DDM'!$D$31:$D$34))/'DCF + DDM'!$D$38} -> 88.829517 | G9: {=(SUMPRODUCT('DCF + DDM'!$H$10:$Q$10/(1+$C9)^'DCF + DDM'!$H$12:$Q$12)+'DCF + DDM'!$Q$16*G$5/(1+$C9)^'DCF + DDM'!$Q$12+SUM('DCF + DDM'!$D$31:$D$34))/'DCF + DDM'!$D$38} -> 92.135195 | H9: {=(SUMPRODUCT('DCF + DDM'!$H$10:$Q$10/(1+$C9)^'DCF + DDM'!$H$12:$Q$12)+'DCF + DDM'!$Q$16*H$5/(1+$C9)^'DCF + DDM'!$Q$12+SUM('DCF + DDM'!$D$31:$D$34))/'DCF + DDM'!$D$38} -> 95.440873 | I9: {=(SUMPRODUCT('DCF + DDM'!$H$10:$Q$10/(1+$C9)^'DCF + DDM'!$H$12:$Q$12)+'DCF + DDM'!$Q$16*I$5/(1+$C9)^'DCF + DDM'!$Q$12+SUM('DCF + DDM'!$D$31:$D$34))/'DCF + DDM'!$D$38} -> 102.05223 | J9: {=(SUMPRODUCT('DCF + DDM'!$H$10:$Q$10/(1+$C9)^'DCF + DDM'!$H$12:$Q$12)+'DCF + DDM'!$Q$16*J$5/(1+$C9)^'DCF + DDM'!$Q$12+SUM('DCF + DDM'!$D$31:$D$34))/'DCF + DDM'!$D$38} -> 108.66358
C10: =+C9-0.005 -> 0.054793999 | D10: {=(SUMPRODUCT('DCF + DDM'!$H$10:$Q$10/(1+$C10)^'DCF + DDM'!$H$12:$Q$12)+'DCF + DDM'!$Q$16*D$5/(1+$C10)^'DCF + DDM'!$Q$12+SUM('DCF + DDM'!$D$31:$D$34))/'DCF + DDM'!$D$38} -> 85.534828 | E10: {=(SUMPRODUCT('DCF + DDM'!$H$10:$Q$10/(1+$C10)^'DCF + DDM'!$H$12:$Q$12)+'DCF + DDM'!$Q$16*E$5/(1+$C10)^'DCF + DDM'!$Q$12+SUM('DCF + DDM'!$D$31:$D$34))/'DCF + DDM'!$D$38} -> 89.000589 | F10: {=(SUMPRODUCT('DCF + DDM'!$H$10:$Q$10/(1+$C10)^'DCF + DDM'!$H$12:$Q$12)+'DCF + DDM'!$Q$16*F$5/(1+$C10)^'DCF + DDM'!$Q$12+SUM('DCF + DDM'!$D$31:$D$34))/'DCF + DDM'!$D$38} -> 92.466349 | G10: {=(SUMPRODUCT('DCF + DDM'!$H$10:$Q$10/(1+$C10)^'DCF + DDM'!$H$12:$Q$12)+'DCF + DDM'!$Q$16*G$5/(1+$C10)^'DCF + DDM'!$Q$12+SUM('DCF + DDM'!$D$31:$D$34))/'DCF + DDM'!$D$38} -> 95.93211 | H10: {=(SUMPRODUCT('DCF + DDM'!$H$10:$Q$10/(1+$C10)^'DCF + DDM'!$H$12:$Q$12)+'DCF + DDM'!$Q$16*H$5/(1+$C10)^'DCF + DDM'!$Q$12+SUM('DCF + DDM'!$D$31:$D$34))/'DCF + DDM'!$D$38} -> 99.39787 | I10: {=(SUMPRODUCT('DCF + DDM'!$H$10:$Q$10/(1+$C10)^'DCF + DDM'!$H$12:$Q$12)+'DCF + DDM'!$Q$16*I$5/(1+$C10)^'DCF + DDM'!$Q$12+SUM('DCF + DDM'!$D$31:$D$34))/'DCF + DDM'!$D$38} -> 106.32939 | J10: {=(SUMPRODUCT('DCF + DDM'!$H$10:$Q$10/(1+$C10)^'DCF + DDM'!$H$12:$Q$12)+'DCF + DDM'!$Q$16*J$5/(1+$C10)^'DCF + DDM'!$Q$12+SUM('DCF + DDM'!$D$31:$D$34))/'DCF + DDM'!$D$38} -> 113.26091
C11: =+C9-0.01 -> 0.049793999 | D11: {=(SUMPRODUCT('DCF + DDM'!$H$10:$Q$10/(1+$C11)^'DCF + DDM'!$H$12:$Q$12)+'DCF + DDM'!$Q$16*D$5/(1+$C11)^'DCF + DDM'!$Q$12+SUM('DCF + DDM'!$D$31:$D$34))/'DCF + DDM'!$D$38} -> 89.020394 | E11: {=(SUMPRODUCT('DCF + DDM'!$H$10:$Q$10/(1+$C11)^'DCF + DDM'!$H$12:$Q$12)+'DCF + DDM'!$Q$16*E$5/(1+$C11)^'DCF + DDM'!$Q$12+SUM('DCF + DDM'!$D$31:$D$34))/'DCF + DDM'!$D$38} -> 92.654806 | F11: {=(SUMPRODUCT('DCF + DDM'!$H$10:$Q$10/(1+$C11)^'DCF + DDM'!$H$12:$Q$12)+'DCF + DDM'!$Q$16*F$5/(1+$C11)^'DCF + DDM'!$Q$12+SUM('DCF + DDM'!$D$31:$D$34))/'DCF + DDM'!$D$38} -> 96.289218 | G11: {=(SUMPRODUCT('DCF + DDM'!$H$10:$Q$10/(1+$C11)^'DCF + DDM'!$H$12:$Q$12)+'DCF + DDM'!$Q$16*G$5/(1+$C11)^'DCF + DDM'!$Q$12+SUM('DCF + DDM'!$D$31:$D$34))/'DCF + DDM'!$D$38} -> 99.92363 | H11: {=(SUMPRODUCT('DCF + DDM'!$H$10:$Q$10/(1+$C11)^'DCF + DDM'!$H$12:$Q$12)+'DCF + DDM'!$Q$16*H$5/(1+$C11)^'DCF + DDM'!$Q$12+SUM('DCF + DDM'!$D$31:$D$34))/'DCF + DDM'!$D$38} -> 103.55804 | I11: {=(SUMPRODUCT('DCF + DDM'!$H$10:$Q$10/(1+$C11)^'DCF + DDM'!$H$12:$Q$12)+'DCF + DDM'!$Q$16*I$5/(1+$C11)^'DCF + DDM'!$Q$12+SUM('DCF + DDM'!$D$31:$D$34))/'DCF + DDM'!$D$38} -> 110.82687 | J11: {=(SUMPRODUCT('DCF + DDM'!$H$10:$Q$10/(1+$C11)^'DCF + DDM'!$H$12:$Q$12)+'DCF + DDM'!$Q$16*J$5/(1+$C11)^'DCF + DDM'!$Q$12+SUM('DCF + DDM'!$D$31:$D$34))/'DCF + DDM'!$D$38} -> 118.09569
C12: =+C9-0.015 -> 0.044793999 | D12: {=(SUMPRODUCT('DCF + DDM'!$H$10:$Q$10/(1+$C12)^'DCF + DDM'!$H$12:$Q$12)+'DCF + DDM'!$Q$16*D$5/(1+$C12)^'DCF + DDM'!$Q$12+SUM('DCF + DDM'!$D$31:$D$34))/'DCF + DDM'!$D$38} -> 92.684515 | E12: {=(SUMPRODUCT('DCF + DDM'!$H$10:$Q$10/(1+$C12)^'DCF + DDM'!$H$12:$Q$12)+'DCF + DDM'!$Q$16*E$5/(1+$C12)^'DCF + DDM'!$Q$12+SUM('DCF + DDM'!$D$31:$D$34))/'DCF + DDM'!$D$38} -> 96.49665 | F12: {=(SUMPRODUCT('DCF + DDM'!$H$10:$Q$10/(1+$C12)^'DCF + DDM'!$H$12:$Q$12)+'DCF + DDM'!$Q$16*F$5/(1+$C12)^'DCF + DDM'!$Q$12+SUM('DCF + DDM'!$D$31:$D$34))/'DCF + DDM'!$D$38} -> 100.30879 | G12: {=(SUMPRODUCT('DCF + DDM'!$H$10:$Q$10/(1+$C12)^'DCF + DDM'!$H$12:$Q$12)+'DCF + DDM'!$Q$16*G$5/(1+$C12)^'DCF + DDM'!$Q$12+SUM('DCF + DDM'!$D$31:$D$34))/'DCF + DDM'!$D$38} -> 104.12092 | H12: {=(SUMPRODUCT('DCF + DDM'!$H$10:$Q$10/(1+$C12)^'DCF + DDM'!$H$12:$Q$12)+'DCF + DDM'!$Q$16*H$5/(1+$C12)^'DCF + DDM'!$Q$12+SUM('DCF + DDM'!$D$31:$D$34))/'DCF + DDM'!$D$38} -> 107.93306 | I12: {=(SUMPRODUCT('DCF + DDM'!$H$10:$Q$10/(1+$C12)^'DCF + DDM'!$H$12:$Q$12)+'DCF + DDM'!$Q$16*I$5/(1+$C12)^'DCF + DDM'!$Q$12+SUM('DCF + DDM'!$D$31:$D$34))/'DCF + DDM'!$D$38} -> 115.55733 | J12: {=(SUMPRODUCT('DCF + DDM'!$H$10:$Q$10/(1+$C12)^'DCF + DDM'!$H$12:$Q$12)+'DCF + DDM'!$Q$16*J$5/(1+$C12)^'DCF + DDM'!$Q$12+SUM('DCF + DDM'!$D$31:$D$34))/'DCF + DDM'!$D$38} -> 123.1816
B16: WACC - Perpetual Growth - Sensitivity Table
D18: Perpetual Growth Rate
D19: =+E19-0.0025 -> 0.0175 | E19: =+F19-0.0025 -> 0.02 | F19: =+G19-0.0025 -> 0.0225 | G19: =+'DCF + DDM'!L29 -> 0.025 | H19: =+G19+0.0025 -> 0.0275 | I19: =+H19+0.0025 -> 0.03 | J19: =+I19+0.0025 -> 0.0325
B20: WACC | C20: =+C23+0.015 -> 0.074793999 | D20: {=(SUMPRODUCT('DCF + DDM'!$H$10:$Q$10/(1+$C20)^'DCF + DDM'!$H$12:$Q$12)+'DCF + DDM'!$L$27*(1+D$19)*(1-D$19/'DCF + DDM'!$L$28)/($C20-D$19)/(1+$C20)^'DCF + DDM'!$Q$12+SUM('DCF + DDM'!$D$31:$D$34))/'DCF + DDM'!$D$38} -> 58.066927 | E20: {=(SUMPRODUCT('DCF + DDM'!$H$10:$Q$10/(1+$C20)^'DCF + DDM'!$H$12:$Q$12)+'DCF + DDM'!$L$27*(1+E$19)*(1-E$19/'DCF + DDM'!$L$28)/($C20-E$19)/(1+$C20)^'DCF + DDM'!$Q$12+SUM('DCF + DDM'!$D$31:$D$34))/'DCF + DDM'!$D$38} -> 59.267617 | F20: {=(SUMPRODUCT('DCF + DDM'!$H$10:$Q$10/(1+$C20)^'DCF + DDM'!$H$12:$Q$12)+'DCF + DDM'!$L$27*(1+F$19)*(1-F$19/'DCF + DDM'!$L$28)/($C20-F$19)/(1+$C20)^'DCF + DDM'!$Q$12+SUM('DCF + DDM'!$D$31:$D$34))/'DCF + DDM'!$D$38} -> 60.580934 | G20: {=(SUMPRODUCT('DCF + DDM'!$H$10:$Q$10/(1+$C20)^'DCF + DDM'!$H$12:$Q$12)+'DCF + DDM'!$L$27*(1+G$19)*(1-G$19/'DCF + DDM'!$L$28)/($C20-G$19)/(1+$C20)^'DCF + DDM'!$Q$12+SUM('DCF + DDM'!$D$31:$D$34))/'DCF + DDM'!$D$38} -> 62.023841 | H20: {=(SUMPRODUCT('DCF + DDM'!$H$10:$Q$10/(1+$C20)^'DCF + DDM'!$H$12:$Q$12)+'DCF + DDM'!$L$27*(1+H$19)*(1-H$19/'DCF + DDM'!$L$28)/($C20-H$19)/(1+$C20)^'DCF + DDM'!$Q$12+SUM('DCF + DDM'!$D$31:$D$34))/'DCF + DDM'!$D$38} -> 63.616889 | I20: {=(SUMPRODUCT('DCF + DDM'!$H$10:$Q$10/(1+$C20)^'DCF + DDM'!$H$12:$Q$12)+'DCF + DDM'!$L$27*(1+I$19)*(1-I$19/'DCF + DDM'!$L$28)/($C20-I$19)/(1+$C20)^'DCF + DDM'!$Q$12+SUM('DCF + DDM'!$D$31:$D$34))/'DCF + DDM'!$D$38} -> 65.385216 | J20: {=(SUMPRODUCT('DCF + DDM'!$H$10:$Q$10/(1+$C20)^'DCF + DDM'!$H$12:$Q$12)+'DCF + DDM'!$L$27*(1+J$19)*(1-J$19/'DCF + DDM'!$L$28)/($C20-J$19)/(1+$C20)^'DCF + DDM'!$Q$12+SUM('DCF + DDM'!$D$31:$D$34))/'DCF + DDM'!$D$38} -> 67.359906
C21: =+C23+0.01 -> 0.069793999 | D21: {=(SUMPRODUCT('DCF + DDM'!$H$10:$Q$10/(1+$C21)^'DCF + DDM'!$H$12:$Q$12)+'DCF + DDM'!$L$27*(1+D$19)*(1-D$19/'DCF + DDM'!$L$28)/($C21-D$19)/(1+$C21)^'DCF + DDM'!$Q$12+SUM('DCF + DDM'!$D$31:$D$34))/'DCF + DDM'!$D$38} -> 63.583457 | E21: {=(SUMPRODUCT('DCF + DDM'!$H$10:$Q$10/(1+$C21)^'DCF + DDM'!$H$12:$Q$12)+'DCF + DDM'!$L$27*(1+E$19)*(1-E$19/'DCF + DDM'!$L$28)/($C21-E$19)/(1+$C21)^'DCF + DDM'!$Q$12+SUM('DCF + DDM'!$D$31:$D$34))/'DCF + DDM'!$D$38} -> 65.137287 | F21: {=(SUMPRODUCT('DCF + DDM'!$H$10:$Q$10/(1+$C21)^'DCF + DDM'!$H$12:$Q$12)+'DCF + DDM'!$L$27*(1+F$19)*(1-F$19/'DCF + DDM'!$L$28)/($C21-F$19)/(1+$C21)^'DCF + DDM'!$Q$12+SUM('DCF + DDM'!$D$31:$D$34))/'DCF + DDM'!$D$38} -> 66.852871 | G21: {=(SUMPRODUCT('DCF + DDM'!$H$10:$Q$10/(1+$C21)^'DCF + DDM'!$H$12:$Q$12)+'DCF + DDM'!$L$27*(1+G$19)*(1-G$19/'DCF + DDM'!$L$28)/($C21-G$19)/(1+$C21)^'DCF + DDM'!$Q$12+SUM('DCF + DDM'!$D$31:$D$34))/'DCF + DDM'!$D$38} -> 68.757291 | H21: {=(SUMPRODUCT('DCF + DDM'!$H$10:$Q$10/(1+$C21)^'DCF + DDM'!$H$12:$Q$12)+'DCF + DDM'!$L$27*(1+H$19)*(1-H$19/'DCF + DDM'!$L$28)/($C21-H$19)/(1+$C21)^'DCF + DDM'!$Q$12+SUM('DCF + DDM'!$D$31:$D$34))/'DCF + DDM'!$D$38} -> 70.884033 | I21: {=(SUMPRODUCT('DCF + DDM'!$H$10:$Q$10/(1+$C21)^'DCF + DDM'!$H$12:$Q$12)+'DCF + DDM'!$L$27*(1+I$19)*(1-I$19/'DCF + DDM'!$L$28)/($C21-I$19)/(1+$C21)^'DCF + DDM'!$Q$12+SUM('DCF + DDM'!$D$31:$D$34))/'DCF + DDM'!$D$38} -> 73.274999 | J21: {=(SUMPRODUCT('DCF + DDM'!$H$10:$Q$10/(1+$C21)^'DCF + DDM'!$H$12:$Q$12)+'DCF + DDM'!$L$27*(1+J$19)*(1-J$19/'DCF + DDM'!$L$28)/($C21-J$19)/(1+$C21)^'DCF + DDM'!$Q$12+SUM('DCF + DDM'!$D$31:$D$34))/'DCF + DDM'!$D$38} -> 75.983325
C22: =+C23+0.005 -> 0.064793999 | D22: {=(SUMPRODUCT('DCF + DDM'!$H$10:$Q$10/(1+$C22)^'DCF + DDM'!$H$12:$Q$12)+'DCF + DDM'!$L$27*(1+D$19)*(1-D$19/'DCF + DDM'!$L$28)/($C22-D$19)/(1+$C22)^'DCF + DDM'!$Q$12+SUM('DCF + DDM'!$D$31:$D$34))/'DCF + DDM'!$D$38} -> 70.277056 | E22: {=(SUMPRODUCT('DCF + DDM'!$H$10:$Q$10/(1+$C22)^'DCF + DDM'!$H$12:$Q$12)+'DCF + DDM'!$L$27*(1+E$19)*(1-E$19/'DCF + DDM'!$L$28)/($C22-E$19)/(1+$C22)^'DCF + DDM'!$Q$12+SUM('DCF + DDM'!$D$31:$D$34))/'DCF + DDM'!$D$38} -> 72.32639 | F22: {=(SUMPRODUCT('DCF + DDM'!$H$10:$Q$10/(1+$C22)^'DCF + DDM'!$H$12:$Q$12)+'DCF + DDM'!$L$27*(1+F$19)*(1-F$19/'DCF + DDM'!$L$28)/($C22-F$19)/(1+$C22)^'DCF + DDM'!$Q$12+SUM('DCF + DDM'!$D$31:$D$34))/'DCF + DDM'!$D$38} -> 74.615042 | G22: {=(SUMPRODUCT('DCF + DDM'!$H$10:$Q$10/(1+$C22)^'DCF + DDM'!$H$12:$Q$12)+'DCF + DDM'!$L$27*(1+G$19)*(1-G$19/'DCF + DDM'!$L$28)/($C22-G$19)/(1+$C22)^'DCF + DDM'!$Q$12+SUM('DCF + DDM'!$D$31:$D$34))/'DCF + DDM'!$D$38} -> 77.188118 | H22: {=(SUMPRODUCT('DCF + DDM'!$H$10:$Q$10/(1+$C22)^'DCF + DDM'!$H$12:$Q$12)+'DCF + DDM'!$L$27*(1+H$19)*(1-H$19/'DCF + DDM'!$L$28)/($C22-H$19)/(1+$C22)^'DCF + DDM'!$Q$12+SUM('DCF + DDM'!$D$31:$D$34))/'DCF + DDM'!$D$38} -> 80.102816 | I22: {=(SUMPRODUCT('DCF + DDM'!$H$10:$Q$10/(1+$C22)^'DCF + DDM'!$H$12:$Q$12)+'DCF + DDM'!$L$27*(1+I$19)*(1-I$19/'DCF + DDM'!$L$28)/($C22-I$19)/(1+$C22)^'DCF + DDM'!$Q$12+SUM('DCF + DDM'!$D$31:$D$34))/'DCF + DDM'!$D$38} -> 83.432775 | J22: {=(SUMPRODUCT('DCF + DDM'!$H$10:$Q$10/(1+$C22)^'DCF + DDM'!$H$12:$Q$12)+'DCF + DDM'!$L$27*(1+J$19)*(1-J$19/'DCF + DDM'!$L$28)/($C22-J$19)/(1+$C22)^'DCF + DDM'!$Q$12+SUM('DCF + DDM'!$D$31:$D$34))/'DCF + DDM'!$D$38} -> 87.274435
C23: =+WACC!$D$25 -> 0.059793999 | D23: {=(SUMPRODUCT('DCF + DDM'!$H$10:$Q$10/(1+$C23)^'DCF + DDM'!$H$12:$Q$12)+'DCF + DDM'!$L$27*(1+D$19)*(1-D$19/'DCF + DDM'!$L$28)/($C23-D$19)/(1+$C23)^'DCF + DDM'!$Q$12+SUM('DCF + DDM'!$D$31:$D$34))/'DCF + DDM'!$D$38} -> 78.565602 | E23: {=(SUMPRODUCT('DCF + DDM'!$H$10:$Q$10/(1+$C23)^'DCF + DDM'!$H$12:$Q$12)+'DCF + DDM'!$L$27*(1+E$19)*(1-E$19/'DCF + DDM'!$L$28)/($C23-E$19)/(1+$C23)^'DCF + DDM'!$Q$12+SUM('DCF + DDM'!$D$31:$D$34))/'DCF + DDM'!$D$38} -> 81.332589 | F23: {=(SUMPRODUCT('DCF + DDM'!$H$10:$Q$10/(1+$C23)^'DCF + DDM'!$H$12:$Q$12)+'DCF + DDM'!$L$27*(1+F$19)*(1-F$19/'DCF + DDM'!$L$28)/($C23-F$19)/(1+$C23)^'DCF + DDM'!$Q$12+SUM('DCF + DDM'!$D$31:$D$34))/'DCF + DDM'!$D$38} -> 84.467035 | G23: {=(SUMPRODUCT('DCF + DDM'!$H$10:$Q$10/(1+$C23)^'DCF + DDM'!$H$12:$Q$12)+'DCF + DDM'!$L$27*(1+G$19)*(1-G$19/'DCF + DDM'!$L$28)/($C23-G$19)/(1+$C23)^'DCF + DDM'!$Q$12+SUM('DCF + DDM'!$D$31:$D$34))/'DCF + DDM'!$D$38} -> 88.048146 | H23: {=(SUMPRODUCT('DCF + DDM'!$H$10:$Q$10/(1+$C23)^'DCF + DDM'!$H$12:$Q$12)+'DCF + DDM'!$L$27*(1+H$19)*(1-H$19/'DCF + DDM'!$L$28)/($C23-H$19)/(1+$C23)^'DCF + DDM'!$Q$12+SUM('DCF + DDM'!$D$31:$D$34))/'DCF + DDM'!$D$38} -> 92.179657 | I23: {=(SUMPRODUCT('DCF + DDM'!$H$10:$Q$10/(1+$C23)^'DCF + DDM'!$H$12:$Q$12)+'DCF + DDM'!$L$27*(1+I$19)*(1-I$19/'DCF + DDM'!$L$28)/($C23-I$19)/(1+$C23)^'DCF + DDM'!$Q$12+SUM('DCF + DDM'!$D$31:$D$34))/'DCF + DDM'!$D$38} -> 97.00012 | J23: {=(SUMPRODUCT('DCF + DDM'!$H$10:$Q$10/(1+$C23)^'DCF + DDM'!$H$12:$Q$12)+'DCF + DDM'!$L$27*(1+J$19)*(1-J$19/'DCF + DDM'!$L$28)/($C23-J$19)/(1+$C23)^'DCF + DDM'!$Q$12+SUM('DCF + DDM'!$D$31:$D$34))/'DCF + DDM'!$D$38} -> 102.69885
C24: =+C23-0.005 -> 0.054793999 | D24: {=(SUMPRODUCT('DCF + DDM'!$H$10:$Q$10/(1+$C24)^'DCF + DDM'!$H$12:$Q$12)+'DCF + DDM'!$L$27*(1+D$19)*(1-D$19/'DCF + DDM'!$L$28)/($C24-D$19)/(1+$C24)^'DCF + DDM'!$Q$12+SUM('DCF + DDM'!$D$31:$D$34))/'DCF + DDM'!$D$38} -> 89.091091 | E24: {=(SUMPRODUCT('DCF + DDM'!$H$10:$Q$10/(1+$C24)^'DCF + DDM'!$H$12:$Q$12)+'DCF + DDM'!$L$27*(1+E$19)*(1-E$19/'DCF + DDM'!$L$28)/($C24-E$19)/(1+$C24)^'DCF + DDM'!$Q$12+SUM('DCF + DDM'!$D$31:$D$34))/'DCF + DDM'!$D$38} -> 92.939627 | F24: {=(SUMPRODUCT('DCF + DDM'!$H$10:$Q$10/(1+$C24)^'DCF + DDM'!$H$12:$Q$12)+'DCF + DDM'!$L$27*(1+F$19)*(1-F$19/'DCF + DDM'!$L$28)/($C24-F$19)/(1+$C24)^'DCF + DDM'!$Q$12+SUM('DCF + DDM'!$D$31:$D$34))/'DCF + DDM'!$D$38} -> 97.379772 | G24: {=(SUMPRODUCT('DCF + DDM'!$H$10:$Q$10/(1+$C24)^'DCF + DDM'!$H$12:$Q$12)+'DCF + DDM'!$L$27*(1+G$19)*(1-G$19/'DCF + DDM'!$L$28)/($C24-G$19)/(1+$C24)^'DCF + DDM'!$Q$12+SUM('DCF + DDM'!$D$31:$D$34))/'DCF + DDM'!$D$38} -> 102.56045 | H24: {=(SUMPRODUCT('DCF + DDM'!$H$10:$Q$10/(1+$C24)^'DCF + DDM'!$H$12:$Q$12)+'DCF + DDM'!$L$27*(1+H$19)*(1-H$19/'DCF + DDM'!$L$28)/($C24-H$19)/(1+$C24)^'DCF + DDM'!$Q$12+SUM('DCF + DDM'!$D$31:$D$34))/'DCF + DDM'!$D$38} -> 108.68515 | I24: {=(SUMPRODUCT('DCF + DDM'!$H$10:$Q$10/(1+$C24)^'DCF + DDM'!$H$12:$Q$12)+'DCF + DDM'!$L$27*(1+I$19)*(1-I$19/'DCF + DDM'!$L$28)/($C24-I$19)/(1+$C24)^'DCF + DDM'!$Q$12+SUM('DCF + DDM'!$D$31:$D$34))/'DCF + DDM'!$D$38} -> 116.03943 | J24: {=(SUMPRODUCT('DCF + DDM'!$H$10:$Q$10/(1+$C24)^'DCF + DDM'!$H$12:$Q$12)+'DCF + DDM'!$L$27*(1+J$19)*(1-J$19/'DCF + DDM'!$L$28)/($C24-J$19)/(1+$C24)^'DCF + DDM'!$Q$12+SUM('DCF + DDM'!$D$31:$D$34))/'DCF + DDM'!$D$38} -> 125.03694
C25: =+C23-0.01 -> 0.049793999 | D25: {=(SUMPRODUCT('DCF + DDM'!$H$10:$Q$10/(1+$C25)^'DCF + DDM'!$H$12:$Q$12)+'DCF + DDM'!$L$27*(1+D$19)*(1-D$19/'DCF + DDM'!$L$28)/($C25-D$19)/(1+$C25)^'DCF + DDM'!$Q$12+SUM('DCF + DDM'!$D$31:$D$34))/'DCF + DDM'!$D$38} -> 102.89313 | E25: {=(SUMPRODUCT('DCF + DDM'!$H$10:$Q$10/(1+$C25)^'DCF + DDM'!$H$12:$Q$12)+'DCF + DDM'!$L$27*(1+E$19)*(1-E$19/'DCF + DDM'!$L$28)/($C25-E$19)/(1+$C25)^'DCF + DDM'!$Q$12+SUM('DCF + DDM'!$D$31:$D$34))/'DCF + DDM'!$D$38} -> 108.45736 | F25: {=(SUMPRODUCT('DCF + DDM'!$H$10:$Q$10/(1+$C25)^'DCF + DDM'!$H$12:$Q$12)+'DCF + DDM'!$L$27*(1+F$19)*(1-F$19/'DCF + DDM'!$L$28)/($C25-F$19)/(1+$C25)^'DCF + DDM'!$Q$12+SUM('DCF + DDM'!$D$31:$D$34))/'DCF + DDM'!$D$38} -> 115.03563 | G25: {=(SUMPRODUCT('DCF + DDM'!$H$10:$Q$10/(1+$C25)^'DCF + DDM'!$H$12:$Q$12)+'DCF + DDM'!$L$27*(1+G$19)*(1-G$19/'DCF + DDM'!$L$28)/($C25-G$19)/(1+$C25)^'DCF + DDM'!$Q$12+SUM('DCF + DDM'!$D$31:$D$34))/'DCF + DDM'!$D$38} -> 122.93468 | H25: {=(SUMPRODUCT('DCF + DDM'!$H$10:$Q$10/(1+$C25)^'DCF + DDM'!$H$12:$Q$12)+'DCF + DDM'!$L$27*(1+H$19)*(1-H$19/'DCF + DDM'!$L$28)/($C25-H$19)/(1+$C25)^'DCF + DDM'!$Q$12+SUM('DCF + DDM'!$D$31:$D$34))/'DCF + DDM'!$D$38} -> 132.59884 | I25: {=(SUMPRODUCT('DCF + DDM'!$H$10:$Q$10/(1+$C25)^'DCF + DDM'!$H$12:$Q$12)+'DCF + DDM'!$L$27*(1+I$19)*(1-I$19/'DCF + DDM'!$L$28)/($C25-I$19)/(1+$C25)^'DCF + DDM'!$Q$12+SUM('DCF + DDM'!$D$31:$D$34))/'DCF + DDM'!$D$38} -> 144.69691 | J25: {=(SUMPRODUCT('DCF + DDM'!$H$10:$Q$10/(1+$C25)^'DCF + DDM'!$H$12:$Q$12)+'DCF + DDM'!$L$27*(1+J$19)*(1-J$19/'DCF + DDM'!$L$28)/($C25-J$19)/(1+$C25)^'DCF + DDM'!$Q$12+SUM('DCF + DDM'!$D$31:$D$34))/'DCF + DDM'!$D$38} -> 160.28442
C26: =+C23-0.015 -> 0.044793999 | D26: {=(SUMPRODUCT('DCF + DDM'!$H$10:$Q$10/(1+$C26)^'DCF + DDM'!$H$12:$Q$12)+'DCF + DDM'!$L$27*(1+D$19)*(1-D$19/'DCF + DDM'!$L$28)/($C26-D$19)/(1+$C26)^'DCF + DDM'!$Q$12+SUM('DCF + DDM'!$D$31:$D$34))/'DCF + DDM'!$D$38} -> 121.77316 | E26: {=(SUMPRODUCT('DCF + DDM'!$H$10:$Q$10/(1+$C26)^'DCF + DDM'!$H$12:$Q$12)+'DCF + DDM'!$L$27*(1+E$19)*(1-E$19/'DCF + DDM'!$L$28)/($C26-E$19)/(1+$C26)^'DCF + DDM'!$Q$12+SUM('DCF + DDM'!$D$31:$D$34))/'DCF + DDM'!$D$38} -> 130.25227 | F26: {=(SUMPRODUCT('DCF + DDM'!$H$10:$Q$10/(1+$C26)^'DCF + DDM'!$H$12:$Q$12)+'DCF + DDM'!$L$27*(1+F$19)*(1-F$19/'DCF + DDM'!$L$28)/($C26-F$19)/(1+$C26)^'DCF + DDM'!$Q$12+SUM('DCF + DDM'!$D$31:$D$34))/'DCF + DDM'!$D$38} -> 140.62628 | G26: {=(SUMPRODUCT('DCF + DDM'!$H$10:$Q$10/(1+$C26)^'DCF + DDM'!$H$12:$Q$12)+'DCF + DDM'!$L$27*(1+G$19)*(1-G$19/'DCF + DDM'!$L$28)/($C26-G$19)/(1+$C26)^'DCF + DDM'!$Q$12+SUM('DCF + DDM'!$D$31:$D$34))/'DCF + DDM'!$D$38} -> 153.61314 | H26: {=(SUMPRODUCT('DCF + DDM'!$H$10:$Q$10/(1+$C26)^'DCF + DDM'!$H$12:$Q$12)+'DCF + DDM'!$L$27*(1+H$19)*(1-H$19/'DCF + DDM'!$L$28)/($C26-H$19)/(1+$C26)^'DCF + DDM'!$Q$12+SUM('DCF + DDM'!$D$31:$D$34))/'DCF + DDM'!$D$38} -> 170.34601 | I26: {=(SUMPRODUCT('DCF + DDM'!$H$10:$Q$10/(1+$C26)^'DCF + DDM'!$H$12:$Q$12)+'DCF + DDM'!$L$27*(1+I$19)*(1-I$19/'DCF + DDM'!$L$28)/($C26-I$19)/(1+$C26)^'DCF + DDM'!$Q$12+SUM('DCF + DDM'!$D$31:$D$34))/'DCF + DDM'!$D$38} -> 192.72396 | J26: {=(SUMPRODUCT('DCF + DDM'!$H$10:$Q$10/(1+$C26)^'DCF + DDM'!$H$12:$Q$12)+'DCF + DDM'!$L$27*(1+J$19)*(1-J$19/'DCF + DDM'!$L$28)/($C26-J$19)/(1+$C26)^'DCF + DDM'!$Q$12+SUM('DCF + DDM'!$D$31:$D$34))/'DCF + DDM'!$D$38} -> 224.19079
B30: WACC - Total Payout - Sensitivity Table
D32: Perpetual Growth Rate
D33: =+E33-0.0025 -> 0.0175 | E33: =+F33-0.0025 -> 0.02 | F33: =+G33-0.0025 -> 0.0225 | G33: =+'DCF + DDM'!P28 -> 0.025 | H33: =+G33+0.0025 -> 0.0275 | I33: =+H33+0.0025 -> 0.03 | J33: =+I33+0.0025 -> 0.0325
B34: Ke | C34: =+C37+0.015 -> 0.078752566 | D34: {=(SUMPRODUCT('DCF + DDM'!$H$20:$Q$20/(1+$C34)^'DCF + DDM'!$H$12:$Q$12)+'DCF + DDM'!$Q$20*(1+D$33)/($C34-D$33)/(1+$C34)^'DCF + DDM'!$Q$12)/'DCF + DDM'!$D$38} -> 53.499072 | E34: {=(SUMPRODUCT('DCF + DDM'!$H$20:$Q$20/(1+$C34)^'DCF + DDM'!$H$12:$Q$12)+'DCF + DDM'!$Q$20*(1+E$33)/($C34-E$33)/(1+$C34)^'DCF + DDM'!$Q$12)/'DCF + DDM'!$D$38} -> 54.997062 | F34: {=(SUMPRODUCT('DCF + DDM'!$H$20:$Q$20/(1+$C34)^'DCF + DDM'!$H$12:$Q$12)+'DCF + DDM'!$Q$20*(1+F$33)/($C34-F$33)/(1+$C34)^'DCF + DDM'!$Q$12)/'DCF + DDM'!$D$38} -> 56.628199 | G34: {=(SUMPRODUCT('DCF + DDM'!$H$20:$Q$20/(1+$C34)^'DCF + DDM'!$H$12:$Q$12)+'DCF + DDM'!$Q$20*(1+G$33)/($C34-G$33)/(1+$C34)^'DCF + DDM'!$Q$12)/'DCF + DDM'!$D$38} -> 58.411064 | H34: {=(SUMPRODUCT('DCF + DDM'!$H$20:$Q$20/(1+$C34)^'DCF + DDM'!$H$12:$Q$12)+'DCF + DDM'!$Q$20*(1+H$33)/($C34-H$33)/(1+$C34)^'DCF + DDM'!$Q$12)/'DCF + DDM'!$D$38} -> 60.367857 | I34: {=(SUMPRODUCT('DCF + DDM'!$H$20:$Q$20/(1+$C34)^'DCF + DDM'!$H$12:$Q$12)+'DCF + DDM'!$Q$20*(1+I$33)/($C34-I$33)/(1+$C34)^'DCF + DDM'!$Q$12)/'DCF + DDM'!$D$38} -> 62.525337 | J34: {=(SUMPRODUCT('DCF + DDM'!$H$20:$Q$20/(1+$C34)^'DCF + DDM'!$H$12:$Q$12)+'DCF + DDM'!$Q$20*(1+J$33)/($C34-J$33)/(1+$C34)^'DCF + DDM'!$Q$12)/'DCF + DDM'!$D$38} -> 64.916045
C35: =+C37+0.01 -> 0.073752566 | D35: {=(SUMPRODUCT('DCF + DDM'!$H$20:$Q$20/(1+$C35)^'DCF + DDM'!$H$12:$Q$12)+'DCF + DDM'!$Q$20*(1+D$33)/($C35-D$33)/(1+$C35)^'DCF + DDM'!$Q$12)/'DCF + DDM'!$D$38} -> 58.701825 | E35: {=(SUMPRODUCT('DCF + DDM'!$H$20:$Q$20/(1+$C35)^'DCF + DDM'!$H$12:$Q$12)+'DCF + DDM'!$Q$20*(1+E$33)/($C35-E$33)/(1+$C35)^'DCF + DDM'!$Q$12)/'DCF + DDM'!$D$38} -> 60.560814 | F35: {=(SUMPRODUCT('DCF + DDM'!$H$20:$Q$20/(1+$C35)^'DCF + DDM'!$H$12:$Q$12)+'DCF + DDM'!$Q$20*(1+F$33)/($C35-F$33)/(1+$C35)^'DCF + DDM'!$Q$12)/'DCF + DDM'!$D$38} -> 62.601159 | G35: {=(SUMPRODUCT('DCF + DDM'!$H$20:$Q$20/(1+$C35)^'DCF + DDM'!$H$12:$Q$12)+'DCF + DDM'!$Q$20*(1+G$33)/($C35-G$33)/(1+$C35)^'DCF + DDM'!$Q$12)/'DCF + DDM'!$D$38} -> 64.85076 | H35: {=(SUMPRODUCT('DCF + DDM'!$H$20:$Q$20/(1+$C35)^'DCF + DDM'!$H$12:$Q$12)+'DCF + DDM'!$Q$20*(1+H$33)/($C35-H$33)/(1+$C35)^'DCF + DDM'!$Q$12)/'DCF + DDM'!$D$38} -> 67.343546 | I35: {=(SUMPRODUCT('DCF + DDM'!$H$20:$Q$20/(1+$C35)^'DCF + DDM'!$H$12:$Q$12)+'DCF + DDM'!$Q$20*(1+I$33)/($C35-I$33)/(1+$C35)^'DCF + DDM'!$Q$12)/'DCF + DDM'!$D$38} -> 70.121207 | J35: {=(SUMPRODUCT('DCF + DDM'!$H$20:$Q$20/(1+$C35)^'DCF + DDM'!$H$12:$Q$12)+'DCF + DDM'!$Q$20*(1+J$33)/($C35-J$33)/(1+$C35)^'DCF + DDM'!$Q$12)/'DCF + DDM'!$D$38} -> 73.235532
C36: =+C37+0.005 -> 0.068752566 | D36: {=(SUMPRODUCT('DCF + DDM'!$H$20:$Q$20/(1+$C36)^'DCF + DDM'!$H$12:$Q$12)+'DCF + DDM'!$Q$20*(1+D$33)/($C36-D$33)/(1+$C36)^'DCF + DDM'!$Q$12)/'DCF + DDM'!$D$38} -> 64.935299 | E36: {=(SUMPRODUCT('DCF + DDM'!$H$20:$Q$20/(1+$C36)^'DCF + DDM'!$H$12:$Q$12)+'DCF + DDM'!$Q$20*(1+E$33)/($C36-E$33)/(1+$C36)^'DCF + DDM'!$Q$12)/'DCF + DDM'!$D$38} -> 67.281411 | F36: {=(SUMPRODUCT('DCF + DDM'!$H$20:$Q$20/(1+$C36)^'DCF + DDM'!$H$12:$Q$12)+'DCF + DDM'!$Q$20*(1+F$33)/($C36-F$33)/(1+$C36)^'DCF + DDM'!$Q$12)/'DCF + DDM'!$D$38} -> 69.881143 | G36: {=(SUMPRODUCT('DCF + DDM'!$H$20:$Q$20/(1+$C36)^'DCF + DDM'!$H$12:$Q$12)+'DCF + DDM'!$Q$20*(1+G$33)/($C36-G$33)/(1+$C36)^'DCF + DDM'!$Q$12)/'DCF + DDM'!$D$38} -> 72.77797 | H36: {=(SUMPRODUCT('DCF + DDM'!$H$20:$Q$20/(1+$C36)^'DCF + DDM'!$H$12:$Q$12)+'DCF + DDM'!$Q$20*(1+H$33)/($C36-H$33)/(1+$C36)^'DCF + DDM'!$Q$12)/'DCF + DDM'!$D$38} -> 76.025905 | I36: {=(SUMPRODUCT('DCF + DDM'!$H$20:$Q$20/(1+$C36)^'DCF + DDM'!$H$12:$Q$12)+'DCF + DDM'!$Q$20*(1+I$33)/($C36-I$33)/(1+$C36)^'DCF + DDM'!$Q$12)/'DCF + DDM'!$D$38} -> 79.692901 | J36: {=(SUMPRODUCT('DCF + DDM'!$H$20:$Q$20/(1+$C36)^'DCF + DDM'!$H$12:$Q$12)+'DCF + DDM'!$Q$20*(1+J$33)/($C36-J$33)/(1+$C36)^'DCF + DDM'!$Q$12)/'DCF + DDM'!$D$38} -> 83.865654
C37: =+WACC!$D$17 -> 0.063752566 | D37: {=(SUMPRODUCT('DCF + DDM'!$H$20:$Q$20/(1+$C37)^'DCF + DDM'!$H$12:$Q$12)+'DCF + DDM'!$Q$20*(1+D$33)/($C37-D$33)/(1+$C37)^'DCF + DDM'!$Q$12)/'DCF + DDM'!$D$38} -> 72.534486 | E37: {=(SUMPRODUCT('DCF + DDM'!$H$20:$Q$20/(1+$C37)^'DCF + DDM'!$H$12:$Q$12)+'DCF + DDM'!$Q$20*(1+E$33)/($C37-E$33)/(1+$C37)^'DCF + DDM'!$Q$12)/'DCF + DDM'!$D$38} -> 75.556187 | F37: {=(SUMPRODUCT('DCF + DDM'!$H$20:$Q$20/(1+$C37)^'DCF + DDM'!$H$12:$Q$12)+'DCF + DDM'!$Q$20*(1+F$33)/($C37-F$33)/(1+$C37)^'DCF + DDM'!$Q$12)/'DCF + DDM'!$D$38} -> 78.944132 | G37: {=(SUMPRODUCT('DCF + DDM'!$H$20:$Q$20/(1+$C37)^'DCF + DDM'!$H$12:$Q$12)+'DCF + DDM'!$Q$20*(1+G$33)/($C37-G$33)/(1+$C37)^'DCF + DDM'!$Q$12)/'DCF + DDM'!$D$38} -> 82.769202 | H37: {=(SUMPRODUCT('DCF + DDM'!$H$20:$Q$20/(1+$C37)^'DCF + DDM'!$H$12:$Q$12)+'DCF + DDM'!$Q$20*(1+H$33)/($C37-H$33)/(1+$C37)^'DCF + DDM'!$Q$12)/'DCF + DDM'!$D$38} -> 87.12183 | I37: {=(SUMPRODUCT('DCF + DDM'!$H$20:$Q$20/(1+$C37)^'DCF + DDM'!$H$12:$Q$12)+'DCF + DDM'!$Q$20*(1+I$33)/($C37-I$33)/(1+$C37)^'DCF + DDM'!$Q$12)/'DCF + DDM'!$D$38} -> 92.119243 | J37: {=(SUMPRODUCT('DCF + DDM'!$H$20:$Q$20/(1+$C37)^'DCF + DDM'!$H$12:$Q$12)+'DCF + DDM'!$Q$20*(1+J$33)/($C37-J$33)/(1+$C37)^'DCF + DDM'!$Q$12)/'DCF + DDM'!$D$38} -> 97.916177
C38: =+C37-0.005 -> 0.058752566 | D38: {=(SUMPRODUCT('DCF + DDM'!$H$20:$Q$20/(1+$C38)^'DCF + DDM'!$H$12:$Q$12)+'DCF + DDM'!$Q$20*(1+D$33)/($C38-D$33)/(1+$C38)^'DCF + DDM'!$Q$12)/'DCF + DDM'!$D$38} -> 81.996826 | E38: {=(SUMPRODUCT('DCF + DDM'!$H$20:$Q$20/(1+$C38)^'DCF + DDM'!$H$12:$Q$12)+'DCF + DDM'!$Q$20*(1+E$33)/($C38-E$33)/(1+$C38)^'DCF + DDM'!$Q$12)/'DCF + DDM'!$D$38} -> 85.987578 | F38: {=(SUMPRODUCT('DCF + DDM'!$H$20:$Q$20/(1+$C38)^'DCF + DDM'!$H$12:$Q$12)+'DCF + DDM'!$Q$20*(1+F$33)/($C38-F$33)/(1+$C38)^'DCF + DDM'!$Q$12)/'DCF + DDM'!$D$38} -> 90.528739 | G38: {=(SUMPRODUCT('DCF + DDM'!$H$20:$Q$20/(1+$C38)^'DCF + DDM'!$H$12:$Q$12)+'DCF + DDM'!$Q$20*(1+G$33)/($C38-G$33)/(1+$C38)^'DCF + DDM'!$Q$12)/'DCF + DDM'!$D$38} -> 95.742613 | H38: {=(SUMPRODUCT('DCF + DDM'!$H$20:$Q$20/(1+$C38)^'DCF + DDM'!$H$12:$Q$12)+'DCF + DDM'!$Q$20*(1+H$33)/($C38-H$33)/(1+$C38)^'DCF + DDM'!$Q$12)/'DCF + DDM'!$D$38} -> 101.79064 | I38: {=(SUMPRODUCT('DCF + DDM'!$H$20:$Q$20/(1+$C38)^'DCF + DDM'!$H$12:$Q$12)+'DCF + DDM'!$Q$20*(1+I$33)/($C38-I$33)/(1+$C38)^'DCF + DDM'!$Q$12)/'DCF + DDM'!$D$38} -> 108.8904 | J38: {=(SUMPRODUCT('DCF + DDM'!$H$20:$Q$20/(1+$C38)^'DCF + DDM'!$H$12:$Q$12)+'DCF + DDM'!$Q$20*(1+J$33)/($C38-J$33)/(1+$C38)^'DCF + DDM'!$Q$12)/'DCF + DDM'!$D$38} -> 117.34237
C39: =+C37-0.01 -> 0.053752566 | D39: {=(SUMPRODUCT('DCF + DDM'!$H$20:$Q$20/(1+$C39)^'DCF + DDM'!$H$12:$Q$12)+'DCF + DDM'!$Q$20*(1+D$33)/($C39-D$33)/(1+$C39)^'DCF + DDM'!$Q$12)/'DCF + DDM'!$D$38} -> 94.094238 | E39: {=(SUMPRODUCT('DCF + DDM'!$H$20:$Q$20/(1+$C39)^'DCF + DDM'!$H$12:$Q$12)+'DCF + DDM'!$Q$20*(1+E$33)/($C39-E$33)/(1+$C39)^'DCF + DDM'!$Q$12)/'DCF + DDM'!$D$38} -> 99.535041 | F39: {=(SUMPRODUCT('DCF + DDM'!$H$20:$Q$20/(1+$C39)^'DCF + DDM'!$H$12:$Q$12)+'DCF + DDM'!$Q$20*(1+F$33)/($C39-F$33)/(1+$C39)^'DCF + DDM'!$Q$12)/'DCF + DDM'!$D$38} -> 105.8463 | G39: {=(SUMPRODUCT('DCF + DDM'!$H$20:$Q$20/(1+$C39)^'DCF + DDM'!$H$12:$Q$12)+'DCF + DDM'!$Q$20*(1+G$33)/($C39-G$33)/(1+$C39)^'DCF + DDM'!$Q$12)/'DCF + DDM'!$D$38} -> 113.25508 | H39: {=(SUMPRODUCT('DCF + DDM'!$H$20:$Q$20/(1+$C39)^'DCF + DDM'!$H$12:$Q$12)+'DCF + DDM'!$Q$20*(1+H$33)/($C39-H$33)/(1+$C39)^'DCF + DDM'!$Q$12)/'DCF + DDM'!$D$38} -> 122.07491 | I39: {=(SUMPRODUCT('DCF + DDM'!$H$20:$Q$20/(1+$C39)^'DCF + DDM'!$H$12:$Q$12)+'DCF + DDM'!$Q$20*(1+I$33)/($C39-I$33)/(1+$C39)^'DCF + DDM'!$Q$12)/'DCF + DDM'!$D$38} -> 132.75134 | J39: {=(SUMPRODUCT('DCF + DDM'!$H$20:$Q$20/(1+$C39)^'DCF + DDM'!$H$12:$Q$12)+'DCF + DDM'!$Q$20*(1+J$33)/($C39-J$33)/(1+$C39)^'DCF + DDM'!$Q$12)/'DCF + DDM'!$D$38} -> 145.93958
C40: =+C37-0.015 -> 0.048752566 | D40: {=(SUMPRODUCT('DCF + DDM'!$H$20:$Q$20/(1+$C40)^'DCF + DDM'!$H$12:$Q$12)+'DCF + DDM'!$Q$20*(1+D$33)/($C40-D$33)/(1+$C40)^'DCF + DDM'!$Q$12)/'DCF + DDM'!$D$38} -> 110.09268 | E40: {=(SUMPRODUCT('DCF + DDM'!$H$20:$Q$20/(1+$C40)^'DCF + DDM'!$H$12:$Q$12)+'DCF + DDM'!$Q$20*(1+E$33)/($C40-E$33)/(1+$C40)^'DCF + DDM'!$Q$12)/'DCF + DDM'!$D$38} -> 117.82548 | F40: {=(SUMPRODUCT('DCF + DDM'!$H$20:$Q$20/(1+$C40)^'DCF + DDM'!$H$12:$Q$12)+'DCF + DDM'!$Q$20*(1+F$33)/($C40-F$33)/(1+$C40)^'DCF + DDM'!$Q$12)/'DCF + DDM'!$D$38} -> 127.03105 | G40: {=(SUMPRODUCT('DCF + DDM'!$H$20:$Q$20/(1+$C40)^'DCF + DDM'!$H$12:$Q$12)+'DCF + DDM'!$Q$20*(1+G$33)/($C40-G$33)/(1+$C40)^'DCF + DDM'!$Q$12)/'DCF + DDM'!$D$38} -> 138.17443 | H40: {=(SUMPRODUCT('DCF + DDM'!$H$20:$Q$20/(1+$C40)^'DCF + DDM'!$H$12:$Q$12)+'DCF + DDM'!$Q$20*(1+H$33)/($C40-H$33)/(1+$C40)^'DCF + DDM'!$Q$12)/'DCF + DDM'!$D$38} -> 151.93946 | I40: {=(SUMPRODUCT('DCF + DDM'!$H$20:$Q$20/(1+$C40)^'DCF + DDM'!$H$12:$Q$12)+'DCF + DDM'!$Q$20*(1+I$33)/($C40-I$33)/(1+$C40)^'DCF + DDM'!$Q$12)/'DCF + DDM'!$D$38} -> 169.37466 | J40: {=(SUMPRODUCT('DCF + DDM'!$H$20:$Q$20/(1+$C40)^'DCF + DDM'!$H$12:$Q$12)+'DCF + DDM'!$Q$20*(1+J$33)/($C40-J$33)/(1+$C40)^'DCF + DDM'!$Q$12)/'DCF + DDM'!$D$38} -> 192.1737

Sheet FootBall Field and Ratios
C1: 2021 | D1: 2022 | E1: 2023 | F1: 2024 | G1: 2025 | H1: 2026 | I1: 2027 | J1: 2028 | K1: 2029 | L1: 2030 | M1: 2031 | N1: 2032 | O1: 2033 | P1: 2034 | Q1: 2035
B3: Profitability Ratios | R3: Historic Average | S3: Proyected Average | U3: Method | V3: Low | W3: Base | X3: High | Y3: Spread | Z3: Base vs Price | AA3: Range basis
B4: EBIT Margin | C4: =+IS!C28 -> 0.28736613 | D4: =+IS!D28 -> 0.29271012 | E4: =+IS!E28 -> 0.2912808 | F4: =+IS!F28 -> 0.22702945 | G4: =+IS!G28 -> 0.29784445 | H4: =+IS!H28 -> 0.28380113 | I4: =+IS!I28 -> 0.29015067 | J4: =+IS!J28 -> 0.29270078 | ... Q4: =+IS!Q28 -> 0.3221817 | R4: =+AVERAGE(C4:G4) -> 0.27924619 | S4: =+AVERAGE(H4:Q4) -> 0.30172578 | U4: DCF – Exit Multiple | V4: =MIN(Sensitivity!F8:H10) -> 85.36869 | W4: ='DCF + DDM'!D40 -> 92.135195 | X4: =MAX(Sensitivity!F8:H10) -> 99.39787 | Y4: =X4-V4 -> 14.02918 | Z4: =W4/$V$25-1 -> -0.0062000328 | AA4: WACC ±0.5% × Exit multiple ±1x
B5: EBITDA Margin | C5: =+IS!C62 -> 0.333773 | D5: =+IS!D62 -> 0.331204 | E5: =+IS!E62 -> 0.324589 | F5: =+IS!F62 -> 0.257671 | G5: =+IS!G62 -> 0.328118 | H5: =+IS!H62 -> 0.30704723 | I5: =+IS!I62 -> 0.31515874 | J5: =+IS!J62 -> 0.31778964 | ... Q5: =+IS!Q62 -> 0.35094663 | R5: =+AVERAGE(C5:G5) -> 0.315071 | S5: =+AVERAGE(H5:Q5) -> 0.3291622 | U5: DCF – Perpetual Growth | V5: =MIN(Sensitivity!F22:H24) -> 74.615042 | W5: ='DCF + DDM'!D41 -> 88.048146 | X5: =MAX(Sensitivity!F22:H24) -> 108.68515 | Y5: =X5-V5 -> 34.070107 | Z5: =W5/$V$25-1 -> -0.050284264 | AA5: WACC ±0.5% × g ±0.25%
B6: Net Margin | C6: =+IS!C47 -> 0.25360857 | D6: =+IS!D47 -> 0.22234354 | E6: =+IS!E47 -> 0.23377162 | F6: =+IS!F47 -> 0.22707209 | G6: =+IS!G47 -> 0.27333444 | H6: =+IS!H47 -> 0.21410956 | I6: =+IS!I47 -> 0.2190559 | J6: =+IS!J47 -> 0.22213107 | ... Q6: =+IS!Q47 -> 0.25030434 | R6: =+AVERAGE(C6:G6) -> 0.24202605 | S6: =+AVERAGE(H6:Q6) -> 0.23105656 | U6: DDM – Total Payout | V6: =MIN(Sensitivity!F36:H38) -> 69.881143 | W6: ='DCF + DDM'!D42 -> 82.769202 | X6: =MAX(Sensitivity!F36:H38) -> 101.79064 | Y6: =X6-V6 -> 31.909496 | Z6: =W6/$V$25-1 -> -0.10722466 | AA6: Ke ±0.5% × g ±0.25%
B7: Basic BPA / Diluted BPA | C7: =+(IS!C54/IS!C57) -> 1.0057937 | D7: =+(IS!D54/IS!D57) -> 1.0050832 | E7: =+(IS!E54/IS!E57) -> 1.0037011 | F7: =+(IS!F54/IS!F57) -> 1.0025528 | G7: =+(IS!G54/IS!G57) -> 1.002324 | H7: =+(IS!H54/IS!H57) -> 1.003891 | I7: =+(IS!I54/IS!I57) -> 1.003891 | J7: =+(IS!J54/IS!J57) -> 1.003891 | ... Q7: =+(IS!Q54/IS!Q57) -> 1.003891 | R7: =+AVERAGE(C7:G7) -> 1.003891 | S7: =+AVERAGE(H7:Q7) -> 1.003891 | U7: Trading Comps – P/E | V7: =V17*$V$15 -> 43.372446 | W7: =V18*$V$15 -> 50.420717 | X7: =V19*$V$15 -> 63.155224 | Y7: =X7-V7 -> 19.782778 | Z7: =W7/$V$25-1 -> -0.45614586 | AA7: Peer P/E 25th–75th pct × FY25 diluted EPS
U8: Trading Comps – Dividend Yield | V8: =$V$16/V22 -> 54.920479 | W8: =$V$16/V21 -> 67.52226 | X8: =$V$16/V20 -> 75.653935 | Y8: =X8-V8 -> 20.733456 | Z8: =W8/$V$25-1 -> -0.2716831 | AA8: FY25 DPS ÷ peer yield 75th–25th pct
B9: Return Ratios | R9: Historic Average | S9: Proyected Average
B10: ROE | C10: =+IS!C51/(BS!C44-BS!C43) -> 0.42484456 | D10: =+IS!D51/(BS!D44-BS!D43) -> 0.39585148 | E10: =+IS!E51/(BS!E44-BS!E43) -> 0.41301415 | F10: =+IS!F51/(BS!F44-BS!F43) -> 0.42770357 | G10: =+IS!G51/(BS!G44-BS!G43) -> 0.40744195 | H10: =+IS!H51/(BS!H44-BS!H43) -> 0.29831105 | I10: =+IS!I51/(BS!I44-BS!I43) -> 0.30244971 | J10: =+IS!J51/(BS!J44-BS!J43) -> 0.31927027 | ... Q10: =+IS!Q51/(BS!Q44-BS!Q43) -> 0.48135473 | R10: =+AVERAGE(C10:G10) -> 0.41377114 | S10: =+AVERAGE(H10:Q10) -> 0.37520443 | U10: Valuation range (avg. of methods) | V10: =AVERAGE(V4:V8) -> 65.63156 | W10: =AVERAGE(W4:W8) -> 76.179104 | X10: =AVERAGE(X4:X8) -> 89.736564 | Y10: =X10-V10 -> 24.105004 | Z10: =W10/$V$25-1 -> -0.17830758
B11: ROIC | C11: =+'DCF + DDM'!C6/(BS!C9+BS!C10+BS!C11-BS!C24-BS!C25-BS!C26+BS!C17) -> 0.14080402 | D11: =+'DCF + DDM'!D6/(BS!D9+BS!D10+BS!D11-BS!D24-BS!D25-BS!D26+BS!D17) -> 0.14744501 | E11: =+'DCF + DDM'!E6/(BS!E9+BS!E10+BS!E11-BS!E24-BS!E25-BS!E26+BS!E17) -> 0.14376697 | F11: =+'DCF + DDM'!F6/(BS!F9+BS!F10+BS!F11-BS!F24-BS!F25-BS!F26+BS!F17) -> 0.11401046 | G11: =+'DCF + DDM'!G6/(BS!G9+BS!G10+BS!G11-BS!G24-BS!G25-BS!G26+BS!G17) -> 0.15812333 | H11: =+'DCF + DDM'!H6/(BS!H9+BS!H10+BS!H11-BS!H24-BS!H25-BS!H26+BS!H17) -> 0.14202768 | I11: =+'DCF + DDM'!I6/(BS!I9+BS!I10+BS!I11-BS!I24-BS!I25-BS!I26+BS!I17) -> 0.14592366 | J11: =+'DCF + DDM'!J6/(BS!J9+BS!J10+BS!J11-BS!J24-BS!J25-BS!J26+BS!J17) -> 0.15368345 | ... Q11: =+'DCF + DDM'!Q6/(BS!Q9+BS!Q10+BS!Q11-BS!Q24-BS!Q25-BS!Q26+BS!Q17) -> 0.22600838 | R11: =+AVERAGE(C11:G11) -> 0.14082996 | S11: =+AVERAGE(H11:Q11) -> 0.17848556
B12: ROCE | C12: =+IS!C27/(BS!C19-BS!C28) -> 0.14930649 | D12: =+IS!D27/(BS!D19-BS!D28) -> 0.17251058 | E12: =+IS!E27/(BS!E19-BS!E28) -> 0.17989532 | F12: =+IS!F27/(BS!F19-BS!F28) -> 0.14139442 | G12: =+IS!G27/(BS!G19-BS!G28) -> 0.1713653 | H12: =+IS!H27/(BS!H19-BS!H28) -> 0.16063141 | I12: =+IS!I27/(BS!I19-BS!I28) -> 0.1646938 | J12: =+IS!J27/(BS!J19-BS!J28) -> 0.17341417 | ... Q12: =+IS!Q27/(BS!Q19-BS!Q28) -> 0.25468952 | R12: =+AVERAGE(C12:G12) -> 0.16289442 | S12: =+AVERAGE(H12:Q12) -> 0.20128617
B13: ROA | C13: =+IS!C46/BS!C19 -> 0.10390656 | D13: =+IS!D46/BS!D19 -> 0.10317691 | E13: =+IS!E46/BS!E19 -> 0.10954628 | F13: =+IS!F46/BS!F19 -> 0.10590856 | G13: =+IS!G46/BS!G19 -> 0.12533392 | H13: =+IS!H46/BS!H19 -> 0.098978011 | I13: =+IS!I46/BS!I19 -> 0.10155133 | J13: =+IS!J46/BS!J19 -> 0.10684262 | ... Q13: =+IS!Q46/BS!Q19 -> 0.15320525 | R13: =+AVERAGE(C13:G13) -> 0.10957445 | S13: =+AVERAGE(H13:Q13) -> 0.12279259
B14: Payout | C14: =+CF!C28*-1/IS!C51 -> 0.7421963 | D14: =+CF!D28*-1/IS!D51 -> 0.79815552 | E14: =+CF!E28*-1/IS!E51 -> 0.74220646 | F14: =+CF!F28*-1/IS!F51 -> 0.78628539 | G14: =+CF!G28*-1/IS!G51 -> 0.66979477 | H14: =+CF!H28*-1/IS!H51 -> 0.73276221 | I14: =+CF!I28*-1/IS!I51 -> 0.73276221 | J14: =+CF!J28*-1/IS!J51 -> 0.73276221 | ... Q14: =+CF!Q28*-1/IS!Q51 -> 0.73276221 | R14: =+AVERAGE(C14:G14) -> 0.74772769 | S14: =+AVERAGE(H14:Q14) -> 0.73276221 | U14: Relative valuation inputs
U15: KO diluted EPS FY2025 ($) | V15: =IS!G57 -> 3.038952
B16: Leverage Ratios | R16: Historic Average | S16: Proyected Average | U16: KO DPS FY2025 ($) | V16: =-CF!G28/IS!G58 -> 2.0354741
B17: Net Debt | C17: =+BS!C27+BS!C30+BS!C31+BS!C32-BS!C7-BS!C8 -> 33255 | D17: =+BS!D27+BS!D30+BS!D31+BS!D32-BS!D7-BS!D8 -> 29712 | E17: =+BS!E27+BS!E30+BS!E31+BS!E32-BS!E7-BS!E8 -> 32084 | F17: =+BS!F27+BS!F30+BS!F31+BS!F32-BS!F7-BS!F8 -> 32102 | G17: =+BS!G27+BS!G30+BS!G31+BS!G32-BS!G7-BS!G8 -> 33551 | H17: =+BS!H27+BS!H30+BS!H31+BS!H32-BS!H7-BS!H8 -> 31943.841 | I17: =+BS!I27+BS!I30+BS!I31+BS!I32-BS!I7-BS!I8 -> 31741.986 | J17: =+BS!J27+BS!J30+BS!J31+BS!J32-BS!J7-BS!J8 -> 31832.528 | ... Q17: =+BS!Q27+BS!Q30+BS!Q31+BS!Q32-BS!Q7-BS!Q8 -> 32557.625 | R17: =+AVERAGE(C17:G17) -> 32140.8 | S17: =+AVERAGE(H17:Q17) -> 32112.608 | U17: Peer P/E – 25th percentile | V17: =_xlfn.QUARTILE.INC(RV!I5:I17,1) -> 14.272172
B18: Net Debt/EBITDA | C18: =+C17/IS!C61 -> 2.5773076 | D18: =+D17/IS!D61 -> 2.0840289 | E18: =+E17/IS!E61 -> 2.1589395 | F18: =+F17/IS!F61 -> 2.6565707 | G18: =+G17/IS!G61 -> 2.1275206 | H18: =+H17/IS!H61 -> 2.1173341 | I18: =+I17/IS!I61 -> 2.0204958 | J18: =+J17/IS!J61 -> 1.9125272 | ... Q18: =+Q17/IS!Q61 -> 1.2776097 | R18: =+AVERAGE(C18:G18) -> 2.3208735 | S18: =+AVERAGE(H18:Q18) -> 1.6754524 | U18: Peer P/E – Median | V18: =MEDIAN(RV!I5:I17) -> 16.591482
B19: Net Debt/Equity | C19: =+C17/BS!C44 -> 1.3376911 | D19: =+D17/BS!D44 -> 1.1504685 | E19: =+E17/BS!E44 -> 1.16754 | F19: =+F17/BS!F44 -> 1.2172759 | G19: =+G17/BS!G44 -> 0.97887673 | H19: =+H17/BS!H44 -> 0.85474763 | I19: =+I17/BS!I44 -> 0.83073678 | J19: =+J17/BS!J44 -> 0.82583896 | ... Q19: =+Q17/BS!Q44 -> 0.81670396 | R19: =+AVERAGE(C19:G19) -> 1.1703705 | S19: =+AVERAGE(H19:Q19) -> 0.82542891 | U19: Peer P/E – 75th percentile | V19: =_xlfn.QUARTILE.INC(RV!I5:I17,3) -> 20.781909
B20: Interest Coverage (EBIT / Net interest) | C20: =+IS!C27/IS!C35 -> 5.1862745 | D20: =+IS!D27/IS!D35 -> 9.6403979 | E20: =+IS!E27/IS!E35 -> 5.4233428 | F20: =+IS!F27/IS!F35 -> 3.9891345 | G20: =+IS!G27/IS!G35 -> 5.9275362 | H20: =+IS!H27/IS!H35 -> 19.231818 | I20: =+IS!I27/IS!I35 -> 19.197226 | J20: =+IS!J27/IS!J35 -> 20.656722 | ... Q20: =+IS!Q27/IS!Q35 -> 30.408444 | R20: =+AVERAGE(C20:G20) -> 6.0333372 | S20: =+AVERAGE(H20:Q20) -> 23.966734 | U20: Peer dividend yield – 25th percentile | V20: =_xlfn.QUARTILE.INC(RV!K5:K17,1)/100 -> 0.026905066
U21: Peer dividend yield – Median | V21: =MEDIAN(RV!K5:K17)/100 -> 0.030145231
B22: Liquidity Ratios | R22: Historic Average | S22: Proyected Average | U22: Peer dividend yield – 75th percentile | V22: =_xlfn.QUARTILE.INC(RV!K5:K17,3)/100 -> 0.037062206
B23: OWC/Sales | C23: =(BS!C9+BS!C10+BS!C11-BS!C24-BS!C25-BS!C26)/IS!C5 -> -0.12985669 | D23: =(BS!D9+BS!D10+BS!D11-BS!D24-BS!D25-BS!D26)/IS!D5 -> -0.12718952 | E23: =(BS!E9+BS!E10+BS!E11-BS!E24-BS!E25-BS!E26)/IS!E5 -> -0.072798358 | F23: =(BS!F9+BS!F10+BS!F11-BS!F24-BS!F25-BS!F26)/IS!F5 -> -0.23967418 | G23: =(BS!G9+BS!G10+BS!G11-BS!G24-BS!G25-BS!G26)/IS!G5 -> 0.011027423 | H23: =(BS!H9+BS!H10+BS!H11-BS!H24-BS!H25-BS!H26)/IS!H5 -> 0.024418461 | I23: =(BS!I9+BS!I10+BS!I11-BS!I24-BS!I25-BS!I26)/IS!I5 -> 0.021948458 | J23: =(BS!J9+BS!J10+BS!J11-BS!J24-BS!J25-BS!J26)/IS!J5 -> 0.01429368 | ... Q23: =(BS!Q9+BS!Q10+BS!Q11-BS!Q24-BS!Q25-BS!Q26)/IS!Q5 -> -0.028262685 | R23: =AVERAGE(C23:G23) -> -0.11169826 | S23: =AVERAGE(H23:Q23) -> -0.0017605487
B24: Current Liquidity | C24: =+BS!C12/BS!C28 -> 1.1300752 | D24: =+BS!D12/BS!D28 -> 1.1453559 | E24: =+BS!E12/BS!E28 -> 1.1341055 | F24: =+BS!F12/BS!F28 -> 1.0296249 | G24: =+BS!G12/BS!G28 -> 1.458766 | H24: =+BS!H12/BS!H28 -> 1.6201025 | I24: =+BS!I12/BS!I28 -> 1.6190826 | J24: =+BS!J12/BS!J28 -> 1.5786151 | ... Q24: =+BS!Q12/BS!Q28 -> 1.3380966 | R24: =+AVERAGE(C24:G24) -> 1.1795855 | S24: =+AVERAGE(H24:Q24) -> 1.4875128
B25: Treasury Ratio | C25: =+BS!C7/BS!C28 -> 0.48541353 | D25: =+BS!D7/BS!D28 -> 0.48261002 | E25: =+BS!E7/BS!E28 -> 0.39735268 | F25: =+BS!F7/BS!F28 -> 0.42884867 | G25: =+BS!G7/BS!G28 -> 0.4825901 | H25: =+BS!H7/BS!H28 -> 0.50172311 | I25: =+BS!I7/BS!I28 -> 0.50744124 | J25: =+BS!J7/BS!J28 -> 0.48809203 | ... Q25: =+BS!Q7/BS!Q28 -> 0.37343203 | R25: =+AVERAGE(C25:G25) -> 0.455363 | S25: =+AVERAGE(H25:Q25) -> 0.44399977 | U25: Current share price ($) | V25: ='DCF + DDM'!D44 -> 92.71
B26: DSO (days) | C26: =BS!C9/IS!C5*365 -> 33.159501 | D26: =BS!D9/IS!D5*365 -> 29.567323 | E26: =BS!E9/IS!E5*365 -> 27.185261 | F26: =BS!F9/IS!F5*365 -> 27.777576 | G26: =BS!G9/IS!G5*365 -> 23.071657 | H26: =BS!H9/IS!H5*365 -> 28.152264 | I26: =BS!I9/IS!I5*365 -> 28.152264 | J26: =BS!J9/IS!J5*365 -> 28.152264 | ... Q26: =BS!Q9/IS!Q5*365 -> 28.152264 | R26: =AVERAGE(C26:G26) -> 28.152264 | S26: =AVERAGE(H26:Q26) -> 28.152264
B27: DIO (days) | C27: =BS!C10/IS!C16*365 -> 80.863725 | D27: =BS!D10/IS!D16*365 -> 84.971952 | E27: =BS!E10/IS!E16*365 -> 87.44977 | F27: =BS!F10/IS!F16*365 -> 94.539279 | G27: =BS!G10/IS!G16*365 -> 88.422479 | H27: =BS!H10/IS!H16*365 -> 87.249441 | I27: =BS!I10/IS!I16*365 -> 87.249441 | J27: =BS!J10/IS!J16*365 -> 87.249441 | ... Q27: =BS!Q10/IS!Q16*365 -> 87.249441 | R27: =AVERAGE(C27:G27) -> 87.249441 | S27: =AVERAGE(H27:Q27) -> 87.249441
B28: DPO (days) | C28: =BS!C24/IS!C16*365 -> 109.0026 | D28: =BS!D24/IS!D16*365 -> 106.5311 | E28: =BS!E24/IS!E16*365 -> 110.49824 | F28: =BS!F24/IS!F16*365 -> 109.33604 | G28: =BS!G24/IS!G16*365 -> 112.88104 | H28: =BS!H24/IS!H16*365 -> 109.58596 | I28: =BS!I24/IS!I16*365 -> 109.58596 | J28: =BS!J24/IS!J16*365 -> 109.58596 | ... Q28: =BS!Q24/IS!Q16*365 -> 109.58596 | R28: =AVERAGE(C28:G28) -> 109.6498 | S28: =AVERAGE(H28:Q28) -> 109.58596
B29: Cycle Days (DSO+DIO-DPO) | C29: =C26+C27-C28 -> 5.0206304 | D29: =D26+D27-D28 -> 8.0081747 | E29: =E26+E27-E28 -> 4.1367911 | F29: =F26+F27-F28 -> 12.98082 | G29: =G26+G27-G28 -> -1.3868994 | H29: =H26+H27-H28 -> 5.815743 | I29: =I26+I27-I28 -> 5.815743 | J29: =J26+J27-J28 -> 5.815743 | ... Q29: =Q26+Q27-Q28 -> 5.815743 | R29: =AVERAGE(C29:G29) -> 5.7519033 | S29: =AVERAGE(H29:Q29) -> 5.815743
B31: Asset Ratios | R31: Historic Average | S31: Proyected Average
B32: CapEx/Sales | C32: =+CF!C21*-1/IS!C5 -> 0.035361374 | D32: =+CF!D21*-1/IS!D5 -> 0.034474748 | E32: =+CF!E21*-1/IS!E5 -> 0.040450813 | F32: =+CF!F21*-1/IS!F5 -> 0.044011344 | G32: =+CF!G21*-1/IS!G5 -> 0.04394324 | H32: =+CF!H21*-1/IS!H5 -> 0.042801799 | I32: =+CF!I21*-1/IS!I5 -> 0.042801799 | J32: =+CF!J21*-1/IS!J5 -> 0.042801799 | ... Q32: =+CF!Q21*-1/IS!Q5 -> 0.042801799 | R32: =+AVERAGE(C32:G32) -> 0.039648304 | S32: =+AVERAGE(H32:Q32) -> 0.042801799
B33: Asset longevity - Remaining life (Net PP&E / D&A, yrs) | C33: =BS!C14/CF!C8 -> 7.8085399 | D33: =BS!D14/CF!D8 -> 8.9261905 | E33: =BS!E14/CF!E8 -> 9.3652482 | F33: =BS!F14/CF!F8 -> 10.683721 | G33: =BS!G14/CF!G8 -> 10.771429 | H33: =BS!H14/CF!H8 -> 10.743177 | I33: =BS!I14/CF!I8 -> 10.554994 | J33: =BS!J14/CF!J8 -> 10.719375 | ... Q33: =BS!Q14/CF!Q8 -> 9.7377739 | R33: =AVERAGE(C33:G33) -> 9.5110256 | S33: =AVERAGE(H33:Q33) -> 9.9172611
B34: Avg useful life (Gross PP&E / Depreciation, yrs) | C34: ='Balance Sheet'!C25/CR!C72 -> 16.069731 | D34: ='Balance Sheet'!D25/CR!D72 -> 18.205333 | E34: ='Balance Sheet'!E25/CR!E72 -> 19.446955 | F34: ='Balance Sheet'!F25/CR!F72 -> 20.7643 | G34: ='Balance Sheet'!G25/CR!G72 -> 20.888548 | R34: =AVERAGE(C34:G34) -> 19.074973 | S34: n/a
B35: Avg asset age (Accum. Dep. / Depreciation, yrs) | C35: ='Balance Sheet'!C26/CR!C72 -> 7.0855784 | D35: ='Balance Sheet'!D26/CR!D72 -> 8.208 | E35: ='Balance Sheet'!E26/CR!E72 -> 9.0697446 | F35: ='Balance Sheet'!F26/CR!F72 -> 9.4378698 | G35: ='Balance Sheet'!G26/CR!G72 -> 9.3241309 | R35: =AVERAGE(C35:G35) -> 8.6250647 | S35: n/a
B36: Reinvestment Ratio | C36: =+CF!C21*-1/CF!C8 -> 0.94146006 | D36: =+CF!D21*-1/CF!D8 -> 1.1777778 | E36: =+CF!E21*-1/CF!E8 -> 1.641844 | F36: =+CF!F21*-1/CF!F8 -> 1.92 | G36: =+CF!G21*-1/CF!G8 -> 2.0114286 | H36: =+CF!H21*-1/CF!H8 -> 1.8412462 | I36: =+CF!I21*-1/CF!I8 -> 1.7115193 | J36: =+CF!J21*-1/CF!J8 -> 1.7060076 | ... Q36: =+CF!Q21*-1/CF!Q8 -> 1.4879854 | R36: =+AVERAGE(C36:G36) -> 1.5385021 | S36: =+AVERAGE(H36:Q36) -> 1.5692116

Sheet General
A2: (KO US) - Info destacada aj BBG
A4: En Millones de USD | C4: FY 2019 | D4: FY 2020 | E4: FY 2021 | F4: FY 2022 | G4: FY 2023 | H4: FY 2024 | I4: FY 2025 | J4: Actual/Últ12M | K4: FY 2026 Est | L4: FY 2027 Est
A5: 12 meses fin | C5: 12/31/2019 | D5: 12/31/2020 | E5: 12/31/2021 | F5: 12/31/2022 | G5: 12/31/2023 | H5: 12/31/2024 | I5: 12/31/2025 | J5: 04/03/2026 | K5: 12/31/2026 | L5: 12/31/2027
A6: Capitalización de mercado | B6: HISTORICAL_MARKET_CAP | C6: 236898 | D6: 235921.68 | E6: 256083.25 | F6: 275304.08 | G6: 253870.44 | H6: 267842.52 | I6: 300752.82 | J6: 330516.7
A7: - Efectivo y equivalentes | B7: CASH_AND_MARKETABLE_SECURITIES | C7: 11175 | D7: 10914 | E7: 12625 | F7: 11631 | G7: 13663 | H7: 14571 | I7: 15806 | J7: 13820
A8: + Preferente y otros | B8: PFD_EQTY_MINORTY_INTEREST | C8: 2117 | D8: 1985 | E8: 1861 | F8: 1721 | G8: 1539 | H8: 1516 | I8: 2106 | J8: 2101
A9: + Deuda total | B9: SHORT_AND_LONG_TERM_DEBT | C9: 44155 | D9: 44415 | E9: 44232 | F9: 40603 | G9: 43426 | H9: 45735 | I9: 47214 | J9: 43890
A10: Valor de empresa | B10: ENTERPRISE_VALUE | C10: 271995 | D10: 271407.68 | E10: 289551.25 | F10: 305997.08 | G10: 285172.44 | H10: 300522.52 | I10: 334266.82 | J10: 362687.7
A12: Ingresos, aj | B12: SALES_REV_TURN | C12: 37280 | D12: 32999 | E12: 38658 | F12: 43046 | G12: 45784 | H12: 46897 | I12: 48062 | J12: 49317 | K12: 49085.5 | L12: 49992.636
A13: % Crec, YoY | B13: SALES_GROWTH | C13: 8.7166 | D13: -11.4834 | E13: 17.149 | F13: 11.3508 | G13: 6.3606 | H13: 2.431 | I13: 2.4842 | J13: 5.193891 | K13: 2.129541 | L13: 1.848074
A14: Beneficio bruto, aj | B14: GROSS_PROFIT | C14: 22660 | D14: 19501 | E14: 23248 | F14: 24863 | G14: 27319 | H14: 28643 | I14: 29796 | J14: 30641 | K14: 30467.861 | L14: 31400.875
A15: % Margen | B15: GROSS_PROFIT | C15: 60.783262 | D15: 59.09573 | E15: 60.137617 | F15: 57.759141 | G15: 59.669317 | H15: 61.076401 | I15: 61.994923 | J15: 62.130705 | K15: 62.071 | L15: 62.811
A16: EBITDA, aj | B16: EBITDA | C16: 12249 | D16: 11421 | E16: 12903 | F16: 14257 | G16: 14861 | H16: 12084 | I16: 15770 | J16: 15950 | K16: 17215.471 | L16: 18248.588
A17: % Margen | B17: EBITDA | C17: 32.85676 | D17: 34.61014 | E17: 33.377309 | F17: 33.120383 | G17: 32.458938 | H17: 25.767107 | I17: 32.811785 | J17: 32.341789 | K17: 35.072416 | L17: 36.502552
A18: Beneficio neto, aj | B18: EARN_FOR_COMMON | C18: 9171 | D18: 8435 | E18: 10086 | F18: 10803 | G18: 11515 | H18: 12373 | I18: 12940 | J18: 14058 | K18: 14104.381 | L18: 14962.857
A19: % Margen | B19: EARN_FOR_COMMON | C19: 24.600322 | D19: 25.561381 | E19: 26.090331 | F19: 25.096408 | G19: 25.150708 | H19: 26.383351 | I19: 26.923557 | J19: 28.505384 | K19: 28.734313 | L19: 29.930122
A20: BPA, aj | B20: IS_DIL_EPS_CONT_OPS | C20: 2.1282 | D20: 1.9491 | E20: 2.3226 | F20: 2.4799 | G20: 2.6546 | H20: 2.8632 | I20: 3.0013 | J20: 3.259655 | K20: 3.27 | L20: 3.48
A21: % Crec, YoY | B21: DILUTED_EPS_AFT_XO_ITEMS_GROWTH | C21: 0.1046 | D21: -8.4125 | E21: 19.1587 | F21: 6.7728 | G21: 7.0455 | H21: 7.8594 | I21: 4.8211 | J21: 13.160658 | K21: 8.9535132 | L21: 6.4220183
A23: Efectivo de operaciones | B23: CF_CASH_FROM_OPER | C23: 10471 | D23: 9844 | E23: 12625 | F23: 11018 | G23: 11599 | H23: 6805 | I23: 7408 | J23: 14631
A24: Gastos de capital | B24: CAPITAL_EXPEND | C24: -2054 | D24: -1177 | E24: -1367 | F24: -1484 | G24: -1852 | H24: -2064 | I24: -2112 | J24: -2077 | K24: -2201.714 | L24: -2148.357
A25: Flujo de caja libre | B25: CF_FREE_CASH_FLOW | C25: 8417 | D25: 8667 | E25: 11258 | F25: 9534 | G25: 9747 | H25: 4741 | I25: 5296 | J25: 12554 | K25: 12111.44 | L25: 13266.993
A26: Fuente: Bloomberg | C26: Hacer clic derecho para ver transparencia de datos (no disponible p/todos)

Sheet Ratios
A2: (KO US) - Rentabilidad
A4: En Millones de USD excepto por acción | C4: FY 2016 | D4: FY 2017 | E4: FY 2018 | F4: FY 2019 | G4: FY 2020 | H4: FY 2021 | I4: FY 2022 | J4: FY 2023 | K4: FY 2024 | L4: FY 2025
A5: 12 meses fin | C5: 12/31/2016 | D5: 12/31/2017 | E5: 12/31/2018 | F5: 12/31/2019 | G5: 12/31/2020 | H5: 12/31/2021 | I5: 12/31/2022 | J5: 12/31/2023 | K5: 12/31/2024 | L5: 12/31/2025
A6: Renta
A7: Retorno sobre el capital común | B7: RETURN_COM_EQY | C7: 26.8512 | D7: 6.2192 | E7: 37.7882 | F7: 49.6079 | G7: 40.4754 | H7: 46.2008 | I7: 40.5146 | J7: 42.8166 | K7: 41.8568 | L7: 45.9693
A8: Retorno en activos | B8: RETURN_ON_ASSET | C8: 7.3641 | D8: 1.4249 | E8: 7.5202 | F8: 10.5191 | G8: 8.9212 | H8: 10.7581 | I8: 10.199 | J8: 11.2503 | K8: 10.7247 | L8: 12.7646
A9: Retorno de capital: | B9: RETURN_ON_CAP | C9: 10.2877 | D9: 2.12 | E9: 11.0828 | F9: 15.208 | G9: 13.6126 | H9: 16.4167 | I9: 15.1908 | J9: 17.4243 | K9: 16.7769 | L9: 18.8745
A10: Retorno de capital invertido | B10: RETURN_ON_INV_CAPITAL | C10: 9.156 | D10: 1.776 | E10: 10.4133 | F10: 12.7578 | G10: 10.5562 | H10: 11.4384 | I10: 12.4269 | J10: 12.9607 | K10: 10.8189 | L10: 14.2502
A12: Márgenes
A13: Margen bruto | B13: GROSS_MARGIN | C13: 60.6693 | D13: 62.1092 | E13: 61.9038 | F13: 60.7712 | G13: 59.3112 | H13: 60.2716 | I13: 58.1434 | J13: 59.5227 | K13: 61.0633 | L13: 61.6257
A14: Margen EBITDA | B14: EBITDA_TO_REVENUE | C14: 24.874 | D14: 24.8951 | E14: 29.8484 | F14: 31.6052 | G14: 32.9739 | H14: 31.3077 | I14: 29.2205 | J14: 28.0544 | K14: 24.2855 | L14: 31.7411
A15: Margen operacional | B15: OPER_MARGIN | C15: 20.6053 | D15: 21.4156 | E15: 26.6822 | F15: 27.0649 | G15: 27.2521 | H15: 26.6667 | I15: 25.3674 | J15: 24.7213 | K15: 21.232 | L15: 28.7061
A16: Margen operacional gradual | B16: INCREMENTAL_OPERATING_MARGIN | C16: -4.1958 | D16: -15.4132 | E16: — | F16: 31.4902 | G16: -25.6115 | H16: 23.2406 | I16: 13.8193 | J16: 14.6182 | K16: — | L16: 428.4091
A17: Margen antes de impuestos | B17: PRETAX_INC_TO_NET_SALES | C17: 19.4348 | D17: 19.0268 | E17: 23.9796 | F17: 28.9433 | G17: 29.5299 | H17: 32.1433 | I17: 27.1742 | J17: 28.3079 | K17: 27.8065 | L17: 33.3702
A18: Margen ingreso antes de PE | B18: INC_BEF_XO_ITEMS_TO_NET_SALES | C18: 15.6463 | D18: 3.543 | E18: 18.8805 | F18: 24.1104 | G18: 23.5294 | H18: 25.3628 | I18: 22.2561 | J18: 23.3925 | K18: 22.6281 | L18: 27.4024
A19: Margen beneficio neto | B19: PROF_MARGIN | C19: 15.5913 | D19: 3.4464 | E19: 18.758 | F19: 23.936 | G19: 23.4658 | H19: 25.2775 | I19: 22.1886 | J19: 23.4165 | K19: 22.5898 | L19: 27.3399
A20: Beneficio neto a margen común | B20: NET_INCOME_TO_COMMON_MARGIN | C20: 15.5913 | D20: 3.4464 | E20: 18.758 | F20: 23.936 | G20: 23.4658 | H20: 25.2775 | I20: 22.1886 | J20: 23.4165 | K20: 22.5898 | L20: 27.3399
A22: Adicional
A23: Tasa impositiva efectiva | B23: EFF_TAX_RATE | C23: 19.4936 | D23: 81.3788 | E23: 21.2644 | F23: 16.6976 | G23: 20.32 | H23: 21.0946 | I23: 18.0986 | J23: 17.3641 | K23: 18.623 | L23: 17.8835
A24: Ratio de pago de dividendos | B24: DVD_PAYOUT_RATIO | C24: 92.5969 | D24: 506.6154 | E24: 103.2645 | F24: 76.6996 | G24: 90.9229 | H24: 74.191 | I24: 79.829 | J24: 74.2423 | K24: 78.6329 | L24: 66.9728
A25: Tasa de crecimiento sostenible | B25: SUSTAIN_GROWTH_RT | C25: 1.9878 | D25: -25.2881 | E25: -1.2336 | F25: 11.5589 | G25: 3.674 | H25: 11.924 | I25: 8.1722 | J25: 11.0286 | K25: 8.9436 | L25: 15.1824
A26: Fuente: Bloomberg | C26: Hacer clic derecho para ver transparencia de datos (no disponible p/todos)

Sheet CR
A2: (KO US) - Ajustados p/BBG
A4: En Millones de USD excepto por acción | C4: FY 2021 | D4: FY 2022 | E4: FY 2023 | F4: FY 2024 | G4: FY 2025 | H4: Últ 12M | I4: FY 2026 Est | J4: FY 2027 Est
A5: 12 meses fin | C5: 12/31/2021 | D5: 12/31/2022 | E5: 12/31/2023 | F5: 12/31/2024 | G5: 12/31/2025 | H5: 04/03/2026 | I5: 12/31/2026 | J5: 12/31/2027
A6: Ingreso | B6: SALES_REV_TURN | C6: 38658 | D6: 43046 | E6: 45784 | F6: 46897 | G6: 48062 | H6: 49317 | I6: 49085.5 | J6: 49992.636
A7: + Ingresos de servicios y ventas | B7: IS_SALES_AND_SERVICES_REVENUES | C7: 38658 | D7: 43046 | E7: 45784 | F7: 46897 | G7: 48062 | H7: 49317
A8: - Coste de ingreso | B8: IS_COGS_TO_FE_AND_PP_AND_G | C8: 15410 | D8: 18183 | E8: 18465 | F8: 18254 | G8: 18266 | H8: 18676
A9: + Coste de bienes y servicios | B9: IS_COG_AND_SERVICES_SOLD | C9: 15410 | D9: 18183 | E9: 18465 | F9: 18254 | G9: 18266 | H9: 18676
A10: Beneficio bruto | B10: GROSS_PROFIT | C10: 23248 | D10: 24863 | E10: 27319 | F10: 28643 | G10: 29796 | H10: 30641 | I10: 30467.861 | J10: 31400.875
A11: + Otros ingresos operacionales | B11: IS_OTHER_OPER_INC | C11: 0 | D11: 0 | E11: 0 | F11: 0 | G11: 0 | H11: 0
A12: - Gastos operacionales | B12: IS_OPERATING_EXPN | C12: 12139 | D12: 12263 | E12: 13983 | F12: 17996 | G12: 15481 | H12: 15738
A13: + Ventas, generales y admin | B13: IS_SGA_EXPENSE | C13: 12144 | D13: 12880 | E13: 13983 | F13: 14582 | G13: 14521 | H13: 14759
A14: + Investigación y desarrollo | B14: IS_OPERATING_EXPENSES_RD | C14: — | D14: — | E14: 0 | F14: 0 | G14: 0
A15: + Otro gasto operativo | B15: IS_OTHER_OPERATING_EXPENSES | C15: -5 | D15: -617 | E15: 0 | F15: 3414 | G15: 960 | H15: 979
A16: Ingreso operacional (pérdida) | B16: IS_OPER_INC | C16: 11109 | D16: 12600 | E16: 13336 | F16: 10647 | G16: 14315 | H16: 14903 | I16: 16000.842 | J16: 16980.316
A17: - Ingreso (pérdida) no operacional | B17: IS_NONOP_INCOME_LOSS | C17: -1318 | D17: -984 | E17: -958 | F17: -4570 | G17: -2030 | H17: -2187
A18: + Gasto de intereses, neto | B18: IS_NET_INTEREST_EXPENSE | C18: 2142 | D18: 409 | E18: 645 | F18: 693 | G18: 843 | H18: 807
A19: + Gastos de intereses | B19: IS_INT_EXPENSE | C19: 2418 | D19: 858 | E19: 1552 | F19: 1681 | G19: 1629 | H19: 1635
A20: - Ingreso de intereses | B20: IS_INT_INC | C20: 276 | D20: 449 | E20: 907 | F20: 988 | G20: 786 | H20: 828
A21: + (Plusvalía) pérdida del tipo de cambio | B21: IS_FOREIGN_EXCH_LOSS | C21: 61 | D21: 0 | E21: 0 | F21: 0 | G21: 0
A22: + Beneficio (pérdida) de filiales | B22: INCOME_LOSS_FROM_AFFILIATES | C22: -1438 | D22: -1472 | E22: -1691 | F22: -1770 | G22: -2031 | H22: -2084
A23: + Otro (ingreso) pérdida no op | B23: IS_OTHER_NON_OPERATING_INC_LOSS | C23: -2083 | D23: 79 | E23: 88 | F23: -3493 | G23: -842 | H23: -910
A24: Beneficios (pérdidas) antes de impuestos, ajustados | B24: PRETAX_INC | C24: 12427 | D24: 13584 | E24: 14294 | F24: 15217 | G24: 16345 | H24: 17090 | I24: 17674 | J24: 18870
A25: - Pérdida anormal | B25: IS_ABNORMAL_ITEM | C25: 2 | D25: 1898 | E25: 1342 | F25: 2131 | G25: 347 | H25: 538
A26: + Gasto de fusión o adquisición | B26: IS_MERGER_ACQUISITION_EXPENSE | C26: -1173 | D26: 408 | E26: 836 | F26: 1377 | G26: -654 | H26: -360
A27: + Cancelación de activos | B27: IS_IMPAIRMENT_ASSETS | C27: 78 | D27: 153 | E27: 39 | F27: 920 | G27: 1110
A28: + Restructura | B28: IS_RESTRUCTURING_EXPENSES | C28: 378 | D28: 117 | E28: 191 | F28: 133 | G28: 97
A29: + Inversiones no realizadas | B29: IS_UNREALIZED_INVESTMENTS | C29: — | D29: — | E29: — | F29: — | G29: —
A30: + Otros elementos atípicos | B30: IS_OTHER_ONE_TIME_ITEMS | C30: 719 | D30: 1220 | E30: 276 | F30: -299 | G30: -206 | H30: -304
A31: Beneficios (pérdidas) antes de impuestos, GAAP | B31: PRETAX_INC | C31: 12425 | D31: 11686 | E31: 12952 | F31: 13086 | G31: 15998 | H31: 16552 | I31: 17674 | J31: 18870
A32: - Gasto de impuesto a la renta (Beneficio) | B32: IS_INC_TAX_EXP | C32: 2621 | D32: 2115 | E32: 2249 | F32: 2437 | G32: 2861 | H32: 2784
A33: + Impuesto sobre la renta actual | B33: IS_CURRENT_INCOME_TAX_BENEFIT | C33: — | D33: — | E33: — | F33: — | G33: —
A34: + Impuesto sobre la renta diferido | B34: IS_DEFERRED_INCOME_TAX_BENEFIT | C34: — | D34: — | E34: — | F34: — | G34: —
A35: Beneficios (pérdidas) de operaciones continuas | B35: IS_INC_BEF_XO_ITEM | C35: 9804 | D35: 9571 | E35: 10703 | F35: 10649 | G35: 13137 | H35: 13768 | I35: 14106 | J35: 14963.9
A36: - Pérdidas (ganancias) extraordinarias netas | B36: XO_GL_NET_OF_TAX | C36: 0 | D36: 0 | E36: 0 | F36: 0 | G36: 0 | H36: 0
A37: + Operaciones discontinuas | B37: IS_DISCONTINUED_OPERATIONS | C37: 0 | D37: 0 | E37: 0 | F37: 0 | G37: 0 | H37: 0
A38: + PE y cambios contables | B38: EXTRAORD_ITEMS_ACCOUNTING_CHANGS | C38: 0 | D38: 0 | E38: 0 | F38: 0 | G38: 0 | H38: 0
A39: Ingreso (pérdida) incl MI | B39: NI_INCLUDING_MINORITY_INT_RATIO | C39: 9804 | D39: 9571 | E39: 10703 | F39: 10649 | G39: 13137 | H39: 13768
A40: - Minoritarios | B40: MIN_NONCONTROL_INTEREST_CREDITS | C40: 33 | D40: 29 | E40: -11 | F40: 18 | G40: 30 | H40: 67
A41: Beneficio neto, GAAP | B41: NET_INCOME | C41: 9771 | D41: 9542 | E41: 10714 | F41: 10631 | G41: 13107 | H41: 13701 | I41: 14106 | J41: 14963.9
A42: - Dividendos preferentes | B42: IS_TOT_CASH_PFD_DVD | C42: 0 | D42: 0 | E42: 0 | F42: 0 | G42: 0 | H42: 0
A43: - Otros ajustes | B43: OTHER_ADJUSTMENTS | C43: 0 | D43: 0 | E43: 0 | F43: 0 | G43: 0 | H43: 0
A44: beneficio neto disponible a accionistas comunes, GAAP | B44: EARN_FOR_COMMON | C44: 9771 | D44: 9542 | E44: 10714 | F44: 10631 | G44: 13107 | H44: 13701 | I44: 14106 | J44: 14963.9
A46: Beneficio neto disponible a cap común, aj | B46: EARN_FOR_COMMON | C46: 10086 | D46: 10803 | E46: 11515 | F46: 12373 | G46: 12940 | H46: 14058 | I46: 14104.381 | J46: 14962.857
A47: Pérdidas atípicas netas (ganancias) | B47: IS_NET_ABNORMAL_ITEMS | C47: 315 | D47: 1261 | E47: 801 | F47: 1742 | G47: -167 | H47: 357
A48: Pérdidas (ganancias) extraordinarias netas | B48: XO_GL_NET_OF_TAX | C48: 0 | D48: 0 | E48: 0 | F48: 0 | G48: 0 | H48: 0
A50: Acciones promedio básicas pond | B50: IS_AVG_NUM_SH_FOR_EPS | C50: 4315 | D50: 4328 | E50: 4323 | F50: 4309 | G50: 4303 | H50: 4302
A51: BPA básicos, GAAP | B51: IS_EPS | C51: 2.26 | D51: 2.2 | E51: 2.48 | F51: 2.47 | G51: 3.05 | H51: 3.19 | I51: 3.27 | J51: 3.48
A52: BPA básicos de operaciones continuas, GAAP | B52: IS_EARN_BEF_XO_ITEMS_PER_SH | C52: 2.26 | D52: 2.2 | E52: 2.48 | F52: 2.47 | G52: 3.05 | H52: 3.19 | I52: 3.27 | J52: 3.48
A53: BPA básicos de ops cont, ajustados | B53: IS_BASIC_EPS_CONT_OPS | C53: 2.3374 | D53: 2.4961 | E53: 2.6637 | F53: 2.8714 | G53: 3.0072 | H53: 3.267184 | I53: 3.27 | J53: 3.48
A55: Acciones diluidas promedio pond | B55: IS_SH_FOR_DILUTED_EPS | C55: 4340 | D55: 4350 | E55: 4339 | F55: 4320 | G55: 4313 | H55: 4314
A56: BPA diluidos, GAAP | B56: IS_DILUTED_EPS | C56: 2.25 | D56: 2.19 | E56: 2.47 | F56: 2.46 | G56: 3.04 | H56: 3.18 | I56: 3.27 | J56: 3.48
A57: BPA diluidos de operaciones continuas valor, GAAP | B57: IS_DIL_EPS_BEF_XO | C57: 2.25 | D57: 2.19 | E57: 2.47 | F57: 2.46 | G57: 3.04 | H57: 3.18 | I57: 3.27 | J57: 3.48
A58: BPA diluidos de ops cont, ajustados | B58: IS_DIL_EPS_CONT_OPS | C58: 2.3226 | D58: 2.4799 | E58: 2.6546 | F58: 2.8632 | G58: 3.0013 | H58: 3.259655 | I58: 3.27 | J58: 3.48
A60: Referencia
A61: Norma de contabilidad | B61: ACCOUNTING_STANDARD | C61: US GAAP | D61: US GAAP | E61: US GAAP | F61: US GAAP | G61: US GAAP
A62: EBITDA | B62: EBITDA | C62: 12903 | D62: 14257 | E62: 14861 | F62: 12084 | G62: 15770 | H62: 15950 | I62: 17215.471 | J62: 18248.588
A63: Margen EBITDA (U12M) | B63: EBITDA_MARGIN | C63: 33.3773 | D63: 33.1204 | E63: 32.4589 | F63: 25.7671 | G63: 32.8118 | H63: 32.341789 | I63: 35.072416 | J63: 36.502552
A64: EBITA | B64: EBITA | C64: 11641 | D64: 13132 | E64: 13843 | F64: 11070 | G64: 14792
A65: EBIT | B65: EBIT | C65: 11109 | D65: 12600 | E65: 13336 | F65: 10647 | G65: 14315 | H65: 14903 | I65: 16000.842 | J65: 16980.316
A66: Margen bruto | B66: GROSS_MARGIN | C66: 60.1376 | D66: 57.7591 | E66: 59.6693 | F66: 61.0764 | G66: 61.9949 | H66: 62.130705 | I66: 62.071 | J66: 62.811
A67: Margen operacional | B67: OPER_MARGIN | C67: 28.7366 | D67: 29.271 | E67: 29.1281 | F67: 22.7029 | G67: 29.7844 | H67: 30.218789 | I67: 32.5979 | J67: 33.965634
A68: Margen de beneficio | B68: PROF_MARGIN | C68: 26.0903 | D68: 25.0964 | E68: 25.1507 | F68: 26.3834 | G68: 26.9236 | H68: 28.505384 | I68: 28.734313 | J68: 29.930122
A69: Ventas por empleado | B69: ACTUAL_SALES_PER_EMPL | C69: 489341.77 | D69: 521769.7 | E69: 578811.63 | F69: 672840.75 | G69: 729317.15
A70: Dividendos por acción | B70: EQY_DPS | C70: 1.68 | D70: 1.76 | E70: 1.84 | F70: 1.94 | G70: 2.04 | H70: 2.06 | I70: 2.187 | J70: 2.289
A71: Dividendos ordinarios totales en efectivo | B71: IS_TOT_CASH_COM_DVD | C71: 7249.2 | D71: 7617.28 | E71: 7954.32 | F71: 8359.46 | G71: 8778.12 | H71: 8863.65
A72: Gasto de depreciación | B72: IS_DEPR_EXP | C72: 1262 | D72: 1125 | E72: 1018 | F72: 1014 | G72: 978
A73: Gasto de renta | B73: BS_CURR_RENTAL_EXPENSE | C73: 342 | D73: 397 | E73: 397 | F73: 362 | G73: 405
A74: Fuente: Bloomberg

Sheet Balance Sheet
A2: (KO US) - Estandarizado
A4: En Millones de USD excepto por acción | C4: FY 2021 | D4: FY 2022 | E4: FY 2023 | F4: FY 2024 | G4: FY 2025
A5: 12 meses fin | C5: 12/31/2021 | D5: 12/31/2022 | E5: 12/31/2023 | F5: 12/31/2024 | G5: 12/31/2025
A6: Activo total
A7: + Efectivo, equivalentes y STI | B7: CASH_CASH_EQTY_STI_DETAILED | C7: 12625 | D7: 11631 | E7: 13663 | F7: 14571 | G7: 15806
A8: + Efectivo y equivalentes | B8: BS_CASH_NEAR_CASH_ITEM | C8: 9684 | D8: 9519 | E8: 9366 | F8: 10828 | G8: 10270
A9: + Inversiones a corto plazo | B9: BS_MKT_SEC_OTHER_ST_INVEST | C9: 2941 | D9: 2112 | E9: 4297 | F9: 3743 | G9: 5536
A10: + Cuentas y notas por cobrar | B10: BS_ACCT_NOTE_RCV | C10: 3512 | D10: 3487 | E10: 3410 | F10: 3569 | G10: 3038
A11: + Cuentas por cobrar, neto | B11: BS_ACCTS_REC_EXCL_NOTES_REC | C11: 3512 | D11: 3487 | E11: 3410 | F11: 3569 | G11: 3038
A12: + Notas por cobrar, netas | B12: NOTES_RECEIVABLE | C12: 0 | D12: 0 | E12: 0 | F12: 0 | G12: 0
A13: + Inventarios | B13: BS_INVENTORIES | C13: 3414 | D13: 4233 | E13: 4424 | F13: 4728 | G13: 4425
A14: + Mat primas | B14: INVTRY_RAW_MATERIALS | C14: 2133 | D14: 2627 | E14: 2618 | F14: 2794 | G14: 2708
A15: + Trabajo en proceso | B15: INVTRY_IN_PROGRESS | C15: 0 | D15: 0 | E15: 0 | F15: 0 | G15: 0
A16: + Bienes de consumo | B16: INVTRY_FINISHED_GOODS | C16: 982 | D16: 1247 | E16: 1449 | F16: 1524 | G16: 1375
A17: + Otro inventario | B17: BS_OTHER_INV | C17: 299 | D17: 359 | E17: 357 | F17: 410 | G17: 342
A18: + Otros activos a CP | B18: OTHER_CURRENT_ASSETS_DETAILED | C18: 2994 | D18: 3240 | E18: 5235 | F18: 3129 | G18: 7775
A19: + Activos derivados y de cobertura | B19: BS_DERIV_HEDGING_ASST_ST | C19: 196 | D19: 206 | E19: 209 | F19: 470 | G19: 247
A20: + Activos mantenidos para la venta | B20: BS_ASSETS_HELD_FOR_SALE_ST | C20: — | D20: — | E20: — | F20: — | G20: 5342
A21: + Operaciones discontinuas | B21: BS_ASSETS_OF_DISCONTINUED_OPS_ST | C21: — | D21: — | E21: — | F21: — | G21: —
A22: + Activos varios a CP | B22: BS_OTHER_CUR_ASSET_LESS_PREPAY | C22: 2798 | D22: 3034 | E22: 5026 | F22: 2659 | G22: 2186
A23: Activos totales actuales | B23: BS_CUR_ASSET_REPORT | C23: 22545 | D23: 22591 | E23: 26732 | F23: 25997 | G23: 31044
A24: + Propiedad, planta y equipo; neto | B24: BS_NET_FIX_ASSET | C24: 11338 | D24: 11247 | E24: 10564 | F24: 11485 | G24: 11310
A25: + Propiedad, planta y equipo | B25: BS_GROSS_FIX_ASSET | C25: 20280 | D25: 20481 | E25: 19797 | F25: 21055 | G25: 20429
A26: - Depreciación acumulada | B26: BS_ACCUM_DEPR | C26: 8942 | D26: 9234 | E26: 9233 | F26: 9570 | G26: 9119
A27: + Inversiones y cuentas por cobrar a LP | B27: BS_LT_INVEST | C27: 818 | D27: 501 | E27: 118 | F27: 0 | G27: 0
A28: + Inversiones a largo plazo | B28: BS_LONG_TERM_INVESTMENTS | C28: 818 | D28: 501 | E28: 118 | F28: — | G28: —
A29: + Otros activos a LP | B29: BS_OTHER_ASSETS_DEF_CHRG_OTHER | C29: 59653 | D29: 58424 | E29: 60289 | F29: 63067 | G29: 62462
A30: + Activos intangibles totales | B30: BS_DISCLOSED_INTANGIBLES | C30: 34613 | D30: 33631 | E30: 33223 | F30: 31440 | G30: 28022
A31: + Fondo de comercio | B31: BS_GOODWILL | C31: 19363 | D31: 18782 | E31: 18358 | F31: 18139 | G31: 15491
A32: + Otros activos intangibles | B32: OTHER_INTANGIBLE_ASSETS_DETAILED | C32: 15250 | D32: 14849 | E32: 14865 | F32: 13301 | G32: 12531
A33: + Activos de impuestos diferidos | B33: BS_DEFERRED_TAX_ASSETS_LT | C33: 2129 | D33: 1746 | E33: 1561 | F33: 1319 | G33: 1206
A34: + Activos de derivados y de cobertura | B34: BS_DERIV_HEDGING_ASST_LT | C34: 312 | D34: 38 | E34: 66 | F34: 117 | G34: 194
A35: + Costes de pensiones prepagados | B35: BS_PREPAID_PENSION_COSTS_LT | C35: 1545 | D35: 1602 | E35: 1543 | F35: 1219 | G35: 1116
A36: + Inversiones en filiales | B36: BS_INVEST_IN_ASSOC_CO | C36: 17598 | D36: 18264 | E36: 19671 | F36: 18087 | G36: 20235
A37: + Activos varios a LP | B37: OTHER_NONCURRENT_ASSETS_DETAILED | C37: 3456 | D37: 3143 | E37: 4225 | F37: 10885 | G37: 11689
A38: Activos totales no corrientes | B38: BS_TOT_NON_CUR_ASSET | C38: 71809 | D38: 70172 | E38: 70971 | F38: 74552 | G38: 73772
A39: Activos totales | B39: BS_TOT_ASSET | C39: 94354 | D39: 92763 | E39: 97703 | F39: 100549 | G39: 104816
A41: Pasivo y capital social
A42: + Cuentas por pagar y devengos | B42: ACCT_PAYABLE_ACCRUALS_DETAILED | C42: 14940 | D42: 16435 | E42: 16402 | F42: 22666 | G42: 14708
A43: + Cuentas por pagar | B43: BS_ACCT_PAYABLE | C43: 4602 | D43: 5307 | E43: 5590 | F43: 5468 | G43: 5649
A44: + Impuestos incurridos | B44: BS_TAXES_PAYABLE | C44: 686 | D44: 1203 | E44: 1569 | F44: 1387 | G44: 525
A45: + Interés y dividendos por pagar | B45: INTEREST_DIVIDENDS_PAYABLE | C45: — | D45: — | E45: — | F45: — | G45: —
A46: + Otras cuentas por pagar y en devengo | B46: BS_ACCRUAL | C46: 9652 | D46: 9925 | E46: 9243 | F46: 15811 | G46: 8534
A47: + Deuda CP | B47: BS_ST_BORROW | C47: 4955 | D47: 3113 | E47: 6878 | F47: 2437 | G47: 3694
A48: + Préstamos CP | B48: SHORT_TERM_DEBT_DETAILED | C48: 3307 | D48: 2373 | E48: 4557 | F48: 1499 | G48: 1551
A49: + Obligaciones de arrendamiento a CP | B49: ST_CAPITALIZED_LEASE_LIABILITIES | C49: 310 | D49: 341 | E49: 361 | F49: 290 | G49: 321
A50: + Arrendamientos de finanzas a CP | B50: ST_CAPITAL_LEASE_OBLIGATIONS | C50: — | D50: — | E50: — | F50: — | G50: —
A51: + Arrendamientos de operación a CP | B51: BS_ST_OPERATING_LEASE_LIABS | C51: 310 | D51: 341 | E51: 361 | F51: 290 | G51: 321
A52: + Porción corriente de deuda a LP | B52: BS_CURR_PORTION_LT_DEBT | C52: 1338 | D52: 399 | E52: 1960 | F52: 648 | G52: 1822
A53: + Otros pasivos a corto plazo | B53: OTHER_CURRENT_LIABS_SUB_DETAILED | C53: 55 | D53: 176 | E53: 291 | F53: 146 | G53: 2879
A54: + Ingreso diferido | B54: ST_DEFERRED_REVENUE | C54: 0 | D54: 0 | E54: 0 | F54: 0 | G54: 0
A55: + Derivados y cobertura | B55: BS_DERIV_HEDGING_LIAB_ST | C55: 55 | D55: 176 | E55: 291 | F55: 146 | G55: 309
A56: + Operaciones discontinuas | B56: BS_LIABS_OF_DISCONTINUED_OPS_ST | C56: — | D56: — | E56: — | F56: — | G56: —
A57: + Pasivos varios a CP | B57: OTHER_CURRENT_LIABS_DETAILED | C57: 0 | D57: 0 | E57: 0 | F57: 0 | G57: 2570
A58: Pasivos totales corrientes | B58: BS_CUR_LIAB | C58: 19950 | D58: 19724 | E58: 23571 | F58: 25249 | G58: 21281
A59: + Deuda LP | B59: BS_LT_BORROW | C59: 39277 | D59: 37490 | E59: 36548 | F59: 43298 | G59: 43520
A60: + Préstamos a largo plazo | B60: LONG_TERM_BORROWINGS_DETAILED | C60: 38116 | D60: 36377 | E60: 35547 | F60: 42375 | G60: 42119
A61: + Obligaciones de arrendamiento a LP | B61: LT_CAPITALIZED_LEASE_LIABILITIES | C61: 1161 | D61: 1113 | E61: 1001 | F61: 923 | G61: 1401
A62: + Arrendamientos de finanzas a LP | B62: LT_CAPITAL_LEASE_OBLIGATIONS | C62: — | D62: — | E62: — | F62: — | G62: —
A63: + Arrendamientos de operación a LP | B63: BS_LT_OPERATING_LEASE_LIABS | C63: 1161 | D63: 1113 | E63: 1001 | F63: 923 | G63: 1401
A64: + Otros pasivos a LP | B64: OTHER_NONCUR_LIABS_SUB_DETAILED | C64: 10267 | D64: 9723 | E64: 10104 | F64: 5630 | G64: 5740
A65: + Pasivos acum | B65: BS_ACCRUED_LIABILITIES | C65: 0 | D65: 0 | E65: 0 | F65: 0 | G65: 0
A66: + Pasivos de pensiones | B66: PENSION_LIABILITIES | C66: 1409 | D66: 855 | E66: 877 | F66: 871 | G66: 8
A67: + Ingreso diferido | B67: LT_DEFERRED_REVENUE | C67: 0 | D67: 0 | E67: 0 | F67: 0 | G67: 0
A68: + Pasivo de impuesto diferido | B68: BS_DEFERRED_TAX_LIABILITIES_LT | C68: 2821 | D68: 2914 | E68: 2639 | F68: 2469 | G68: 2406
A69: + Derivados y cobertura | B69: BS_DERIV_HEDGING_LIAB_LT | C69: 1 | D69: 25 | E69: 1157 | F69: 973 | G69: 740
A70: + Pasivos varios a LP | B70: OTHER_NONCURRENT_LIABS_DETAILED | C70: 6036 | D70: 5929 | E70: 5431 | F70: 1317 | G70: 2586
A71: Pasivos totales no corrientes | B71: NON_CUR_LIAB | C71: 49544 | D71: 47213 | E71: 46652 | F71: 48928 | G71: 49260
A72: Pasivos totales | B72: BS_TOT_LIAB2 | C72: 69494 | D72: 66937 | E72: 70223 | F72: 74177 | G72: 70541
A73: + Acciones preferentes y capital híbrido | B73: PFD_EQTY_HYBRID_CAPITAL | C73: 0 | D73: 0 | E73: 0 | F73: 0 | G73: 0
A74: + Capital en acciones y APIC | B74: BS_SH_CAP_AND_APIC | C74: 19876 | D74: 20582 | E74: 20969 | F74: 21561 | G74: 22341
... A83: Pasivo y capital totales | B83: TOT_LIAB_AND_EQY | C83: 94354 | D83: 92763 | E83: 97703 | F83: 100549 | G83: 104816
A85: Referencia
A86: Norma de contabilidad | B86: ACCOUNTING_STANDARD | C86: US GAAP | D86: US GAAP | E86: US GAAP | F86: US GAAP | G86: US GAAP
A87: Acciones en circulación: | B87: BS_SH_OUT | C87: 4325 | D87: 4328 | E87: 4308 | F87: 4302 | G87: 4302
A88: Núm de acciones de Tesorería | B88: BS_NUM_OF_TSY_SH | C88: 2715 | D88: 2712 | E88: 2732 | F88: 2738 | G88: 2738
A89: Obligaciones de pensión | B89: BS_PENSION_RSRV | C89: 1409 | D89: 855 | E89: 877 | F89: 871 | G89: 8
A90: Arriendos futuros mínimos de operaciones | B90: BS_FUTURE_MIN_OPER_LEASE_OBLIG | C90: 1647 | D90: 1614 | E90: 1522 | F90: 1378 | G90: 2019
A91: Arrend capital - Total | B91: BS_TOTAL_CAPITAL_LEASES | C91: — | D91: — | E91: — | F91: — | G91: —
A92: Opciones dadas en el periodo | B92: BS_OPTIONS_GRANTED | C92: 7 | D92: 7 | E92: 3 | F92: 2 | G92: 3
A93: Opciones en circulación al fin del periodo | B93: BS_OPTIONS_OUTSTANDING | C93: 75 | D93: 59 | E93: 47 | F93: 31 | G93: 27
A94: Deuda neta | B94: NET_DEBT | C94: 31607 | D94: 28972 | E94: 29763 | F94: 31164 | G94: 31408
A95: Deuda neta a capital | B95: NET_DEBT_TO_SHRHLDR_EQTY | C95: 127.14 | D95: 112.1815 | E95: 108.3079 | F95: 118.1708 | G95: 91.6353
A96: Ratio de capital ordinario tangible | B96: TCE_RATIO | C96: -19.4406 | D96: -16.1097 | E96: -11.2934 | F96: -9.527 | G96: 5.4002
A97: Ratio corriente | B97: CUR_RATIO | C97: 1.1301 | D97: 1.1454 | E97: 1.1341 | F97: 1.0296 | G97: 1.4588
A98: Ciclo de conversión de efectivo | B98: CASH_CONVERSION_CYCLE | C98: 15.2448 | D98: 11.1404 | E98: 6.5329 | F98: 9.9055 | G98: 3.8214
A99: Efectivo en el extranjero | B99: BS_CASH_HELD_OVERSEAS | C99: — | D99: — | E99: — | F99: — | G99: —
A100: Número de empleados | B100: NUM_OF_EMPLOYEES | C100: 79000 | D100: 82500 | E100: 79100 | F100: 69700 | G100: 65900
A101: Fuente: Bloomberg

Sheet FC
A2: (KO US) - Estandarizado
A4: En Millones de USD excepto por acción | C4: FY 2021 | D4: FY 2022 | E4: FY 2023 | F4: FY 2024 | G4: FY 2025 | H4: Últ 12M
A5: 12 meses fin | C5: 12/31/2021 | D5: 12/31/2022 | E5: 12/31/2023 | F5: 12/31/2024 | G5: 12/31/2025 | H5: 04/03/2026
A6: Efectivo de actividades operacionales
A7: + Ingreso neto | B7: CF_NET_INC | C7: 9771 | D7: 9542 | E7: 10714 | F7: 10631 | G7: 13107 | H7: 13701
A8: + Depreciación + amortización | B8: CF_DEPR_AMORT | C8: 1452 | D8: 1260 | E8: 1128 | F8: 1075 | G8: 1050 | H8: 1047
A9: + Partidas no monetarias | B9: NON_CASH_ITEMS_DETAILED | C9: 77 | D9: 821 | E9: 603 | F9: 1333 | G9: 459 | H9: 833
A10: + Compensación en acciones | B10: CF_STOCK_BASED_COMPENSATION | C10: 337 | D10: 356 | E10: 254 | F10: 286 | G10: 279 | H10: 272
A11: + Impuestos al ingreso diferidos | B11: CF_DEF_INC_TAX | C11: 894 | D11: -122 | E11: -2 | F11: -11 | G11: 517 | H11: 627
A12: + Otros ajustes no en efectivo | B12: OTHER_NON_CASH_ADJ_LESS_DETAILED | C12: -1154 | D12: 587 | E12: 351 | F12: 1058 | G12: -337 | H12: -66
A13: + Var en fondo de maniobra no en efectivo | B13: CF_CHNG_NON_CASH_WORK_CAP | C13: 1325 | D13: -605 | E13: -846 | F13: -6234 | G13: -7208 | H13: -950
A14: + Aum (baja) de otros | B14: INC_DEC_IN_OT_OP_AST_LIAB_DETAIL | C14: 1325 | D14: -605 | E14: -846 | F14: -6234 | G14: -7208 | H14: -950
A15: + Efectivo neto de ops disc | B15: CF_NET_CASH_DISCONT_OPS_OPER | C15: 0 | D15: 0 | E15: 0 | F15: 0 | G15: 0 | H15: 0
A16: Efectivo de actividades operacionales | B16: CF_CASH_FROM_OPER | C16: 12625 | D16: 11018 | E16: 11599 | F16: 6805 | G16: 7408 | H16: 14631
A18: Efectivo de actividades de inversión
A19: + Cambio en fijos e intangibles | B19: FIXED_INTANG_ASST_CHANGE | C19: -1259 | D19: -1409 | E19: -1778 | F19: -2024 | G19: -2099 | H19: -2062
A20: + Desp en fijos e intangibles | B20: DISPOSAL_OF_FIXED_INTANG | C20: 108 | D20: 75 | E20: 74 | F20: 40 | G20: 13 | H20: 15
A21: + Desp de activos fijos prod | B21: CF_DISPOSAL_OF_FIXED_PROD_ASSETS | C21: 108 | D21: 75 | E21: 74 | F21: 40 | G21: 13 | H21: 15
A22: + Desp de activos intangibles | B22: CF_DISPOSAL_OF_INTANGIBLE_ASSETS | C22: 0 | D22: 0 | E22: 0 | F22: 0 | G22: 0 | H22: 0
A23: + Adq de fijos e intangibles | B23: ACQUIS_OF_FIXED_INTANG | C23: -1367 | D23: -1484 | E23: -1852 | F23: -2064 | G23: -2112 | H23: -1187
A24: + Adq de activos fijos prod | B24: CF_PURCHASE_OF_FIXED_PROD_ASSETS | C24: -1367 | D24: -1484 | E24: -1852 | F24: -2064 | G24: -2112 | H24: -1187
A25: + Adq de activos intangibles | B25: CF_ACQUISITION_OF_INTANG_ASSETS | C25: 0 | D25: 0 | E25: 0 | F25: 0 | G25: 0 | H25: 0
A26: + Cambio neto en inversiones LP | B26: NET_CHG_IN_LT_INVEST_DETAILED | C26: 0 | D26: 0 | E26: 0 | F26: 0 | G26: 0 | H26: 0
A27: + Dec en inversiones LP | B27: CF_DECR_INVEST | C27: 0 | D27: 0 | E27: 0 | F27: 0 | G27: 0 | H27: 0
A28: + Inc en inversiones LP | B28: CF_INCR_INVEST | C28: 0 | D28: 0 | E28: 0 | F28: 0 | G28: 0 | H28: 0
A29: + Efectivo neto de adq y div | B29: CF_NT_CSH_RCVD_PD_FOR_ACQUIS_DIV | C29: -2586 | D29: 385 | E29: 368 | F29: 3170 | G29: 3106 | H29: 2363
A30: + Efectivo por despojos | B30: CF_CASH_FOR_DIVESTITURES | C30: 2180 | D30: 458 | E30: 430 | F30: 3485 | G30: 3567 | H30: 2819
... A35: Efectivo de actividades de inversión | B35: CF_CASH_FROM_INV_ACT | C35: -2765 | D35: -763 | E35: -3349 | F35: 2524 | G35: -67 | H35: 2746
A37: Efectivo de actividades de financiación
A38: + Dividendos pagados | B38: CF_DVD_PAID | C38: -7252 | D38: -7616 | E38: -7952 | F38: -8359 | G38: -8779 | H38: -10971
A39: + Efectivo de (pagos) deuda | B39: PROC_FR_REPAYMNTS_BOR_DETAILED | C39: 228 | D39: -958 | E39: 1857 | F39: 2528 | G39: 13 | H39: -5086
A40: + Efectivo (recompra) de acciones | B40: PROC_FR_REPURCH_EQTY_DETAILED | C40: 591 | D40: -581 | E40: -1750 | F40: -1048 | G40: -433 | H40: -544
A41: + Aumento en capital | B41: CF_INCR_CAP_STOCK | C41: 702 | D41: 837 | E41: 539 | F41: 747 | G41: 313 | H41: 309
A42: + Baja en capital | B42: CF_DECR_CAP_STOCK | C42: -111 | D42: -1418 | E42: -2289 | F42: -1795 | G42: -746 | H42: -853
A43: + Otras actividades de financiación | B43: OTHER_FIN_AND_DEC_CAP | C43: -353 | D43: -1095 | E43: -465 | F43: -31 | G43: 1059 | H43: 1161
A44: + Efectivo neto de ops disc | B44: CF_NET_CASH_DISCONTINUED_OPS_FIN | C44: 0 | D44: 0 | E44: 0 | F44: 0 | G44: 0 | H44: 0
A45: Efectivo de actividades de financiación | B45: CFF_ACTIVITIES_DETAILED | C45: -6786 | D45: -10250 | E45: -8310 | F45: -6910 | G45: -8140 | H45: -15440
A47: Efecto de los tipos de cambio | B47: CF_EFFECT_FOREIGN_EXCHANGES | C47: -159 | D47: -205 | E47: -73 | F47: -623 | G47: 321 | H47: 244
A49: Cambios netos en el efectivo | B49: CF_NET_CHNG_CASH | C49: 2915 | D49: -200 | E49: -133 | F49: 1796 | G49: -478 | H49: 2181
A51: Efectivo pagado por impuestos | B51: CF_CASH_PAID_FOR_TAX | C51: 2168 | D51: 2403 | E51: 2580 | F51: 3262 | G51: 2873
A52: Efectivo pagado en intereses | B52: CF_ACT_CASH_PAID_FOR_INT_DEBT | C52: 738 | D52: 848 | E52: 1415 | F52: 1669 | G52: 1724
A54: Referencia
A55: EBITDA | B55: EBITDA | C55: 12102 | D55: 12566 | E55: 12836 | F55: 11429 | G55: 15217 | H55: 15509
A56: Margen EBITDA últimos 12M | B56: EBITDA_MARGIN | C56: 31.3077 | D56: 29.2205 | E56: 28.0544 | F56: 24.2855 | G56: 31.7411 | H56: 31.468631
A57: Efectivo neto desembolsado por adquisiciones | B57: CF_NET_CASH_PAID_FOR_AQUIS | C57: 4766 | D57: 73 | E57: 62 | F57: 315 | G57: 461 | H57: 456
A58: Flujo de caja libre | B58: CF_FREE_CASH_FLOW | C58: 11258 | D58: 9534 | E58: 9747 | F58: 4741 | G58: 5296 | H58: 12554
A59: Flujo de caja libre a empresa | B59: CF_FREE_CASH_FLOW_FIRM | C59: 12518.12 | D59: 10256.371 | E59: 11008.85 | F59: 6088.6039 | G59: 6654.2072 | H59: 13910.672
A60: Flujo libre de caja a capital | B60: FREE_CASH_FLOW_EQUITY | C60: 11594 | D60: 8651 | E60: 11678 | F60: 7309 | G60: 5322 | H60: 7483
A61: Flujo libre de caja por acción | B61: FREE_CASH_FLOW_PER_SH | C61: 2.609 | D61: 2.2029 | E61: 2.2547 | F61: 1.1003 | G61: 1.2308 | H61: 2.9175671
A62: Precio a flujo de caja libre | B62: PX_TO_FREE_CASH_FLOW | C62: 22.6942 | D62: 28.876 | E62: 26.1367 | F62: 56.5869 | G62: 56.8019 | H62: 26.330157
A63: Flujo de caja a beneficio neto | B63: CASH_FLOW_TO_NET_INC | C63: 1.2921 | D63: 1.1547 | E63: 1.0826 | F63: 0.6401 | G63: 0.5652 | H63: 0.51503568
A64: Fuente: Bloomberg

Sheet MODL
A1: Coca-Cola Co/The- Declaración financiera de empresa (Múltiples periodos)
A2: KO US Equity Periodicidad:A Divisa:USD Estimación Fuente:BST Fuente efectiva: Bloomberg
A3: En Millones de USD | D3: 2026 A (Fwd) | E3: 2027 A (Fwd) | F3: 2028 A (Fwd) | G3: 2029 A (Fwd) | H3: 2030 A (Fwd) | I3: 2031 A (Fwd) | J3: 2032 A (Fwd) | K3: 2033 A (Fwd) | L3: 2034 A (Fwd) | M3: 2035 A (Fwd)
A4: % 1 meses terminando | B4: Expresión de campo | C4: Campo calcrt | D4: 46387 | E4: 46752 | F4: 47118 | G4: 47483 | H4: 47848 | I4: 48213 | J4: 48579 | K4: 48944 | L4: 49309 | M4: 49674
A5: Highlights
A6: BPA estimados ajustados comparables | B6: IS_COMP_EPS_ADJUSTED_OLD | C6: IS900 | D6: 3.2695652 | E6: 3.4795652 | F6: 3.70375 | G6: 3.9525 | H6: 4.22 | I6: 4.5466667 | J6: 4.8433333 | K6: 5.1566667 | L6: 5.55 | M6: 5.935
A7: Est de ventas comparables | B7: IS_COMP_SALES | C7: IS902 | D7: 49085.5 | E7: 49992.636 | F7: 52572 | G7: 55061 | H7: 57724.25 | I7: 60486.5 | J7: 63401 | K7: 66377.25 | L7: 69878.667 | M7: 73289.667
A8: Ingreso | B8: SALES_REV_TURN | C8: IS010 | D8: 49028.213 | E8: 49942.983 | F8: 52682.796 | G8: 56304.173 | H8: 59176.064 | I8: 62571.752 | J8: 65872.025 | K8: 69350.256 | L8: 73016.283 | M8: 76880.501
A10: Tasa de crecimiento orgánico | B10: IS_ORGANIC_GROWTH_RATE | C10: IS950 | D10: 4.7258264 | E10: 4.6633719 | F10: 4.6689495 | G10: 4.2408925 | H10: 4.4995557 | I10: 4.5092981 | J10: 4.8022752 | K10: 4.281989 | L10: 4.54087 | M10: 4.5510235
A11: Cambio en ventas porcentual precio | B11: IS_PCT_SALES_CHANGE_PRICE | C11: IM762 | D11: 2.486402 | E11: 2.7216901 | F11: 2.6476573 | G11: 2.6090838 | H11: 2.5915584 | I11: 2.5917736 | J11: 2.5046925 | K11: 2.6103248 | L11: 2.592715 | M11: 2.5931229
A12: Cambio en ventas porcentual volumen | B12: IS_PCT_SALES_CHANGE_VOLUME | C12: IM763 | D12: 2.2991337 | E12: 1.8760072 | F12: 2.0212923 | G12: 1.6318087 | H12: 1.9079973 | I12: 1.9175245 | J12: 2.2975827 | K12: 1.6716642 | L12: 1.9481551 | M12: 1.9579006
A13: Volume Growth Percentage | B13: VOLUME_GROWTH_PERCENTAGE | C13: M6035 | D13: 2.2186818 | E13: 1.9003567 | F13: 1.8779694 | G13: 1.9139446 | H13: 1.9239302 | I13: 1.9339761 | J13: 1.9440811 | K13: 1.954244 | L13: 1.9644636 | M13: 1.9747384
A14: IS Sales Change - Currencies (%) | B14: IS_SALES_CHANGE_CURRENCIES_PCT | C14: IC056 | D14: 1.4544124 | E14: 0.058872843 | F14: 0
A15: IS Sales Change - Aquis and Divest (%) | B15: IS_SALES_CHG_ACQ_AND_DIVEST_PCT | C15: IC057 | D15: -4.2056105 | E15: -3.3554203 | F15: 0
A17: Business Revenue
A18: Bottling Investments | B18: IS_ADJ_REVENUE_COMP_BASIS_INCLUDING_INTERSEG | C18: IC602 | D18: 4547.8245 | E18: 2991.2172 | F18: 3407.1848 | G18: 3480.9578 | H18: 3665.6085 | I18: 3860.0748 | J18: 4064.8797 | K18: 4280.574 | L18: 4507.7376 | M18: 4746.9819
A19: Corporate | B19: IS_ADJ_REVENUE_COMP_BASIS_INCLUDING_INTERSEG | C19: IC602 | D19: 150.08836 | E19: 154.79571 | F19: 156.19083 | G19: 171.33711 | H19: 179.27499 | I19: 187.59268 | J19: 196.30905 | K19: 205.44396 | L19: 215.01827 | M19: 225.05396
A20: Eliminations | B20: SALES_REV_TURN | C20: IS010 | D20: -980.75922 | E20: -878.78021 | F20: -967.71507 | G20: -780.26779 | H20: -820.79512 | I20: -863.46361 | J20: -908.38868 | K20: -955.6921 | L20: -1005.5024 | M20: -1057.9551
A21: Regional Revenue
A22: Europe, Middle East, & Africa | B22: IS_ADJ_REVENUE_COMP_BASIS_INCLUDING_INTERSEG | C22: IC602 | D22: 12228.31 | E22: 12807.234 | F22: 13275.826 | G22: 13870.206 | H22: 14458.353 | I22: 15071.516 | J22: 15738.958 | K22: 16386.003 | L22: 17081.262 | M22: 17806.112
A23: Latin America | B23: SALES_REV_TURN | C23: IS010 | D23: 6858.39 | E23: 7327.7213 | F23: 7814.0493 | G23: 8301.7422 | H23: 8862.3368 | I23: 9460.8197 | J23: 10108.896 | K23: 10778.33 | L23: 11506.449 | M23: 12283.798
A24: North America | B24: IS_ADJ_REVENUE_COMP_BASIS_INCLUDING_INTERSEG | C24: IC602 | D24: 20552.014 | E24: 21420.587 | F24: 22437.034 | G24: 24115.795 | H24: 25321.585 | I24: 26587.664 | J24: 27917.047 | K24: 29312.9 | L24: 30778.545 | M24: 32317.472
A25: Asia Pacific | B25: IS_ADJ_REVENUE_COMP_BASIS_INCLUDING_INTERSEG | C25: IC602 | D25: 5779.3126 | E25: 6053.5422 | F25: 6267.5138 | G25: 6793.3604 | H25: 7164.8467 | I25: 7556.6366 | J25: 7994.723 | K25: 8421.0042 | L25: 8881.5204 | M25: 9367.2076
A27: Porcentaje de margen bruto comparable | B27: IS_COMP_GROSS_MARGIN_PERCENTAGE | C27: IM092 | D27: 62.070871 | E27: 62.810797 | F27: 63.205139 | G27: 62.122064 | H27: 62.244621 | I27: 62.367179 | J27: 62.505573 | K27: 62.627162 | L27: 62.749717 | M27: 62.872272
A28: EBIT comparable | B28: IS_COMPARABLE_EBIT | C28: IM132 | D28: 16000.842 | E28: 16980.316 | F28: 18079.714 | G28: 19069 | H28: 20205.25 | I28: 21678 | J28: 22926.667 | K28: 24247.667 | L28: 26230 | M28: 27835.5
A29: Estimación de gastos de capital comparables | B29: HEADLINE_CAPEX | C29: F1705 | D29: -2201.7143 | E29: -2148.3571 | F29: -2185.3636 | G29: -2127.5 | H29: -2166.5 | I29: -2327.3333 | J29: -2440.3333 | K29: -2554.6667 | L29: -2815.5 | M29: -2954.5
A31: Company Operating Metrics
A33: Company-Level Industry Statistics
A34: Tasa de crecimiento orgánico | B34: IS_ORGANIC_GROWTH_RATE | C34: IS950 | D34: 4.7258264 | E34: 4.6633719 | F34: 4.6689495 | G34: 4.2408925 | H34: 4.4995557 | I34: 4.5092981 | J34: 4.8022752 | K34: 4.281989 | L34: 4.54087 | M34: 4.5510235 | N34: =+AVERAGE(D34:M34) -> 4.5484052
A35: Europe, Middle East & Africa | B35: IS_ORGANIC_GROWTH_RATE | C35: IS950 | D35: 5.795102 | E35: 4.5261133 | F35: 4.5518364 | G35: 3.7190631 | H35: 3.9820309 | I35: 3.9818125 | J35: 4.3566416 | K35: 3.7197778 | L35: 3.9824571 | M35: 3.9822394 | N35: =+AVERAGE(D35:M35) -> 4.2597074
A36: Latin America | B36: IS_ORGANIC_GROWTH_RATE | C36: IS950 | D36: 4.5139482 | E36: 6.5433257 | F36: 6.5 | G36: =+F36 -> 6.5 | H36: =+G36 -> 6.5 | I36: =+H36 -> 6.5 | J36: =+I36 -> 6.5 | K36: =+J36 -> 6.5 | L36: =+K36 -> 6.5 | M36: =+L36 -> 6.5 | N36: =+AVERAGE(D36:M36) -> 6.3057274
A37: North America | B37: IS_ORGANIC_GROWTH_RATE | C37: IS950 | D37: 5.1145989 | E37: 4.2054848 | F37: 4.3643297 | G37: 4.255804 | H37: 4.3816365 | I37: 4.3815331 | J37: 4.4692868 | K37: 4.2560639 | L37: 4.3818392 | M37: 4.3817359 | N37: =+AVERAGE(D37:M37) -> 4.4192313
A38: Asia Pacific | B38: IS_ORGANIC_GROWTH_RATE | C38: IS950 | D38: 1.6135375 | E38: 4.0113099 | F38: 4.6312062 | G38: 5.1487102 | H38: 5.4339401 | I38: 5.4336071 | J38: 6.1215387 | K38: 5.1500027 | L38: 5.4345872 | M38: 5.4342565 | N38: =+AVERAGE(D38:M38) -> 4.8412696
A39: Bottling Investments | B39: IS_ORGANIC_GROWTH_RATE | C39: IS950 | D39: 4.7353967 | E39: 4.8955426 | F39: 5.2 | G39: 5 | H39: 5 | I39: 5 | J39: 5 | K39: 5 | L39: 5 | M39: 5
A41: Cambio en ventas porcentual precio | B41: IS_PCT_SALES_CHANGE_PRICE | C41: IM762 | D41: 2.486402 | E41: 2.7216901 | F41: 2.6476573 | G41: 2.6090838 | H41: 2.5915584 | I41: 2.5917736 | J41: 2.5046925 | K41: 2.6103248 | L41: 2.592715 | M41: 2.5931229
A42: Europe, Middle East & Africa | B42: IS_PCT_SALES_CHANGE_PRICE | C42: IM762 | D42: 4.1898946 | E42: 2.4721553 | F42: 2.5714286 | G42: 2.75 | H42: 2.75 | I42: 2.75 | J42: 2.75 | K42: 2.75 | L42: 2.75 | M42: 2.75
A43: Latin America | B43: IS_PCT_SALES_CHANGE_PRICE | C43: IM762 | D43: 2.4595365 | E43: 4.3052706 | F43: 4.1666667 | G43: 4.25 | H43: 4.25 | I43: 4.25 | J43: 4.25 | K43: 4.25 | L43: 4.25 | M43: 4.25
A44: North America | B44: IS_PCT_SALES_CHANGE_PRICE | C44: IM762 | D44: 2.4441447 | E44: 2.6896294 | F44: 2.4583333 | G44: 2.875 | H44: 2.875 | I44: 2.875 | J44: 2.875 | K44: 2.875 | L44: 2.875 | M44: 2.875
A45: Asia Pacific | B45: IS_PCT_SALES_CHANGE_PRICE | C45: IM762 | D45: -2.3913584 | E45: 1.8238133 | F45: 2 | G45: 2.25 | H45: 2.25 | I45: 2.25 | J45: 2.25 | K45: 2.25 | L45: 2.25 | M45: 2.25
A46: Bottling Investments | B46: IS_PCT_SALES_CHANGE_PRICE | C46: IM762 | D46: 0.58220357 | E46: 2.0562719 | F46: 2.4166667 | G46: 2.75 | H46: 2.75 | I46: 2.75 | J46: 2.75 | K46: 2.75 | L46: 2.75 | M46: 2.75
A48: Cambio en ventas porcentual volumen | B48: IS_PCT_SALES_CHANGE_VOLUME | C48: IM763 | D48: 2.2991337 | E48: 1.8760072 | F48: 2.0212923 | G48: 1.6318087 | H48: 1.9079973 | I48: 1.9175245 | J48: 2.2975827 | K48: 1.6716642 | L48: 1.9481551 | M48: 1.9579006
A49: Europe, Middle East & Africa | B49: IS_PCT_SALES_CHANGE_VOLUME | C49: IM763 | D49: 1.8853465 | E49: 1.8797658 | F49: 1.747026 | G49: 1.3595316 | H49: 1.4910155 | I49: 1.4909063 | J49: 1.6783208 | K49: 1.3598889 | L49: 1.4912286 | M49: 1.4911197
A50: Latin America | B50: IS_PCT_SALES_CHANGE_VOLUME | C50: IM763 | D50: 2.2121029 | E50: 2.5656242 | F50: 2.4702097 | G50: 2.3752253 | H50: 2.5064485 | I50: 2.5062672 | J50: 2.6016905 | K50: 2.375707 | L50: 2.5068041 | M50: 2.5066228
A51: North America | B51: IS_PCT_SALES_CHANGE_VOLUME | C51: IM763 | D51: 2.7632415 | E51: 1.5353537 | F51: 1.8257583 | G51: 1.380804 | H51: 1.5066365 | I51: 1.5065331 | J51: 1.5942868 | K51: 1.3810639 | L51: 1.5068392 | M51: 1.5067359
A52: Asia Pacific | B52: IS_PCT_SALES_CHANGE_VOLUME | C52: IM763 | D52: 4.4111758 | E52: 2.35165 | F52: 2.5937187 | G52: 3.0743551 | H52: 3.2169701 | I52: 3.2168035 | J52: 3.5607694 | K52: 3.0750014 | L52: 3.2172936 | M52: 3.2171282
... A60: Bottling Investment | B60: VOLUME_GROWTH_PERCENTAGE | C60: M6035 | D60: 2.326616 | E60: 2.8571429 | F60: 2.6 | G60: 2 | H60: 2 | I60: 2 | J60: 2 | K60: 2 | L60: 2 | M60: 2
A61: Sparkling Soft Drinks | B61: VOLUME_GROWTH_PERCENTAGE | C61: M6035
A62: Trademark Coca-Cola | B62: VOLUME_GROWTH_PERCENTAGE | C62: M6035
A63: Coca-Cola Zero Sugar | B63: VOLUME_GROWTH_PERCENTAGE | C63: M6035
A64: Sparkling Flavors | B64: VOLUME_GROWTH_PERCENTAGE | C64: M6035
A65: Juice, Dairy, & Plant-Based Beverages | B65: VOLUME_GROWTH_PERCENTAGE | C65: M6035
A66: Water, Sports, Coffee and Tea | B66: VOLUME_GROWTH_PERCENTAGE | C66: M6035
A67: Water | B67: VOLUME_GROWTH_PERCENTAGE | C67: M6035
A68: Sports Drinks | B68: VOLUME_GROWTH_PERCENTAGE | C68: M6035
A69: Coffee | B69: VOLUME_GROWTH_PERCENTAGE | C69: M6035
A70: Tea | B70: VOLUME_GROWTH_PERCENTAGE | C70: M6035
A72: IS Sales Change - Currencies (%) | B72: IS_SALES_CHANGE_CURRENCIES_PCT | C72: IC056 | D72: 1.4544124 | E72: 0.058872843 | F72: 0
A73: Europe, Middle East & Africa | B73: IS_SALES_CHANGE_CURRENCIES_PCT | C73: IC056 | D73: 2.9870618 | E73: 0.06271417
A74: Latin America | B74: IS_SALES_CHANGE_CURRENCIES_PCT | C74: IC056 | D74: 3.6264314 | E74: 0.44824431
A75: North America | B75: IS_SALES_CHANGE_CURRENCIES_PCT | C75: IC056
A76: Asia Pacific | B76: IS_SALES_CHANGE_CURRENCIES_PCT | C76: IC056 | D76: 0.53642816 | E76: 0.010153699
A77: Bottling Investments | B77: IS_SALES_CHANGE_CURRENCIES_PCT | C77: IC056 | D77: 2.6532632 | E77: -0.12833038
A79: IS Sales Change - Aquis and Divest (%) | B79: IS_SALES_CHG_ACQ_AND_DIVEST_PCT | C79: IC057 | D79: -4.2056105 | E79: -3.3554203 | F79: 0
A80: Europe, Middle East & Africa | B80: IS_SALES_CHG_ACQ_AND_DIVEST_PCT | C80: IC057 | D80: -7.9276131 | E80: -4.0950026
A81: Latin America | B81: IS_SALES_CHG_ACQ_AND_DIVEST_PCT | C81: IC057
A82: North America | B82: IS_SALES_CHG_ACQ_AND_DIVEST_PCT | C82: IC057
A83: Asia Pacific | B83: IS_SALES_CHG_ACQ_AND_DIVEST_PCT | C83: IC057 | D83: -0.875 | E83: 0
A84: Bottling Investments | B84: IS_SALES_CHG_ACQ_AND_DIVEST_PCT | C84: IC057 | D84: -28.465323 | E84: -40.319509
A86: Operating Income - CC Growth (%)
A87: Europe, Middle East & Africa | B87: IS_ADJ_OP_INC_GRWTH_PCT_CHG_IN_CC | C87: IM701 | D87: 7.1761316 | E87: 4.6650619 | F87: 4.5656692
A88: Latin America | B88: IS_ADJ_OP_INC_GRWTH_PCT_CHG_IN_CC | C88: IM701 | D88: 3.9473962 | E88: 9.4048213 | F88: 9.7210234
A89: North America | B89: IS_ADJ_OP_INC_GRWTH_PCT_CHG_IN_CC | C89: IM701 | D89: 6.0733455 | E89: 6.4221057 | F89: 5.7699924 | G89: 5.25 | H89: 5 | I89: 5 | J89: 5 | K89: 5 | L89: 5 | M89: 5
A90: Asia Pacific | B90: IS_ADJ_OP_INC_GRWTH_PCT_CHG_IN_CC | C90: IM701 | D90: -4.5150385 | E90: 10.848443 | F90: 6.6897038
A91: Bottling Investments | B91: IS_ADJ_OP_INC_GRWTH_PCT_CHG_IN_CC | C91: IM701 | D91: 21.7277 | E91: 8.2010782
A93: Prior Disclosures
A94: Global Ventures Organic Growth | B94: IS_ORGANIC_GROWTH_RATE | C94: IS950
A95: Global Ventures Price/Mix | B95: IS_PCT_SALES_CHANGE_PRICE | C95: IM762
A96: Global Ventures Change in Concentrate Revenue | B96: IS_PCT_SALES_CHANGE_VOLUME | C96: IM763
A97: Global Ventures Unit Case Volume | B97: VOLUME_GROWTH_PERCENTAGE | C97: M6035
A98: Global Ventures FX Impact | B98: IS_SALES_CHANGE_CURRENCIES_PCT | C98: IC056
A99: Global Ventures M&A Impact | B99: IS_SALES_CHG_ACQ_AND_DIVEST_PCT | C99: IC057
A100: Global Ventures Operating Income CC | B100: IS_ADJ_OP_INC_GRWTH_PCT_CHG_IN_CC | C100: IM701
A102: Business Breakdown
A103: Bottling Investments
A104: Net Operating Revenue | B104: IS_ADJ_REVENUE_COMP_BASIS_INCLUDING_INTERSEG | C104: IC602 | D104: 4547.8245 | E104: 2991.2172 | F104: 3407.1848 | G104: 3480.9578 | H104: 3665.6085 | I104: 3860.0748 | J104: 4064.8797 | K104: 4280.574 | L104: 4507.7376 | M104: 4746.9819
A105: As % of Revenue | B105: IS_PERCENTAGE_OF_REVENUE | C105: IC214 | D105: 8.2368739 | E105: 4.6620666 | F105: 4.6354881
A106: GAAP Operating Income | B106: IS_OPER_INC | C106: IS033 | D106: 482.86485 | E106: 396.06765 | F106: 415.073
A107: Adjusted Operating Income | B107: IS_ADJ_EBIT_OP_INC_AS_REPORTED | C107: IS922 | D107: 400.11982 | E107: 283.01937 | F107: 326.42239 | G107: 368.3056 | H107: 394.733 | I107: 422.95618 | J107: 453.0929 | K107: 485.26846 | L107: 519.61617 | M107: 556.27783
A108: Operating Margin (%) | B108: CB_IS_OPERATING_MARGIN | C108: IC231 | D108: 8.7078806 | E108: 8.9842082 | F108: 8.9649419 | G108: 10.206226 | H108: 10.371663 | I108: 10.537486 | J108: 10.703698 | K108: 10.870302 | L108: 11.037303 | M108: 11.204703
A110: Corporate
A111: Net Operating Revenue | B111: IS_ADJ_REVENUE_COMP_BASIS_INCLUDING_INTERSEG | C111: IC602 | D111: 150.08836 | E111: 154.79571 | F111: 156.19083 | G111: 171.33711 | H111: 179.27499 | I111: 187.59268 | J111: 196.30905 | K111: 205.44396 | L111: 215.01827 | M111: 225.05396
A112: As % of Revenue | B112: IS_PERCENTAGE_OF_REVENUE | C112: IC214 | D112: 0.29826174 | E112: 0.2984991 | F112: 0.28981412
A113: GAAP Operating Income | B113: IS_OPER_INC | C113: IS033 | D113: -1386.8951 | E113: -1985.2011 | F113: -2287.2946 | G113: -1378.7762 | H113: -1390.8653 | I113: -1400.485 | J113: -1407.336 | K113: -1411.0927 | L113: -1411.4023 | M113: -1407.8818
A114: Adjusted Operating Income | B114: IS_ADJ_EBIT_OP_INC_AS_REPORTED | C114: IS922 | D114: -1569.5974 | E114: -1542.7238 | F114: -1638.2996 | G114: -1518.7143 | H114: -1562.0785 | I114: -1605.8874 | J114: -1650.0669 | K114: -1694.5332 | L114: -1739.1924 | M114: -1783.9393
A115: Capital Expenditures | B115: IS_CAPEX_AS_REPORTED | C115: IM168
A117: Eliminations
A118: Net Operating Revenue | B118: SALES_REV_TURN | C118: IS010 | D118: -980.75922 | E118: -878.78021 | F118: -967.71507 | G118: -780.26779 | H118: -820.79512 | I118: -863.46361 | J118: -908.38868 | K118: -955.6921 | L118: -1005.5024 | M118: -1057.9551
A120: Prior Disclosures
A121: Global Ventures
A122: Net Operating Revenue | B122: IS_ADJ_REVENUE_COMP_BASIS_INCLUDING_INTERSEG | C122: IC602
...

Sheet RV
A1: Ticker | B1: Name | C1: Cap mercado (USD) | D1: Últ prc (USD) | E1: Chg Pct 1D | F1: Chg Pct 1M | G1: Rev - 1 Yr Gr:Y | H1: BPA - Cr 1 añ:A | I1: P/E | J1: ROE | K1: Dvd 12M Yld
A2: None (14 securities)
A3: Median | B3: Median | C3: 9843.5683 | D3: 56.205 | E3: -1.6000485 | F3: -5.5352465 | G3: 2.3694162 | H3: 5.053227 | I3: 16.934872 | J3: 23.509989 | K3: 2.9685006
A4: KO US Equity | B4: COCA-COLA CO/THE | C4: 330516.7 | D4: 76.82 | E4: -2.463179 | F4: -2.115193 | G4: 2.4841674 | H4: 4.8210751 | I4: 23.566911 | J4: 46.98922 | K4: 2.6812442
A5: COKE US Equity | B5: COCA-COLA CONSOLIDATED INC | C5: 11333.902 | D5: 170.27 | E5: -3.986692 | F5: -20.95172 | G5: 4.7587321 | H5: 5.5924336 | I5: 20.781909 | J5: #N/A N/A | K5: 0.58730252
A6: COCO US Equity | B6: VITA COCO CO INC/THE | C6: 4225.1933 | D6: 73.98 | E6: -1.596169 | F6: 9.131139 | G6: 18.171441 | H6: 11.143794 | I6: 52.715927 | J6: 26.965987 | K6: #N/A N/A
A7: FIZZ US Equity | B7: NATIONAL BEVERAGE CORP | C7: 3251.8429 | D7: 34.73 | E7: -3.339827 | F7: -0.5440956 | G7: 0.81061078 | H7: 5.2853789 | I7: 17.278263 | J7: 38.004004 | K7: #N/A N/A
A8: MNST US Equity | B8: MONSTER BEVERAGE CORP | C8: 86592.838 | D8: 88.54 | E8: -0.5615454 | F8: 16.80738 | G8: 10.698854 | H8: 23.957696 | I8: 41.669824 | J8: 27.363237 | K8: #N/A N/A
A9: KDP US Equity | B9: KEURIG DR PEPPER INC | C9: 40898.418 | D9: 30.06 | E9: -1.603928 | F9: 3.941908 | G9: 8.1558205 | H9: 5.8405781 | I9: 16.317313 | J9: 10.105791 | K9: 3.0605456
A10: PRMB US Equity | B10: PRIMO BRANDS CORP | C10: 8353.2343 | D10: 23.02 | E10: -4.836709 | F10: 13.56684 | G10: 29.335274 | H10: 46.807996 | I10: 24.949711 | J10: 10.897517 | K10: 1.9113814
A11: CELH US Equity | B11: CELSIUS HOLDINGS INC | C11: 7094.02 | D11: 27.75 | E11: -7.530823 | F11: -17.2136 | G11: 85.542442 | H11: 111.21406 | I11: 16.591482 | J11: 43.742309 | K11: #N/A N/A
A12: PEP US Equity | B12: PEPSICO INC | C12: 194286.12 | D12: 142.15 | E12: -0.2736074 | F12: -8.31398 | G12: 2.254665 | H12: -2.2267488 | I12: 17.422693 | J12: 56.262748 | K12: 4.0432641
A13: MGPI US Equity | B13: MGP INGREDIENTS INC | C13: 347.71003 | D13: 16.27 | E13: -0.1227747 | F13: -18.52779 | G13: -23.769764 | H13: -48.620117 | I13: 3.4836328 | J13: 14.174299 | K13: 2.9502151
A14: STZ US Equity | B14: CONSTELLATION BRANDS INC-A | C14: 23725.676 | D14: 137.78 | E14: 1.757755 | F14: -8.024034 | G14: -10.478318 | H14: -34.789629 | I14: 13.779376 | J14: 23.509989 | K14: 2.9685006
A15: BF/B US Equity | B15: BROWN-FORMAN CORP-CLASS B | C15: 11820.085 | D15: 25.46 | E15: 2.827141 | F15: -3.046459 | G15: -1.1823899 | H15: -11.636811 | I15: 14.272172 | J15: 21.336875 | K15: 3.5938728
A16: TAP US Equity | B16: MOLSON COORS BEVERAGE CO - B | C16: 7258.1808 | D16: 38.43 | E16: -0.4919731 | F16: -8.912062 | G16: -4.1816462 | H16: -13.117082 | I16: 3.7445535 | J16: 17.53394 | K16: 4.9440541
A17: SAM US Equity | B17: BOSTON BEER COMPANY INC-A | C17: 1677.3972 | D17: 161.08 | E17: -1.636541 | F17: -21.90061 | G17: -2.3812102 | H17: 2.380316 | I17: 15.795121 | J17: 14.150705 | K17: #N/A N/A
